Workbook
Name _1925165: #REF!
Name _81: #REF!
Name _RR2: [12]RentRoll!$A$69:$Y$129
Name _SF1: #REF!
Name _SF2: [13]Assumptions!#REF!
Name a: #REF!
Name ACCOUNTING_2: "_($* #,##0.00_);_($* (#,##0.00);_($* " & """'-""" & "_);_(@_)"
Name AfterFee: #REF!
Name Age_Restricted_Housing_Type: [18]Dropdowns!$AW$3:$AW$6
Name AMORT_PERIOD: [19]Inputs!$I$24
Name ANALYSIS_END_DATE: [19]Inputs!$I$50
Name ANALYSIS_START: [19]Inputs!$I$14
Name Applicable_Index_Type: [18]Dropdowns!$M$3:$M$15
Name Assignment: OFFSET([21]T12!$O$18,,,COUNTA([21]T12!$O:$O),1)
Name Assumptions: #REF!
Name base: [23]Salaries!$P$4
Name baseburden: [23]Salaries!$S$134
Name baseperc: [23]Salaries!$Q$4
Name BeforeFee: #REF!
Name Begin_Clear: #REF!
Name Begin_Table: #REF!
Name bld_stories: [24]Instruction!$C$57:$C$72
Name bld_type_list: [24]Lookup!$C$805:$C$809
Name bld_type_start: [24]Lookup!$C$805
Name BlindUW: [25]ASSUMPTIONS!$C$49
Name Bond_Property_Type: [18]Dropdowns!$AT$3:$AT$5
Name Bond_Type: [18]Dropdowns!$AQ$3:$AQ$6
Name Bond_Variable_Rate_Index: [18]Dropdowns!$AY$3:$AY$12
Name Borrower_Principal_Role: [18]Dropdowns!$U$3:$U$14
Name building_total: [24]Instruction!$K$18
Name building_types: [24]Lookup!$W$493:$W$497
Name burden: [23]Salaries!$M$4
Name burden_tbl: [27]Salaries!#REF!
Name CAcct: #REF!
Name CAP_INCREMENT: '[28]Valuation Summary-Output'!#REF!
Name Capmark_fund: #REF!
Name cdsConforming: '[18]ASR Dropdowns'!$AD$3:$AD$5
Name cdsConstructionTypes: '[18]ASR Dropdowns'!$I$3:$I$11
Name cdsEntityTypes: '[18]ASR Dropdowns'!$AB$3:$AB$6
Name cdsExteriorFinishes: '[18]ASR Dropdowns'!$L$3:$L$16
Name cdsLeaseTypes: '[18]ASR Dropdowns'!$A$3:$A$8
Name cdsOpStmntColumns: [18]IandE!#REF!
Name cdsOwnershipTypes: '[18]ASR Dropdowns'!$Z$3:$Z$5
Name cdsRoofTypes: '[18]ASR Dropdowns'!$O$3:$O$16
Name cdsSeismicZones: '[18]ASR Dropdowns'!$R$3:$R$7
Name cdsYesNo: '[18]ASR Dropdowns'!$E$3:$E$5
Name cdsYesNoNA: '[18]ASR Dropdowns'!$G$3:$G$6
Name cdsYesNoPlus: '[18]ASR Dropdowns'!$C$3:$C$8
Name CHeader: #REF!
Name Clear_Range: #REF!
Name client_address: [24]Instruction!$J$10
Name client_address_2: [24]Instruction!$J$11
Name client_name: [24]Instruction!$J$9
Name Clients: [24]Lookup!$A$344:$M$468
Name climate_zone: [24]Energy_Audit_Data!$C$127
Name CommUnits: OFFSET([25]ASSUMPTIONS!$B$66,,,COUNT([25]ASSUMPTIONS!$B$66:$B$75),)
Name ConditionList: [24]Lookup!$U$583:$U$593
Name Construction_Term: [18]Dropdowns!$AV$3:$AV$5
Name Contract_Rent: '[29] Rent Roll-Input'!$G$5:$G$304
Name COST_OF_SALE: [19]Inputs!$I$49

Sheet Service Fee Calculator
B2: Assumable Loan Info | O2: New Loan Info | T2: Service Fee | U2: Matthews Split
B3: Original Loan Balance | C3: ='[29]Proforma-Input'!E113 -> 0 | O3: New Loan Balance | P3: 9700000 | S3: Year 1 | T3: =SUM(AA16:AA27) -> 9645.1116 | U3: =SUM(AB16:AB27) -> 2411.2779
B4: Existing Loan Balance | C4: ='[29]Proforma-Input'!E114 -> 0 | O4: Interest Rate | P4: 0.068 | S4: Year 2 | T4: =SUM(AA28:AA39) -> 9538.8675 | U4: =SUM(AB28:AB39) -> 2384.7169
B5: Interest Rate | C5: ='[29]Proforma-Input'!K113 -> 0 | O5: Amortization (In Years) | P5: 30 | S5: Year 3 | T5: =SUM(AA40:AA51) -> 9425.1694 | U5: =SUM(AB40:AB51) -> 2356.2923
B6: Amortization (In Years) | C6: ='[29]Proforma-Input'!K110 -> 0 | O6: Term(Years) | P6: 5 | S6: Year 4 | T6: =SUM(AA52:AA63) -> 9303.4942 | U6: =SUM(AB52:AB63) -> 2325.8736
B7: Remaining Term in Months | C7: ='[29]Optimistic Return Calculation'!E54 -> 0 | O7: Monthly Payment | P7: =PMT(P4/12,P5*12,-P3,0) -> 63236.743 | S7: Year 5 | T7: =SUM(AA64:AA75) -> 9173.2823 | U7: =SUM(AB64:AB75) -> 2293.3206
B8: Monthly Payment | C8: ='[29]Proforma-Input'!K114 -> 0 | N8: Yes | O8: I/O(Monthly): | P8: 0 | Q8: Total(Term)
B9: Final Payment Date | C9: =IFERROR('[29]Proforma-Input'!E111+(C7*30),"-") -> - | O9: Service Fee | P9: 0.001 | Q9: =SUMIFS($AA$15:$AA$374, $Q$15:$Q$374, "<=" & 12 * $P$6) -> 47135.01
B10: IO: | C10: =IFERROR('[29]Proforma-Input'!K116*12,"-") -> 0 | D10: =IF(C10>0,"Yes","No") -> No | O10: Matthews Split | P10: 0.25 | Q10: =SUMIFS($AB$15:$AB$374, $Q$15:$Q$374, "<=" & 12 * $P$6) -> 11783.753
C13: Assumable Loan Table | P13: Loan Calculations
B14: Month | C14: Year | D14: # of Months | E14: Month/Year | F14: Beg. Balance | G14: Payment | H14: Rate | I14: Interest | J14: Principal | K14: End Balance | L14: Interest/Year | M14: Principal/Year | O14: Month | P14: Year | Q14: # of Months | R14: Month/Year | S14: Beg. Balance | T14: Payment | U14: Rate | V14: Interest | W14: Principal | X14: End Balance | Y14: Cumulative Interest | Z14: Cumulative Principal | AA14: Service Fee | AB14: Matthews Split | AC14: Interest/Year | AD14: Principal/Year | AF14: Input Data
B15: ='[29]Proforma-Input'!$E$111 -> - | C15: 1 | D15: 1 | E15: 1 | F15: =IF('[29]Proforma-Input'!$C$108="Yes",$C$4,) -> 0 | G15: =IF(AND($D$10="Yes",D15<=$C$10),I15,IF(F15>0,$C$8,)) -> 0 | H15: =IF('[29]Proforma-Input'!$C$108="Yes",C5,) -> 0 | I15: =(H15/12)*F15 -> 0 | J15: =IF(D15=$C$7,0,G15-I15) -> 0 | K15: =IFERROR(F15-J15,) -> 0 | L15: =IF(C15>0,SUM(I15:I26),"-") -> 0 | M15: =IF(C15>0,SUM(J15:J26),"-") -> 0 | O15: =NOW() -> 45933.485 | P15: 1 | Q15: =IF(S15>0,1,) -> 1 | R15: 1 | S15: =IF('[29]Proforma-Input'!$C$108="No",$P$3,IF(AF15="True",$P$3,)) -> 9700000 | T15: =IF(AND($N$8="Yes",Q15<=$P$8),V15,IF(S15>0,$P$7,)) -> 63236.743 | U15: =$P$4 -> 0.068 | V15: =IF(S15>0,U15/12*S15,0) -> 54966.667 | W15: =T15-V15 -> 8270.0766 | X15: =S15-W15 -> 9691729.9 | Y15: =IF(Q15=1,V15,Y14+V15) -> 54966.667 | Z15: =IF(Q15=1,W15,Z14+W15) -> 8270.0766 | AA15: =$P$9*S15/12 -> 808.33333 | AB15: =$P$10*AA15 -> 202.08333 | AC15: =IF(P15>0,SUM(V15:V26),"-") -> 656447.82 | AD15: =IF(P15>0,SUM(W15:W26),"-") -> 102393.1 | AF15: =IF('[29]Proforma-Input'!$C$108="Yes",MONTH(O15)&YEAR(O15)=MONTH($C$9)&YEAR($C$9),0) -> 0 | AG15: 1
B16: =IFERROR(DATE(YEAR(B15),MONTH(B15)+1,DAY(B15)),"-") -> - | D16: 2 | E16: =1+E15 -> 2 | F16: =IFERROR(IF(B16<$C$9,IF('[29]Proforma-Input'!$C$108="Yes",K15,K15),0),) -> 0 | G16: =IFERROR(IF(D16=$C$7,K15,IF(AND($D$10="Yes",D16<=$C$10),I16,IF(F16>0,$C$8,))),) -> 0 | H16: =IFERROR(IF(B16<$C$9,IF('[29]Proforma-Input'!$C$108="Yes",H15,),0),) -> 0 | I16: =(H16/12)*F16 -> 0 | J16: =IF(D16=$C$7,0,G16-I16) -> 0 | K16: =IFERROR(F16-J16,) -> 0 | L16: =IF(C16>0,SUM(I16:I27),"-") -> - | M16: =IF(C16>0,SUM(J16:J27),"-") -> - | O16: =IFERROR(DATE(YEAR(O15),MONTH(O15)+1,DAY(O15)),"-") -> 45964 | Q16: =IF(S16>0,1+Q15,) -> 2 | R16: =1+R15 -> 2 | S16: =IF('[29]Proforma-Input'!$C$108="No",X15,IF(AF16=TRUE,$P$3,X15)) -> 9691729.9 | T16: =IF(AND($N$8="Yes",Q16<=$P$8),V16,IF(S16>0,$P$7,)) -> 63236.743 | U16: =$P$4 -> 0.068 | V16: =IF(S16>0,U16/12*S16,0) -> 54919.803 | W16: =T16-V16 -> 8316.9404 | X16: =S16-W16 -> 9683413 | Y16: =IF(Q16=1,V16,Y15+V16) -> 109886.47 | Z16: =IF(Q16=1,W16,Z15+W16) -> 16587.017 | AA16: =$P$9*S16/12 -> 807.64416 | AB16: =$P$10*AA16 -> 201.91104 | AC16: =IF(P16>0,SUM(V16:V27),"-") -> - | AD16: =IF(P16>0,SUM(W16:W27),"-") -> - | AF16: =IF('[29]Proforma-Input'!$C$108="Yes",MONTH(O16)&YEAR(O16)=MONTH($C$9)&YEAR($C$9),0) -> 0 | AG16: 1
B17: =IFERROR(DATE(YEAR(B16),MONTH(B16)+1,DAY(B16)),"-") -> - | D17: 3 | E17: =1+E16 -> 3 | F17: =IFERROR(IF(B17<$C$9,IF('[29]Proforma-Input'!$C$108="Yes",K16,K16),0),) -> 0 | G17: =IFERROR(IF(D17=$C$7,K16,IF(AND($D$10="Yes",D17<=$C$10),I17,IF(F17>0,$C$8,))),) -> 0 | H17: =IFERROR(IF(B17<$C$9,IF('[29]Proforma-Input'!$C$108="Yes",H16,),0),) -> 0 | I17: =(H17/12)*F17 -> 0 | J17: =IF(D17=$C$7,0,G17-I17) -> 0 | K17: =IFERROR(F17-J17,) -> 0 | L17: =IF(C17>0,SUM(I17:I28),"-") -> - | M17: =IF(C17>0,SUM(J17:J28),"-") -> - | O17: =IFERROR(DATE(YEAR(O16),MONTH(O16)+1,DAY(O16)),"-") -> 45994 | Q17: =IF(S17>0,1+Q16,) -> 3 | R17: =1+R16 -> 3 | S17: =IF('[29]Proforma-Input'!$C$108="No",X16,IF(AF17=TRUE,$P$3,X16)) -> 9683413 | T17: =IF(AND($N$8="Yes",Q17<=$P$8),V17,IF(S17>0,$P$7,)) -> 63236.743 | U17: =$P$4 -> 0.068 | V17: =IF(S17>0,U17/12*S17,0) -> 54872.674 | W17: =T17-V17 -> 8364.0697 | X17: =S17-W17 -> 9675048.9 | Y17: =IF(Q17=1,V17,Y16+V17) -> 164759.14 | Z17: =IF(Q17=1,W17,Z16+W17) -> 24951.087 | AA17: =$P$9*S17/12 -> 806.95108 | AB17: =$P$10*AA17 -> 201.73777 | AC17: =IF(P17>0,SUM(V17:V28),"-") -> - | AD17: =IF(P17>0,SUM(W17:W28),"-") -> - | AF17: =IF('[29]Proforma-Input'!$C$108="Yes",MONTH(O17)&YEAR(O17)=MONTH($C$9)&YEAR($C$9),0) -> 0 | AG17: 1
B18: =IFERROR(DATE(YEAR(B17),MONTH(B17)+1,DAY(B17)),"-") -> - | D18: 4 | E18: =1+E17 -> 4 | F18: =IFERROR(IF(B18<$C$9,IF('[29]Proforma-Input'!$C$108="Yes",K17,K17),0),) -> 0 | G18: =IFERROR(IF(D18=$C$7,K17,IF(AND($D$10="Yes",D18<=$C$10),I18,IF(F18>0,$C$8,))),) -> 0 | H18: =IFERROR(IF(B18<$C$9,IF('[29]Proforma-Input'!$C$108="Yes",H17,),0),) -> 0 | I18: =(H18/12)*F18 -> 0 | J18: =IF(D18=$C$7,0,G18-I18) -> 0 | K18: =IFERROR(F18-J18,) -> 0 | L18: =IF(C18>0,SUM(I18:I29),"-") -> - | M18: =IF(C18>0,SUM(J18:J29),"-") -> - | O18: =IFERROR(DATE(YEAR(O17),MONTH(O17)+1,DAY(O17)),"-") -> 46025 | Q18: =IF(S18>0,1+Q17,) -> 4 | R18: =1+R17 -> 4 | S18: =IF('[29]Proforma-Input'!$C$108="No",X17,IF(AF18=TRUE,$P$3,X17)) -> 9675048.9 | T18: =IF(AND($N$8="Yes",Q18<=$P$8),V18,IF(S18>0,$P$7,)) -> 63236.743 | U18: =$P$4 -> 0.068 | V18: =IF(S18>0,U18/12*S18,0) -> 54825.277 | W18: =T18-V18 -> 8411.4661 | X18: =S18-W18 -> 9666637.4 | Y18: =IF(Q18=1,V18,Y17+V18) -> 219584.42 | Z18: =IF(Q18=1,W18,Z17+W18) -> 33362.553 | AA18: =$P$9*S18/12 -> 806.25408 | AB18: =$P$10*AA18 -> 201.56352 | AC18: =IF(P18>0,SUM(V18:V29),"-") -> - | AD18: =IF(P18>0,SUM(W18:W29),"-") -> - | AF18: =IF('[29]Proforma-Input'!$C$108="Yes",MONTH(O18)&YEAR(O18)=MONTH($C$9)&YEAR($C$9),0) -> 0 | AG18: 1
B19: =IFERROR(DATE(YEAR(B18),MONTH(B18)+1,DAY(B18)),"-") -> - | D19: 5 | E19: =1+E18 -> 5 | F19: =IFERROR(IF(B19<$C$9,IF('[29]Proforma-Input'!$C$108="Yes",K18,K18),0),) -> 0 | G19: =IFERROR(IF(D19=$C$7,K18,IF(AND($D$10="Yes",D19<=$C$10),I19,IF(F19>0,$C$8,))),) -> 0 | H19: =IFERROR(IF(B19<$C$9,IF('[29]Proforma-Input'!$C$108="Yes",H18,),0),) -> 0 | I19: =(H19/12)*F19 -> 0 | J19: =IF(D19=$C$7,0,G19-I19) -> 0 | K19: =IFERROR(F19-J19,) -> 0 | L19: =IF(C19>0,SUM(I19:I30),"-") -> - | M19: =IF(C19>0,SUM(J19:J30),"-") -> - | O19: =IFERROR(DATE(YEAR(O18),MONTH(O18)+1,DAY(O18)),"-") -> 46056 | Q19: =IF(S19>0,1+Q18,) -> 5 | R19: =1+R18 -> 5 | S19: =IF('[29]Proforma-Input'!$C$108="No",X18,IF(AF19=TRUE,$P$3,X18)) -> 9666637.4 | T19: =IF(AND($N$8="Yes",Q19<=$P$8),V19,IF(S19>0,$P$7,)) -> 63236.743 | U19: =$P$4 -> 0.068 | V19: =IF(S19>0,U19/12*S19,0) -> 54777.612 | W19: =T19-V19 -> 8459.1311 | X19: =S19-W19 -> 9658178.3 | Y19: =IF(Q19=1,V19,Y18+V19) -> 274362.03 | Z19: =IF(Q19=1,W19,Z18+W19) -> 41821.684 | AA19: =$P$9*S19/12 -> 805.55312 | AB19: =$P$10*AA19 -> 201.38828 | AC19: =IF(P19>0,SUM(V19:V30),"-") -> - | AD19: =IF(P19>0,SUM(W19:W30),"-") -> - | AF19: =IF('[29]Proforma-Input'!$C$108="Yes",MONTH(O19)&YEAR(O19)=MONTH($C$9)&YEAR($C$9),0) -> 0 | AG19: 1
B20: =IFERROR(DATE(YEAR(B19),MONTH(B19)+1,DAY(B19)),"-") -> - | D20: 6 | E20: =1+E19 -> 6 | F20: =IFERROR(IF(B20<$C$9,IF('[29]Proforma-Input'!$C$108="Yes",K19,K19),0),) -> 0 | G20: =IFERROR(IF(D20=$C$7,K19,IF(AND($D$10="Yes",D20<=$C$10),I20,IF(F20>0,$C$8,))),) -> 0 | H20: =IFERROR(IF(B20<$C$9,IF('[29]Proforma-Input'!$C$108="Yes",H19,),0),) -> 0 | I20: =(H20/12)*F20 -> 0 | J20: =IF(D20=$C$7,0,G20-I20) -> 0 | K20: =IFERROR(F20-J20,) -> 0 | L20: =IF(C20>0,SUM(I20:I31),"-") -> - | M20: =IF(C20>0,SUM(J20:J31),"-") -> - | O20: =IFERROR(DATE(YEAR(O19),MONTH(O19)+1,DAY(O19)),"-") -> 46084 | Q20: =IF(S20>0,1+Q19,) -> 6 | R20: =1+R19 -> 6 | S20: =IF('[29]Proforma-Input'!$C$108="No",X19,IF(AF20=TRUE,$P$3,X19)) -> 9658178.3 | T20: =IF(AND($N$8="Yes",Q20<=$P$8),V20,IF(S20>0,$P$7,)) -> 63236.743 | U20: =$P$4 -> 0.068 | V20: =IF(S20>0,U20/12*S20,0) -> 54729.677 | W20: =T20-V20 -> 8507.0661 | X20: =S20-W20 -> 9649671.3 | Y20: =IF(Q20=1,V20,Y19+V20) -> 329091.71 | Z20: =IF(Q20=1,W20,Z19+W20) -> 50328.75 | AA20: =$P$9*S20/12 -> 804.84819 | AB20: =$P$10*AA20 -> 201.21205 | AC20: =IF(P20>0,SUM(V20:V31),"-") -> - | AD20: =IF(P20>0,SUM(W20:W31),"-") -> - | AF20: =IF('[29]Proforma-Input'!$C$108="Yes",MONTH(O20)&YEAR(O20)=MONTH($C$9)&YEAR($C$9),0) -> 0 | AG20: 1
B21: =IFERROR(DATE(YEAR(B20),MONTH(B20)+1,DAY(B20)),"-") -> - | D21: 7 | E21: =1+E20 -> 7 | F21: =IFERROR(IF(B21<$C$9,IF('[29]Proforma-Input'!$C$108="Yes",K20,K20),0),) -> 0 | G21: =IFERROR(IF(D21=$C$7,K20,IF(AND($D$10="Yes",D21<=$C$10),I21,IF(F21>0,$C$8,))),) -> 0 | H21: =IFERROR(IF(B21<$C$9,IF('[29]Proforma-Input'!$C$108="Yes",H20,),0),) -> 0 | I21: =(H21/12)*F21 -> 0 | J21: =IF(D21=$C$7,0,G21-I21) -> 0 | K21: =IFERROR(F21-J21,) -> 0 | L21: =IF(C21>0,SUM(I21:I32),"-") -> - | M21: =IF(C21>0,SUM(J21:J32),"-") -> - | O21: =IFERROR(DATE(YEAR(O20),MONTH(O20)+1,DAY(O20)),"-") -> 46115 | Q21: =IF(S21>0,1+Q20,) -> 7 | R21: =1+R20 -> 7 | S21: =IF('[29]Proforma-Input'!$C$108="No",X20,IF(AF21=TRUE,$P$3,X20)) -> 9649671.3 | T21: =IF(AND($N$8="Yes",Q21<=$P$8),V21,IF(S21>0,$P$7,)) -> 63236.743 | U21: =$P$4 -> 0.068 | V21: =IF(S21>0,U21/12*S21,0) -> 54681.47 | W21: =T21-V21 -> 8555.2728 | X21: =S21-W21 -> 9641116 | Y21: =IF(Q21=1,V21,Y20+V21) -> 383773.18 | Z21: =IF(Q21=1,W21,Z20+W21) -> 58884.023 | AA21: =$P$9*S21/12 -> 804.13927 | AB21: =$P$10*AA21 -> 201.03482 | AC21: =IF(P21>0,SUM(V21:V32),"-") -> - | AD21: =IF(P21>0,SUM(W21:W32),"-") -> - | AF21: =IF('[29]Proforma-Input'!$C$108="Yes",MONTH(O21)&YEAR(O21)=MONTH($C$9)&YEAR($C$9),0) -> 0 | AG21: 1
B22: =IFERROR(DATE(YEAR(B21),MONTH(B21)+1,DAY(B21)),"-") -> - | D22: 8 | E22: =1+E21 -> 8 | F22: =IFERROR(IF(B22<$C$9,IF('[29]Proforma-Input'!$C$108="Yes",K21,K21),0),) -> 0 | G22: =IFERROR(IF(D22=$C$7,K21,IF(AND($D$10="Yes",D22<=$C$10),I22,IF(F22>0,$C$8,))),) -> 0 | H22: =IFERROR(IF(B22<$C$9,IF('[29]Proforma-Input'!$C$108="Yes",H21,),0),) -> 0 | I22: =(H22/12)*F22 -> 0 | J22: =IF(D22=$C$7,0,G22-I22) -> 0 | K22: =IFERROR(F22-J22,) -> 0 | L22: =IF(C22>0,SUM(I22:I33),"-") -> - | M22: =IF(C22>0,SUM(J22:J33),"-") -> - | O22: =IFERROR(DATE(YEAR(O21),MONTH(O21)+1,DAY(O21)),"-") -> 46145 | Q22: =IF(S22>0,1+Q21,) -> 8 | R22: =1+R21 -> 8 | S22: =IF('[29]Proforma-Input'!$C$108="No",X21,IF(AF22=TRUE,$P$3,X21)) -> 9641116 | T22: =IF(AND($N$8="Yes",Q22<=$P$8),V22,IF(S22>0,$P$7,)) -> 63236.743 | U22: =$P$4 -> 0.068 | V22: =IF(S22>0,U22/12*S22,0) -> 54632.991 | W22: =T22-V22 -> 8603.7527 | X22: =S22-W22 -> 9632512.2 | Y22: =IF(Q22=1,V22,Y21+V22) -> 438406.17 | Z22: =IF(Q22=1,W22,Z21+W22) -> 67487.775 | AA22: =$P$9*S22/12 -> 803.42633 | AB22: =$P$10*AA22 -> 200.85658 | AC22: =IF(P22>0,SUM(V22:V33),"-") -> - | AD22: =IF(P22>0,SUM(W22:W33),"-") -> - | AF22: =IF('[29]Proforma-Input'!$C$108="Yes",MONTH(O22)&YEAR(O22)=MONTH($C$9)&YEAR($C$9),0) -> 0 | AG22: 1
B23: =IFERROR(DATE(YEAR(B22),MONTH(B22)+1,DAY(B22)),"-") -> - | D23: 9 | E23: =1+E22 -> 9 | F23: =IFERROR(IF(B23<$C$9,IF('[29]Proforma-Input'!$C$108="Yes",K22,K22),0),) -> 0 | G23: =IFERROR(IF(D23=$C$7,K22,IF(AND($D$10="Yes",D23<=$C$10),I23,IF(F23>0,$C$8,))),) -> 0 | H23: =IFERROR(IF(B23<$C$9,IF('[29]Proforma-Input'!$C$108="Yes",H22,),0),) -> 0 | I23: =(H23/12)*F23 -> 0 | J23: =IF(D23=$C$7,0,G23-I23) -> 0 | K23: =IFERROR(F23-J23,) -> 0 | L23: =IF(C23>0,SUM(I23:I34),"-") -> - | M23: =IF(C23>0,SUM(J23:J34),"-") -> - | O23: =IFERROR(DATE(YEAR(O22),MONTH(O22)+1,DAY(O22)),"-") -> 46176 | Q23: =IF(S23>0,1+Q22,) -> 9 | R23: =1+R22 -> 9 | S23: =IF('[29]Proforma-Input'!$C$108="No",X22,IF(AF23=TRUE,$P$3,X22)) -> 9632512.2 | T23: =IF(AND($N$8="Yes",Q23<=$P$8),V23,IF(S23>0,$P$7,)) -> 63236.743 | U23: =$P$4 -> 0.068 | V23: =IF(S23>0,U23/12*S23,0) -> 54584.236 | W23: =T23-V23 -> 8652.5073 | X23: =S23-W23 -> 9623859.7 | Y23: =IF(Q23=1,V23,Y22+V23) -> 492990.41 | Z23: =IF(Q23=1,W23,Z22+W23) -> 76140.283 | AA23: =$P$9*S23/12 -> 802.70935 | AB23: =$P$10*AA23 -> 200.67734 | AC23: =IF(P23>0,SUM(V23:V34),"-") -> - | AD23: =IF(P23>0,SUM(W23:W34),"-") -> - | AF23: =IF('[29]Proforma-Input'!$C$108="Yes",MONTH(O23)&YEAR(O23)=MONTH($C$9)&YEAR($C$9),0) -> 0 | AG23: 1
B24: =IFERROR(DATE(YEAR(B23),MONTH(B23)+1,DAY(B23)),"-") -> - | D24: 10 | E24: =1+E23 -> 10 | F24: =IFERROR(IF(B24<$C$9,IF('[29]Proforma-Input'!$C$108="Yes",K23,K23),0),) -> 0 | G24: =IFERROR(IF(D24=$C$7,K23,IF(AND($D$10="Yes",D24<=$C$10),I24,IF(F24>0,$C$8,))),) -> 0 | H24: =IFERROR(IF(B24<$C$9,IF('[29]Proforma-Input'!$C$108="Yes",H23,),0),) -> 0 | I24: =(H24/12)*F24 -> 0 | J24: =IF(D24=$C$7,0,G24-I24) -> 0 | K24: =IFERROR(F24-J24,) -> 0 | L24: =IF(C24>0,SUM(I24:I35),"-") -> - | M24: =IF(C24>0,SUM(J24:J35),"-") -> - | O24: =IFERROR(DATE(YEAR(O23),MONTH(O23)+1,DAY(O23)),"-") -> 46206 | Q24: =IF(S24>0,1+Q23,) -> 10 | R24: =1+R23 -> 10 | S24: =IF('[29]Proforma-Input'!$C$108="No",X23,IF(AF24=TRUE,$P$3,X23)) -> 9623859.7 | T24: =IF(AND($N$8="Yes",Q24<=$P$8),V24,IF(S24>0,$P$7,)) -> 63236.743 | U24: =$P$4 -> 0.068 | V24: =IF(S24>0,U24/12*S24,0) -> 54535.205 | W24: =T24-V24 -> 8701.5382 | X24: =S24-W24 -> 9615158.2 | Y24: =IF(Q24=1,V24,Y23+V24) -> 547525.61 | Z24: =IF(Q24=1,W24,Z23+W24) -> 84841.821 | AA24: =$P$9*S24/12 -> 801.98831 | AB24: =$P$10*AA24 -> 200.49708 | AC24: =IF(P24>0,SUM(V24:V35),"-") -> - | AD24: =IF(P24>0,SUM(W24:W35),"-") -> - | AF24: =IF('[29]Proforma-Input'!$C$108="Yes",MONTH(O24)&YEAR(O24)=MONTH($C$9)&YEAR($C$9),0) -> 0 | AG24: 1
B25: =IFERROR(DATE(YEAR(B24),MONTH(B24)+1,DAY(B24)),"-") -> - | D25: 11 | E25: =1+E24 -> 11 | F25: =IFERROR(IF(B25<$C$9,IF('[29]Proforma-Input'!$C$108="Yes",K24,K24),0),) -> 0 | G25: =IFERROR(IF(D25=$C$7,K24,IF(AND($D$10="Yes",D25<=$C$10),I25,IF(F25>0,$C$8,))),) -> 0 | H25: =IFERROR(IF(B25<$C$9,IF('[29]Proforma-Input'!$C$108="Yes",H24,),0),) -> 0 | I25: =(H25/12)*F25 -> 0 | J25: =IF(D25=$C$7,0,G25-I25) -> 0 | K25: =IFERROR(F25-J25,) -> 0 | L25: =IF(C25>0,SUM(I25:I36),"-") -> - | M25: =IF(C25>0,SUM(J25:J36),"-") -> - | O25: =IFERROR(DATE(YEAR(O24),MONTH(O24)+1,DAY(O24)),"-") -> 46237 | Q25: =IF(S25>0,1+Q24,) -> 11 | R25: =1+R24 -> 11 | S25: =IF('[29]Proforma-Input'!$C$108="No",X24,IF(AF25=TRUE,$P$3,X24)) -> 9615158.2 | T25: =IF(AND($N$8="Yes",Q25<=$P$8),V25,IF(S25>0,$P$7,)) -> 63236.743 | U25: =$P$4 -> 0.068 | V25: =IF(S25>0,U25/12*S25,0) -> 54485.896 | W25: =T25-V25 -> 8750.8469 | X25: =S25-W25 -> 9606407.3 | Y25: =IF(Q25=1,V25,Y24+V25) -> 602011.51 | Z25: =IF(Q25=1,W25,Z24+W25) -> 93592.668 | AA25: =$P$9*S25/12 -> 801.26318 | AB25: =$P$10*AA25 -> 200.3158 | AC25: =IF(P25>0,SUM(V25:V36),"-") -> - | AD25: =IF(P25>0,SUM(W25:W36),"-") -> - | AF25: =IF('[29]Proforma-Input'!$C$108="Yes",MONTH(O25)&YEAR(O25)=MONTH($C$9)&YEAR($C$9),0) -> 0 | AG25: 1
B26: =IFERROR(DATE(YEAR(B25),MONTH(B25)+1,DAY(B25)),"-") -> - | D26: 12 | E26: =1+E25 -> 12 | F26: =IFERROR(IF(B26<$C$9,IF('[29]Proforma-Input'!$C$108="Yes",K25,K25),0),) -> 0 | G26: =IFERROR(IF(D26=$C$7,K25,IF(AND($D$10="Yes",D26<=$C$10),I26,IF(F26>0,$C$8,))),) -> 0 | H26: =IFERROR(IF(B26<$C$9,IF('[29]Proforma-Input'!$C$108="Yes",H25,),0),) -> 0 | I26: =(H26/12)*F26 -> 0 | J26: =IF(D26=$C$7,0,G26-I26) -> 0 | K26: =IFERROR(F26-J26,) -> 0 | L26: =IF(C26>0,SUM(I26:I37),"-") -> - | M26: =IF(C26>0,SUM(J26:J37),"-") -> - | O26: =IFERROR(DATE(YEAR(O25),MONTH(O25)+1,DAY(O25)),"-") -> 46268 | Q26: =IF(S26>0,1+Q25,) -> 12 | R26: =1+R25 -> 12 | S26: =IF('[29]Proforma-Input'!$C$108="No",X25,IF(AF26=TRUE,$P$3,X25)) -> 9606407.3 | T26: =IF(AND($N$8="Yes",Q26<=$P$8),V26,IF(S26>0,$P$7,)) -> 63236.743 | U26: =$P$4 -> 0.068 | V26: =IF(S26>0,U26/12*S26,0) -> 54436.308 | W26: =T26-V26 -> 8800.435 | X26: =S26-W26 -> 9597606.9 | Y26: =IF(Q26=1,V26,Y25+V26) -> 656447.82 | Z26: =IF(Q26=1,W26,Z25+W26) -> 102393.1 | AA26: =$P$9*S26/12 -> 800.53394 | AB26: =$P$10*AA26 -> 200.13349 | AC26: =IF(P26>0,SUM(V26:V37),"-") -> - | AD26: =IF(P26>0,SUM(W26:W37),"-") -> - | AF26: =IF('[29]Proforma-Input'!$C$108="Yes",MONTH(O26)&YEAR(O26)=MONTH($C$9)&YEAR($C$9),0) -> 0 | AG26: 1
B27: =IFERROR(DATE(YEAR(B26),MONTH(B26)+1,DAY(B26)),"-") -> - | C27: 2 | D27: 13 | E27: 1 | F27: =IFERROR(IF(B27<$C$9,IF('[29]Proforma-Input'!$C$108="Yes",K26,K26),0),) -> 0 | G27: =IFERROR(IF(D27=$C$7,K26,IF(AND($D$10="Yes",D27<=$C$10),I27,IF(F27>0,$C$8,))),) -> 0 | H27: =IFERROR(IF(B27<$C$9,IF('[29]Proforma-Input'!$C$108="Yes",H26,),0),) -> 0 | I27: =(H27/12)*F27 -> 0 | J27: =IF(D27=$C$7,0,G27-I27) -> 0 | K27: =IFERROR(F27-J27,) -> 0 | L27: =IF(C27>0,SUM(I27:I38),"-") -> 0 | M27: =IF(C27>0,SUM(J27:J38),"-") -> 0 | O27: =IFERROR(DATE(YEAR(O26),MONTH(O26)+1,DAY(O26)),"-") -> 46298 | P27: 2 | Q27: =IF(S27>0,1+Q26,) -> 13 | R27: 1 | S27: =IF('[29]Proforma-Input'!$C$108="No",X26,IF(AF27=TRUE,$P$3,X26)) -> 9597606.9 | T27: =IF(AND($N$8="Yes",Q27<=$P$8),V27,IF(S27>0,$P$7,)) -> 63236.743 | U27: =$P$4 -> 0.068 | V27: =IF(S27>0,U27/12*S27,0) -> 54386.439 | W27: =T27-V27 -> 8850.3042 | X27: =S27-W27 -> 9588756.6 | Y27: =IF(Q27=1,V27,Y26+V27) -> 710834.26 | Z27: =IF(Q27=1,W27,Z26+W27) -> 111243.41 | AA27: =$P$9*S27/12 -> 799.80057 | AB27: =$P$10*AA27 -> 199.95014 | AC27: =IF(P27>0,SUM(V27:V38),"-") -> 649263.93 | AD27: =IF(P27>0,SUM(W27:W38),"-") -> 109576.99 | AF27: =IF('[29]Proforma-Input'!$C$108="Yes",MONTH(O27)&YEAR(O27)=MONTH($C$9)&YEAR($C$9),0) -> 0 | AG27: 2
B28: =IFERROR(DATE(YEAR(B27),MONTH(B27)+1,DAY(B27)),"-") -> - | D28: 14 | E28: =1+E27 -> 2 | F28: =IFERROR(IF(B28<$C$9,IF('[29]Proforma-Input'!$C$108="Yes",K27,K27),0),) -> 0 | G28: =IFERROR(IF(D28=$C$7,K27,IF(AND($D$10="Yes",D28<=$C$10),I28,IF(F28>0,$C$8,))),) -> 0 | H28: =IFERROR(IF(B28<$C$9,IF('[29]Proforma-Input'!$C$108="Yes",H27,),0),) -> 0 | I28: =(H28/12)*F28 -> 0 | J28: =IF(D28=$C$7,0,G28-I28) -> 0 | K28: =IFERROR(F28-J28,) -> 0 | L28: =IF(C28>0,SUM(I28:I39),"-") -> - | M28: =IF(C28>0,SUM(J28:J39),"-") -> - | O28: =IFERROR(DATE(YEAR(O27),MONTH(O27)+1,DAY(O27)),"-") -> 46329 | Q28: =IF(S28>0,1+Q27,) -> 14 | R28: =1+R27 -> 2 | S28: =IF('[29]Proforma-Input'!$C$108="No",X27,IF(AF28=TRUE,$P$3,X27)) -> 9588756.6 | T28: =IF(AND($N$8="Yes",Q28<=$P$8),V28,IF(S28>0,$P$7,)) -> 63236.743 | U28: =$P$4 -> 0.068 | V28: =IF(S28>0,U28/12*S28,0) -> 54336.287 | W28: =T28-V28 -> 8900.4559 | X28: =S28-W28 -> 9579856.1 | Y28: =IF(Q28=1,V28,Y27+V28) -> 765170.54 | Z28: =IF(Q28=1,W28,Z27+W28) -> 120143.86 | AA28: =$P$9*S28/12 -> 799.06305 | AB28: =$P$10*AA28 -> 199.76576 | AC28: =IF(P28>0,SUM(V28:V39),"-") -> - | AD28: =IF(P28>0,SUM(W28:W39),"-") -> - | AF28: =IF('[29]Proforma-Input'!$C$108="Yes",MONTH(O28)&YEAR(O28)=MONTH($C$9)&YEAR($C$9),0) -> 0 | AG28: 2
B29: =IFERROR(DATE(YEAR(B28),MONTH(B28)+1,DAY(B28)),"-") -> - | D29: 15 | E29: =1+E28 -> 3 | F29: =IFERROR(IF(B29<$C$9,IF('[29]Proforma-Input'!$C$108="Yes",K28,K28),0),) -> 0 | G29: =IFERROR(IF(D29=$C$7,K28,IF(AND($D$10="Yes",D29<=$C$10),I29,IF(F29>0,$C$8,))),) -> 0 | H29: =IFERROR(IF(B29<$C$9,IF('[29]Proforma-Input'!$C$108="Yes",H28,),0),) -> 0 | I29: =(H29/12)*F29 -> 0 | J29: =IF(D29=$C$7,0,G29-I29) -> 0 | K29: =IFERROR(F29-J29,) -> 0 | L29: =IF(C29>0,SUM(I29:I40),"-") -> - | M29: =IF(C29>0,SUM(J29:J40),"-") -> - | O29: =IFERROR(DATE(YEAR(O28),MONTH(O28)+1,DAY(O28)),"-") -> 46359 | Q29: =IF(S29>0,1+Q28,) -> 15 | R29: =1+R28 -> 3 | S29: =IF('[29]Proforma-Input'!$C$108="No",X28,IF(AF29=TRUE,$P$3,X28)) -> 9579856.1 | T29: =IF(AND($N$8="Yes",Q29<=$P$8),V29,IF(S29>0,$P$7,)) -> 63236.743 | U29: =$P$4 -> 0.068 | V29: =IF(S29>0,U29/12*S29,0) -> 54285.851 | W29: =T29-V29 -> 8950.8918 | X29: =S29-W29 -> 9570905.2 | Y29: =IF(Q29=1,V29,Y28+V29) -> 819456.39 | Z29: =IF(Q29=1,W29,Z28+W29) -> 129094.75 | AA29: =$P$9*S29/12 -> 798.32134 | AB29: =$P$10*AA29 -> 199.58034 | AC29: =IF(P29>0,SUM(V29:V40),"-") -> - | AD29: =IF(P29>0,SUM(W29:W40),"-") -> - | AF29: =IF('[29]Proforma-Input'!$C$108="Yes",MONTH(O29)&YEAR(O29)=MONTH($C$9)&YEAR($C$9),0) -> 0 | AG29: 2
B30: =IFERROR(DATE(YEAR(B29),MONTH(B29)+1,DAY(B29)),"-") -> - | D30: 16 | E30: =1+E29 -> 4 | F30: =IFERROR(IF(B30<$C$9,IF('[29]Proforma-Input'!$C$108="Yes",K29,K29),0),) -> 0 | G30: =IFERROR(IF(D30=$C$7,K29,IF(AND($D$10="Yes",D30<=$C$10),I30,IF(F30>0,$C$8,))),) -> 0 | H30: =IFERROR(IF(B30<$C$9,IF('[29]Proforma-Input'!$C$108="Yes",H29,),0),) -> 0 | I30: =(H30/12)*F30 -> 0 | J30: =IF(D30=$C$7,0,G30-I30) -> 0 | K30: =IFERROR(F30-J30,) -> 0 | L30: =IF(C30>0,SUM(I30:I41),"-") -> - | M30: =IF(C30>0,SUM(J30:J41),"-") -> - | O30: =IFERROR(DATE(YEAR(O29),MONTH(O29)+1,DAY(O29)),"-") -> 46390 | Q30: =IF(S30>0,1+Q29,) -> 16 | R30: =1+R29 -> 4 | S30: =IF('[29]Proforma-Input'!$C$108="No",X29,IF(AF30=TRUE,$P$3,X29)) -> 9570905.2 | T30: =IF(AND($N$8="Yes",Q30<=$P$8),V30,IF(S30>0,$P$7,)) -> 63236.743 | U30: =$P$4 -> 0.068 | V30: =IF(S30>0,U30/12*S30,0) -> 54235.13 | W30: =T30-V30 -> 9001.6135 | X30: =S30-W30 -> 9561903.6 | Y30: =IF(Q30=1,V30,Y29+V30) -> 873691.52 | Z30: =IF(Q30=1,W30,Z29+W30) -> 138096.37 | AA30: =$P$9*S30/12 -> 797.57544 | AB30: =$P$10*AA30 -> 199.39386 | AC30: =IF(P30>0,SUM(V30:V41),"-") -> - | AD30: =IF(P30>0,SUM(W30:W41),"-") -> - | AF30: =IF('[29]Proforma-Input'!$C$108="Yes",MONTH(O30)&YEAR(O30)=MONTH($C$9)&YEAR($C$9),0) -> 0 | AG30: 2
B31: =IFERROR(DATE(YEAR(B30),MONTH(B30)+1,DAY(B30)),"-") -> - | D31: 17 | E31: =1+E30 -> 5 | F31: =IFERROR(IF(B31<$C$9,IF('[29]Proforma-Input'!$C$108="Yes",K30,K30),0),) -> 0 | G31: =IFERROR(IF(D31=$C$7,K30,IF(AND($D$10="Yes",D31<=$C$10),I31,IF(F31>0,$C$8,))),) -> 0 | H31: =IFERROR(IF(B31<$C$9,IF('[29]Proforma-Input'!$C$108="Yes",H30,),0),) -> 0 | I31: =(H31/12)*F31 -> 0 | J31: =IF(D31=$C$7,0,G31-I31) -> 0 | K31: =IFERROR(F31-J31,) -> 0 | L31: =IF(C31>0,SUM(I31:I42),"-") -> - | M31: =IF(C31>0,SUM(J31:J42),"-") -> - | O31: =IFERROR(DATE(YEAR(O30),MONTH(O30)+1,DAY(O30)),"-") -> 46421 | Q31: =IF(S31>0,1+Q30,) -> 17 | R31: =1+R30 -> 5 | S31: =IF('[29]Proforma-Input'!$C$108="No",X30,IF(AF31=TRUE,$P$3,X30)) -> 9561903.6 | T31: =IF(AND($N$8="Yes",Q31<=$P$8),V31,IF(S31>0,$P$7,)) -> 63236.743 | U31: =$P$4 -> 0.068 | V31: =IF(S31>0,U31/12*S31,0) -> 54184.121 | W31: =T31-V31 -> 9052.6227 | X31: =S31-W31 -> 9552851 | Y31: =IF(Q31=1,V31,Y30+V31) -> 927875.64 | Z31: =IF(Q31=1,W31,Z30+W31) -> 147148.99 | AA31: =$P$9*S31/12 -> 796.8253 | AB31: =$P$10*AA31 -> 199.20633 | AC31: =IF(P31>0,SUM(V31:V42),"-") -> - | AD31: =IF(P31>0,SUM(W31:W42),"-") -> - | AF31: =IF('[29]Proforma-Input'!$C$108="Yes",MONTH(O31)&YEAR(O31)=MONTH($C$9)&YEAR($C$9),0) -> 0 | AG31: 2
B32: =IFERROR(DATE(YEAR(B31),MONTH(B31)+1,DAY(B31)),"-") -> - | D32: 18 | E32: =1+E31 -> 6 | F32: =IFERROR(IF(B32<$C$9,IF('[29]Proforma-Input'!$C$108="Yes",K31,K31),0),) -> 0 | G32: =IFERROR(IF(D32=$C$7,K31,IF(AND($D$10="Yes",D32<=$C$10),I32,IF(F32>0,$C$8,))),) -> 0 | H32: =IFERROR(IF(B32<$C$9,IF('[29]Proforma-Input'!$C$108="Yes",H31,),0),) -> 0 | I32: =(H32/12)*F32 -> 0 | J32: =IF(D32=$C$7,0,G32-I32) -> 0 | K32: =IFERROR(F32-J32,) -> 0 | L32: =IF(C32>0,SUM(I32:I43),"-") -> - | M32: =IF(C32>0,SUM(J32:J43),"-") -> - | O32: =IFERROR(DATE(YEAR(O31),MONTH(O31)+1,DAY(O31)),"-") -> 46449 | Q32: =IF(S32>0,1+Q31,) -> 18 | R32: =1+R31 -> 6 | S32: =IF('[29]Proforma-Input'!$C$108="No",X31,IF(AF32=TRUE,$P$3,X31)) -> 9552851 | T32: =IF(AND($N$8="Yes",Q32<=$P$8),V32,IF(S32>0,$P$7,)) -> 63236.743 | U32: =$P$4 -> 0.068 | V32: =IF(S32>0,U32/12*S32,0) -> 54132.822 | W32: =T32-V32 -> 9103.9209 | X32: =S32-W32 -> 9543747.1 | Y32: =IF(Q32=1,V32,Y31+V32) -> 982008.47 | Z32: =IF(Q32=1,W32,Z31+W32) -> 156252.91 | AA32: =$P$9*S32/12 -> 796.07092 | AB32: =$P$10*AA32 -> 199.01773 | AC32: =IF(P32>0,SUM(V32:V43),"-") -> - | AD32: =IF(P32>0,SUM(W32:W43),"-") -> - | AF32: =IF('[29]Proforma-Input'!$C$108="Yes",MONTH(O32)&YEAR(O32)=MONTH($C$9)&YEAR($C$9),0) -> 0 | AG32: 2
B33: =IFERROR(DATE(YEAR(B32),MONTH(B32)+1,DAY(B32)),"-") -> - | D33: 19 | E33: =1+E32 -> 7 | F33: =IFERROR(IF(B33<$C$9,IF('[29]Proforma-Input'!$C$108="Yes",K32,K32),0),) -> 0 | G33: =IFERROR(IF(D33=$C$7,K32,IF(AND($D$10="Yes",D33<=$C$10),I33,IF(F33>0,$C$8,))),) -> 0 | H33: =IFERROR(IF(B33<$C$9,IF('[29]Proforma-Input'!$C$108="Yes",H32,),0),) -> 0 | I33: =(H33/12)*F33 -> 0 | J33: =IF(D33=$C$7,0,G33-I33) -> 0 | K33: =IFERROR(F33-J33,) -> 0 | L33: =IF(C33>0,SUM(I33:I44),"-") -> - | M33: =IF(C33>0,SUM(J33:J44),"-") -> - | O33: =IFERROR(DATE(YEAR(O32),MONTH(O32)+1,DAY(O32)),"-") -> 46480 | Q33: =IF(S33>0,1+Q32,) -> 19 | R33: =1+R32 -> 7 | S33: =IF('[29]Proforma-Input'!$C$108="No",X32,IF(AF33=TRUE,$P$3,X32)) -> 9543747.1 | T33: =IF(AND($N$8="Yes",Q33<=$P$8),V33,IF(S33>0,$P$7,)) -> 63236.743 | U33: =$P$4 -> 0.068 | V33: =IF(S33>0,U33/12*S33,0) -> 54081.233 | W33: =T33-V33 -> 9155.5098 | X33: =S33-W33 -> 9534591.6 | Y33: =IF(Q33=1,V33,Y32+V33) -> 1036089.7 | Z33: =IF(Q33=1,W33,Z32+W33) -> 165408.42 | AA33: =$P$9*S33/12 -> 795.31226 | AB33: =$P$10*AA33 -> 198.82806 | AC33: =IF(P33>0,SUM(V33:V44),"-") -> - | AD33: =IF(P33>0,SUM(W33:W44),"-") -> - | AF33: =IF('[29]Proforma-Input'!$C$108="Yes",MONTH(O33)&YEAR(O33)=MONTH($C$9)&YEAR($C$9),0) -> 0 | AG33: 2
B34: =IFERROR(DATE(YEAR(B33),MONTH(B33)+1,DAY(B33)),"-") -> - | D34: 20 | E34: =1+E33 -> 8 | F34: =IFERROR(IF(B34<$C$9,IF('[29]Proforma-Input'!$C$108="Yes",K33,K33),0),) -> 0 | G34: =IFERROR(IF(D34=$C$7,K33,IF(AND($D$10="Yes",D34<=$C$10),I34,IF(F34>0,$C$8,))),) -> 0 | H34: =IFERROR(IF(B34<$C$9,IF('[29]Proforma-Input'!$C$108="Yes",H33,),0),) -> 0 | I34: =(H34/12)*F34 -> 0 | J34: =IF(D34=$C$7,0,G34-I34) -> 0 | K34: =IFERROR(F34-J34,) -> 0 | L34: =IF(C34>0,SUM(I34:I45),"-") -> - | M34: =IF(C34>0,SUM(J34:J45),"-") -> - | O34: =IFERROR(DATE(YEAR(O33),MONTH(O33)+1,DAY(O33)),"-") -> 46510 | Q34: =IF(S34>0,1+Q33,) -> 20 | R34: =1+R33 -> 8 | S34: =IF('[29]Proforma-Input'!$C$108="No",X33,IF(AF34=TRUE,$P$3,X33)) -> 9534591.6 | T34: =IF(AND($N$8="Yes",Q34<=$P$8),V34,IF(S34>0,$P$7,)) -> 63236.743 | U34: =$P$4 -> 0.068 | V34: =IF(S34>0,U34/12*S34,0) -> 54029.352 | W34: =T34-V34 -> 9207.391 | X34: =S34-W34 -> 9525384.2 | Y34: =IF(Q34=1,V34,Y33+V34) -> 1090119.1 | Z34: =IF(Q34=1,W34,Z33+W34) -> 174615.81 | AA34: =$P$9*S34/12 -> 794.5493 | AB34: =$P$10*AA34 -> 198.63732 | AC34: =IF(P34>0,SUM(V34:V45),"-") -> - | AD34: =IF(P34>0,SUM(W34:W45),"-") -> - | AF34: =IF('[29]Proforma-Input'!$C$108="Yes",MONTH(O34)&YEAR(O34)=MONTH($C$9)&YEAR($C$9),0) -> 0 | AG34: 2
B35: =IFERROR(DATE(YEAR(B34),MONTH(B34)+1,DAY(B34)),"-") -> - | D35: 21 | E35: =1+E34 -> 9 | F35: =IFERROR(IF(B35<$C$9,IF('[29]Proforma-Input'!$C$108="Yes",K34,K34),0),) -> 0 | G35: =IFERROR(IF(D35=$C$7,K34,IF(AND($D$10="Yes",D35<=$C$10),I35,IF(F35>0,$C$8,))),) -> 0 | H35: =IFERROR(IF(B35<$C$9,IF('[29]Proforma-Input'!$C$108="Yes",H34,),0),) -> 0 | I35: =(H35/12)*F35 -> 0 | J35: =IF(D35=$C$7,0,G35-I35) -> 0 | K35: =IFERROR(F35-J35,) -> 0 | L35: =IF(C35>0,SUM(I35:I46),"-") -> - | M35: =IF(C35>0,SUM(J35:J46),"-") -> - | O35: =IFERROR(DATE(YEAR(O34),MONTH(O34)+1,DAY(O34)),"-") -> 46541 | Q35: =IF(S35>0,1+Q34,) -> 21 | R35: =1+R34 -> 9 | S35: =IF('[29]Proforma-Input'!$C$108="No",X34,IF(AF35=TRUE,$P$3,X34)) -> 9525384.2 | T35: =IF(AND($N$8="Yes",Q35<=$P$8),V35,IF(S35>0,$P$7,)) -> 63236.743 | U35: =$P$4 -> 0.068 | V35: =IF(S35>0,U35/12*S35,0) -> 53977.177 | W35: =T35-V35 -> 9259.5662 | X35: =S35-W35 -> 9516124.6 | Y35: =IF(Q35=1,V35,Y34+V35) -> 1144096.2 | Z35: =IF(Q35=1,W35,Z34+W35) -> 183875.38 | AA35: =$P$9*S35/12 -> 793.78202 | AB35: =$P$10*AA35 -> 198.4455 | AC35: =IF(P35>0,SUM(V35:V46),"-") -> - | AD35: =IF(P35>0,SUM(W35:W46),"-") -> - | AF35: =IF('[29]Proforma-Input'!$C$108="Yes",MONTH(O35)&YEAR(O35)=MONTH($C$9)&YEAR($C$9),0) -> 0 | AG35: 2
B36: =IFERROR(DATE(YEAR(B35),MONTH(B35)+1,DAY(B35)),"-") -> - | D36: 22 | E36: =1+E35 -> 10 | F36: =IFERROR(IF(B36<$C$9,IF('[29]Proforma-Input'!$C$108="Yes",K35,K35),0),) -> 0 | G36: =IFERROR(IF(D36=$C$7,K35,IF(AND($D$10="Yes",D36<=$C$10),I36,IF(F36>0,$C$8,))),) -> 0 | H36: =IFERROR(IF(B36<$C$9,IF('[29]Proforma-Input'!$C$108="Yes",H35,),0),) -> 0 | I36: =(H36/12)*F36 -> 0 | J36: =IF(D36=$C$7,0,G36-I36) -> 0 | K36: =IFERROR(F36-J36,) -> 0 | L36: =IF(C36>0,SUM(I36:I47),"-") -> - | M36: =IF(C36>0,SUM(J36:J47),"-") -> - | O36: =IFERROR(DATE(YEAR(O35),MONTH(O35)+1,DAY(O35)),"-") -> 46571 | Q36: =IF(S36>0,1+Q35,) -> 22 | R36: =1+R35 -> 10 | S36: =IF('[29]Proforma-Input'!$C$108="No",X35,IF(AF36=TRUE,$P$3,X35)) -> 9516124.6 | T36: =IF(AND($N$8="Yes",Q36<=$P$8),V36,IF(S36>0,$P$7,)) -> 63236.743 | U36: =$P$4 -> 0.068 | V36: =IF(S36>0,U36/12*S36,0) -> 53924.706 | W36: =T36-V36 -> 9312.0371 | X36: =S36-W36 -> 9506812.6 | Y36: =IF(Q36=1,V36,Y35+V36) -> 1198020.9 | Z36: =IF(Q36=1,W36,Z35+W36) -> 193187.42 | AA36: =$P$9*S36/12 -> 793.01039 | AB36: =$P$10*AA36 -> 198.2526 | AC36: =IF(P36>0,SUM(V36:V47),"-") -> - | AD36: =IF(P36>0,SUM(W36:W47),"-") -> - | AF36: =IF('[29]Proforma-Input'!$C$108="Yes",MONTH(O36)&YEAR(O36)=MONTH($C$9)&YEAR($C$9),0) -> 0 | AG36: 2
B37: =IFERROR(DATE(YEAR(B36),MONTH(B36)+1,DAY(B36)),"-") -> - | D37: 23 | E37: =1+E36 -> 11 | F37: =IFERROR(IF(B37<$C$9,IF('[29]Proforma-Input'!$C$108="Yes",K36,K36),0),) -> 0 | G37: =IFERROR(IF(D37=$C$7,K36,IF(AND($D$10="Yes",D37<=$C$10),I37,IF(F37>0,$C$8,))),) -> 0 | H37: =IFERROR(IF(B37<$C$9,IF('[29]Proforma-Input'!$C$108="Yes",H36,),0),) -> 0 | I37: =(H37/12)*F37 -> 0 | J37: =IF(D37=$C$7,0,G37-I37) -> 0 | K37: =IFERROR(F37-J37,) -> 0 | L37: =IF(C37>0,SUM(I37:I48),"-") -> - | M37: =IF(C37>0,SUM(J37:J48),"-") -> - | O37: =IFERROR(DATE(YEAR(O36),MONTH(O36)+1,DAY(O36)),"-") -> 46602 | Q37: =IF(S37>0,1+Q36,) -> 23 | R37: =1+R36 -> 11 | S37: =IF('[29]Proforma-Input'!$C$108="No",X36,IF(AF37=TRUE,$P$3,X36)) -> 9506812.6 | T37: =IF(AND($N$8="Yes",Q37<=$P$8),V37,IF(S37>0,$P$7,)) -> 63236.743 | U37: =$P$4 -> 0.068 | V37: =IF(S37>0,U37/12*S37,0) -> 53871.938 | W37: =T37-V37 -> 9364.8053 | X37: =S37-W37 -> 9497447.8 | Y37: =IF(Q37=1,V37,Y36+V37) -> 1251892.9 | Z37: =IF(Q37=1,W37,Z36+W37) -> 202552.22 | AA37: =$P$9*S37/12 -> 792.23438 | AB37: =$P$10*AA37 -> 198.0586 | AC37: =IF(P37>0,SUM(V37:V48),"-") -> - | AD37: =IF(P37>0,SUM(W37:W48),"-") -> - | AF37: =IF('[29]Proforma-Input'!$C$108="Yes",MONTH(O37)&YEAR(O37)=MONTH($C$9)&YEAR($C$9),0) -> 0 | AG37: 2
B38: =IFERROR(DATE(YEAR(B37),MONTH(B37)+1,DAY(B37)),"-") -> - | D38: 24 | E38: =1+E37 -> 12 | F38: =IFERROR(IF(B38<$C$9,IF('[29]Proforma-Input'!$C$108="Yes",K37,K37),0),) -> 0 | G38: =IFERROR(IF(D38=$C$7,K37,IF(AND($D$10="Yes",D38<=$C$10),I38,IF(F38>0,$C$8,))),) -> 0 | H38: =IFERROR(IF(B38<$C$9,IF('[29]Proforma-Input'!$C$108="Yes",H37,),0),) -> 0 | I38: =(H38/12)*F38 -> 0 | J38: =IF(D38=$C$7,0,G38-I38) -> 0 | K38: =IFERROR(F38-J38,) -> 0 | L38: =IF(C38>0,SUM(I38:I49),"-") -> - | M38: =IF(C38>0,SUM(J38:J49),"-") -> - | O38: =IFERROR(DATE(YEAR(O37),MONTH(O37)+1,DAY(O37)),"-") -> 46633 | Q38: =IF(S38>0,1+Q37,) -> 24 | R38: =1+R37 -> 12 | S38: =IF('[29]Proforma-Input'!$C$108="No",X37,IF(AF38=TRUE,$P$3,X37)) -> 9497447.8 | T38: =IF(AND($N$8="Yes",Q38<=$P$8),V38,IF(S38>0,$P$7,)) -> 63236.743 | U38: =$P$4 -> 0.068 | V38: =IF(S38>0,U38/12*S38,0) -> 53818.871 | W38: =T38-V38 -> 9417.8725 | X38: =S38-W38 -> 9488029.9 | Y38: =IF(Q38=1,V38,Y37+V38) -> 1305711.7 | Z38: =IF(Q38=1,W38,Z37+W38) -> 211970.09 | AA38: =$P$9*S38/12 -> 791.45398 | AB38: =$P$10*AA38 -> 197.8635 | AC38: =IF(P38>0,SUM(V38:V49),"-") -> - | AD38: =IF(P38>0,SUM(W38:W49),"-") -> - | AF38: =IF('[29]Proforma-Input'!$C$108="Yes",MONTH(O38)&YEAR(O38)=MONTH($C$9)&YEAR($C$9),0) -> 0 | AG38: 2
B39: =IFERROR(DATE(YEAR(B38),MONTH(B38)+1,DAY(B38)),"-") -> - | C39: 3 | D39: 25 | E39: 1 | F39: =IFERROR(IF(B39<$C$9,IF('[29]Proforma-Input'!$C$108="Yes",K38,K38),0),) -> 0 | G39: =IFERROR(IF(D39=$C$7,K38,IF(AND($D$10="Yes",D39<=$C$10),I39,IF(F39>0,$C$8,))),) -> 0 | H39: =IFERROR(IF(B39<$C$9,IF('[29]Proforma-Input'!$C$108="Yes",H38,),0),) -> 0 | I39: =(H39/12)*F39 -> 0 | J39: =IF(D39=$C$7,0,G39-I39) -> 0 | K39: =IFERROR(F39-J39,) -> 0 | L39: =IF(C39>0,SUM(I39:I50),"-") -> 0 | M39: =IF(C39>0,SUM(J39:J50),"-") -> 0 | O39: =IFERROR(DATE(YEAR(O38),MONTH(O38)+1,DAY(O38)),"-") -> 46663 | P39: 3 | Q39: =IF(S39>0,1+Q38,) -> 25 | R39: 1 | S39: =IF('[29]Proforma-Input'!$C$108="No",X38,IF(AF39=TRUE,$P$3,X38)) -> 9488029.9 | T39: =IF(AND($N$8="Yes",Q39<=$P$8),V39,IF(S39>0,$P$7,)) -> 63236.743 | U39: =$P$4 -> 0.068 | V39: =IF(S39>0,U39/12*S39,0) -> 53765.503 | W39: =T39-V39 -> 9471.2404 | X39: =S39-W39 -> 9478558.7 | Y39: =IF(Q39=1,V39,Y38+V39) -> 1359477.2 | Z39: =IF(Q39=1,W39,Z38+W39) -> 221441.33 | AA39: =$P$9*S39/12 -> 790.66916 | AB39: =$P$10*AA39 -> 197.66729 | AC39: =IF(P39>0,SUM(V39:V50),"-") -> 641576.02 | AD39: =IF(P39>0,SUM(W39:W50),"-") -> 117264.9 | AF39: =IF('[29]Proforma-Input'!$C$108="Yes",MONTH(O39)&YEAR(O39)=MONTH($C$9)&YEAR($C$9),0) -> 0 | AG39: 3
B40: =IFERROR(DATE(YEAR(B39),MONTH(B39)+1,DAY(B39)),"-") -> - | D40: 26 | E40: =1+E39 -> 2 | F40: =IFERROR(IF(B40<$C$9,IF('[29]Proforma-Input'!$C$108="Yes",K39,K39),0),) -> 0 | G40: =IFERROR(IF(D40=$C$7,K39,IF(AND($D$10="Yes",D40<=$C$10),I40,IF(F40>0,$C$8,))),) -> 0 | H40: =IFERROR(IF(B40<$C$9,IF('[29]Proforma-Input'!$C$108="Yes",H39,),0),) -> 0 | I40: =(H40/12)*F40 -> 0 | J40: =IF(D40=$C$7,0,G40-I40) -> 0 | K40: =IFERROR(F40-J40,) -> 0 | L40: =IF(C40>0,SUM(I40:I51),"-") -> - | M40: =IF(C40>0,SUM(J40:J51),"-") -> - | O40: =IFERROR(DATE(YEAR(O39),MONTH(O39)+1,DAY(O39)),"-") -> 46694 | Q40: =IF(S40>0,1+Q39,) -> 26 | R40: =1+R39 -> 2 | S40: =IF('[29]Proforma-Input'!$C$108="No",X39,IF(AF40=TRUE,$P$3,X39)) -> 9478558.7 | T40: =IF(AND($N$8="Yes",Q40<=$P$8),V40,IF(S40>0,$P$7,)) -> 63236.743 | U40: =$P$4 -> 0.068 | V40: =IF(S40>0,U40/12*S40,0) -> 53711.832 | W40: =T40-V40 -> 9524.9108 | X40: =S40-W40 -> 9469033.8 | Y40: =IF(Q40=1,V40,Y39+V40) -> 1413189.1 | Z40: =IF(Q40=1,W40,Z39+W40) -> 230966.24 | AA40: =$P$9*S40/12 -> 789.87989 | AB40: =$P$10*AA40 -> 197.46997 | AC40: =IF(P40>0,SUM(V40:V51),"-") -> - | AD40: =IF(P40>0,SUM(W40:W51),"-") -> - | AF40: =IF('[29]Proforma-Input'!$C$108="Yes",MONTH(O40)&YEAR(O40)=MONTH($C$9)&YEAR($C$9),0) -> 0 | AG40: 3
B41: =IFERROR(DATE(YEAR(B40),MONTH(B40)+1,DAY(B40)),"-") -> - | D41: 27 | E41: =1+E40 -> 3 | F41: =IFERROR(IF(B41<$C$9,IF('[29]Proforma-Input'!$C$108="Yes",K40,K40),0),) -> 0 | G41: =IFERROR(IF(D41=$C$7,K40,IF(AND($D$10="Yes",D41<=$C$10),I41,IF(F41>0,$C$8,))),) -> 0 | H41: =IFERROR(IF(B41<$C$9,IF('[29]Proforma-Input'!$C$108="Yes",H40,),0),) -> 0 | I41: =(H41/12)*F41 -> 0 | J41: =IF(D41=$C$7,0,G41-I41) -> 0 | K41: =IFERROR(F41-J41,) -> 0 | L41: =IF(C41>0,SUM(I41:I52),"-") -> - | M41: =IF(C41>0,SUM(J41:J52),"-") -> - | O41: =IFERROR(DATE(YEAR(O40),MONTH(O40)+1,DAY(O40)),"-") -> 46724 | Q41: =IF(S41>0,1+Q40,) -> 27 | R41: =1+R40 -> 3 | S41: =IF('[29]Proforma-Input'!$C$108="No",X40,IF(AF41=TRUE,$P$3,X40)) -> 9469033.8 | T41: =IF(AND($N$8="Yes",Q41<=$P$8),V41,IF(S41>0,$P$7,)) -> 63236.743 | U41: =$P$4 -> 0.068 | V41: =IF(S41>0,U41/12*S41,0) -> 53657.858 | W41: =T41-V41 -> 9578.8853 | X41: =S41-W41 -> 9459454.9 | Y41: =IF(Q41=1,V41,Y40+V41) -> 1466846.9 | Z41: =IF(Q41=1,W41,Z40+W41) -> 240545.13 | AA41: =$P$9*S41/12 -> 789.08615 | AB41: =$P$10*AA41 -> 197.27154 | AC41: =IF(P41>0,SUM(V41:V52),"-") -> - | AD41: =IF(P41>0,SUM(W41:W52),"-") -> - | AF41: =IF('[29]Proforma-Input'!$C$108="Yes",MONTH(O41)&YEAR(O41)=MONTH($C$9)&YEAR($C$9),0) -> 0 | AG41: 3
B42: =IFERROR(DATE(YEAR(B41),MONTH(B41)+1,DAY(B41)),"-") -> - | D42: 28 | E42: =1+E41 -> 4 | F42: =IFERROR(IF(B42<$C$9,IF('[29]Proforma-Input'!$C$108="Yes",K41,K41),0),) -> 0 | G42: =IFERROR(IF(D42=$C$7,K41,IF(AND($D$10="Yes",D42<=$C$10),I42,IF(F42>0,$C$8,))),) -> 0 | H42: =IFERROR(IF(B42<$C$9,IF('[29]Proforma-Input'!$C$108="Yes",H41,),0),) -> 0 | I42: =(H42/12)*F42 -> 0 | J42: =IF(D42=$C$7,0,G42-I42) -> 0 | K42: =IFERROR(F42-J42,) -> 0 | L42: =IF(C42>0,SUM(I42:I53),"-") -> - | M42: =IF(C42>0,SUM(J42:J53),"-") -> - | O42: =IFERROR(DATE(YEAR(O41),MONTH(O41)+1,DAY(O41)),"-") -> 46755 | Q42: =IF(S42>0,1+Q41,) -> 28 | R42: =1+R41 -> 4 | S42: =IF('[29]Proforma-Input'!$C$108="No",X41,IF(AF42=TRUE,$P$3,X41)) -> 9459454.9 | T42: =IF(AND($N$8="Yes",Q42<=$P$8),V42,IF(S42>0,$P$7,)) -> 63236.743 | U42: =$P$4 -> 0.068 | V42: =IF(S42>0,U42/12*S42,0) -> 53603.578 | W42: =T42-V42 -> 9633.1657 | X42: =S42-W42 -> 9449821.7 | Y42: =IF(Q42=1,V42,Y41+V42) -> 1520450.5 | Z42: =IF(Q42=1,W42,Z41+W42) -> 250178.3 | AA42: =$P$9*S42/12 -> 788.28791 | AB42: =$P$10*AA42 -> 197.07198 | AC42: =IF(P42>0,SUM(V42:V53),"-") -> - | AD42: =IF(P42>0,SUM(W42:W53),"-") -> - | AF42: =IF('[29]Proforma-Input'!$C$108="Yes",MONTH(O42)&YEAR(O42)=MONTH($C$9)&YEAR($C$9),0) -> 0 | AG42: 3
B43: =IFERROR(DATE(YEAR(B42),MONTH(B42)+1,DAY(B42)),"-") -> - | D43: 29 | E43: =1+E42 -> 5 | F43: =IFERROR(IF(B43<$C$9,IF('[29]Proforma-Input'!$C$108="Yes",K42,K42),0),) -> 0 | G43: =IFERROR(IF(D43=$C$7,K42,IF(AND($D$10="Yes",D43<=$C$10),I43,IF(F43>0,$C$8,))),) -> 0 | H43: =IFERROR(IF(B43<$C$9,IF('[29]Proforma-Input'!$C$108="Yes",H42,),0),) -> 0 | I43: =(H43/12)*F43 -> 0 | J43: =IF(D43=$C$7,0,G43-I43) -> 0 | K43: =IFERROR(F43-J43,) -> 0 | L43: =IF(C43>0,SUM(I43:I54),"-") -> - | M43: =IF(C43>0,SUM(J43:J54),"-") -> - | O43: =IFERROR(DATE(YEAR(O42),MONTH(O42)+1,DAY(O42)),"-") -> 46786 | Q43: =IF(S43>0,1+Q42,) -> 29 | R43: =1+R42 -> 5 | S43: =IF('[29]Proforma-Input'!$C$108="No",X42,IF(AF43=TRUE,$P$3,X42)) -> 9449821.7 | T43: =IF(AND($N$8="Yes",Q43<=$P$8),V43,IF(S43>0,$P$7,)) -> 63236.743 | U43: =$P$4 -> 0.068 | V43: =IF(S43>0,U43/12*S43,0) -> 53548.99 | W43: =T43-V43 -> 9687.7536 | X43: =S43-W43 -> 9440134 | Y43: =IF(Q43=1,V43,Y42+V43) -> 1573999.5 | Z43: =IF(Q43=1,W43,Z42+W43) -> 259866.05 | AA43: =$P$9*S43/12 -> 787.48514 | AB43: =$P$10*AA43 -> 196.87129 | AC43: =IF(P43>0,SUM(V43:V54),"-") -> - | AD43: =IF(P43>0,SUM(W43:W54),"-") -> - | AF43: =IF('[29]Proforma-Input'!$C$108="Yes",MONTH(O43)&YEAR(O43)=MONTH($C$9)&YEAR($C$9),0) -> 0 | AG43: 3
B44: =IFERROR(DATE(YEAR(B43),MONTH(B43)+1,DAY(B43)),"-") -> - | D44: 30 | E44: =1+E43 -> 6 | F44: =IFERROR(IF(B44<$C$9,IF('[29]Proforma-Input'!$C$108="Yes",K43,K43),0),) -> 0 | G44: =IFERROR(IF(D44=$C$7,K43,IF(AND($D$10="Yes",D44<=$C$10),I44,IF(F44>0,$C$8,))),) -> 0 | H44: =IFERROR(IF(B44<$C$9,IF('[29]Proforma-Input'!$C$108="Yes",H43,),0),) -> 0 | I44: =(H44/12)*F44 -> 0 | J44: =IF(D44=$C$7,0,G44-I44) -> 0 | K44: =IFERROR(F44-J44,) -> 0 | L44: =IF(C44>0,SUM(I44:I55),"-") -> - | M44: =IF(C44>0,SUM(J44:J55),"-") -> - | O44: =IFERROR(DATE(YEAR(O43),MONTH(O43)+1,DAY(O43)),"-") -> 46815 | Q44: =IF(S44>0,1+Q43,) -> 30 | R44: =1+R43 -> 6 | S44: =IF('[29]Proforma-Input'!$C$108="No",X43,IF(AF44=TRUE,$P$3,X43)) -> 9440134 | T44: =IF(AND($N$8="Yes",Q44<=$P$8),V44,IF(S44>0,$P$7,)) -> 63236.743 | U44: =$P$4 -> 0.068 | V44: =IF(S44>0,U44/12*S44,0) -> 53494.092 | W44: =T44-V44 -> 9742.6509 | X44: =S44-W44 -> 9430391.3 | Y44: =IF(Q44=1,V44,Y43+V44) -> 1627493.6 | Z44: =IF(Q44=1,W44,Z43+W44) -> 269608.7 | AA44: =$P$9*S44/12 -> 786.67783 | AB44: =$P$10*AA44 -> 196.66946 | AC44: =IF(P44>0,SUM(V44:V55),"-") -> - | AD44: =IF(P44>0,SUM(W44:W55),"-") -> - | AF44: =IF('[29]Proforma-Input'!$C$108="Yes",MONTH(O44)&YEAR(O44)=MONTH($C$9)&YEAR($C$9),0) -> 0 | AG44: 3
B45: =IFERROR(DATE(YEAR(B44),MONTH(B44)+1,DAY(B44)),"-") -> - | D45: 31 | E45: =1+E44 -> 7 | F45: =IFERROR(IF(B45<$C$9,IF('[29]Proforma-Input'!$C$108="Yes",K44,K44),0),) -> 0 | G45: =IFERROR(IF(D45=$C$7,K44,IF(AND($D$10="Yes",D45<=$C$10),I45,IF(F45>0,$C$8,))),) -> 0 | H45: =IFERROR(IF(B45<$C$9,IF('[29]Proforma-Input'!$C$108="Yes",H44,),0),) -> 0 | I45: =(H45/12)*F45 -> 0 | J45: =IF(D45=$C$7,0,G45-I45) -> 0 | K45: =IFERROR(F45-J45,) -> 0 | L45: =IF(C45>0,SUM(I45:I56),"-") -> - | M45: =IF(C45>0,SUM(J45:J56),"-") -> - | O45: =IFERROR(DATE(YEAR(O44),MONTH(O44)+1,DAY(O44)),"-") -> 46846 | Q45: =IF(S45>0,1+Q44,) -> 31 | R45: =1+R44 -> 7 | S45: =IF('[29]Proforma-Input'!$C$108="No",X44,IF(AF45=TRUE,$P$3,X44)) -> 9430391.3 | T45: =IF(AND($N$8="Yes",Q45<=$P$8),V45,IF(S45>0,$P$7,)) -> 63236.743 | U45: =$P$4 -> 0.068 | V45: =IF(S45>0,U45/12*S45,0) -> 53438.884 | W45: =T45-V45 -> 9797.8592 | X45: =S45-W45 -> 9420593.4 | Y45: =IF(Q45=1,V45,Y44+V45) -> 1680932.5 | Z45: =IF(Q45=1,W45,Z44+W45) -> 279406.56 | AA45: =$P$9*S45/12 -> 785.86594 | AB45: =$P$10*AA45 -> 196.46649 | AC45: =IF(P45>0,SUM(V45:V56),"-") -> - | AD45: =IF(P45>0,SUM(W45:W56),"-") -> - | AF45: =IF('[29]Proforma-Input'!$C$108="Yes",MONTH(O45)&YEAR(O45)=MONTH($C$9)&YEAR($C$9),0) -> 0 | AG45: 3
B46: =IFERROR(DATE(YEAR(B45),MONTH(B45)+1,DAY(B45)),"-") -> - | D46: 32 | E46: =1+E45 -> 8 | F46: =IFERROR(IF(B46<$C$9,IF('[29]Proforma-Input'!$C$108="Yes",K45,K45),0),) -> 0 | G46: =IFERROR(IF(D46=$C$7,K45,IF(AND($D$10="Yes",D46<=$C$10),I46,IF(F46>0,$C$8,))),) -> 0 | H46: =IFERROR(IF(B46<$C$9,IF('[29]Proforma-Input'!$C$108="Yes",H45,),0),) -> 0 | I46: =(H46/12)*F46 -> 0 | J46: =IF(D46=$C$7,0,G46-I46) -> 0 | K46: =IFERROR(F46-J46,) -> 0 | L46: =IF(C46>0,SUM(I46:I57),"-") -> - | M46: =IF(C46>0,SUM(J46:J57),"-") -> - | O46: =IFERROR(DATE(YEAR(O45),MONTH(O45)+1,DAY(O45)),"-") -> 46876 | Q46: =IF(S46>0,1+Q45,) -> 32 | R46: =1+R45 -> 8 | S46: =IF('[29]Proforma-Input'!$C$108="No",X45,IF(AF46=TRUE,$P$3,X45)) -> 9420593.4 | T46: =IF(AND($N$8="Yes",Q46<=$P$8),V46,IF(S46>0,$P$7,)) -> 63236.743 | U46: =$P$4 -> 0.068 | V46: =IF(S46>0,U46/12*S46,0) -> 53383.363 | W46: =T46-V46 -> 9853.3804 | X46: =S46-W46 -> 9410740.1 | Y46: =IF(Q46=1,V46,Y45+V46) -> 1734315.8 | Z46: =IF(Q46=1,W46,Z45+W46) -> 289259.94 | AA46: =$P$9*S46/12 -> 785.04945 | AB46: =$P$10*AA46 -> 196.26236 | AC46: =IF(P46>0,SUM(V46:V57),"-") -> - | AD46: =IF(P46>0,SUM(W46:W57),"-") -> - | AF46: =IF('[29]Proforma-Input'!$C$108="Yes",MONTH(O46)&YEAR(O46)=MONTH($C$9)&YEAR($C$9),0) -> 0 | AG46: 3
B47: =IFERROR(DATE(YEAR(B46),MONTH(B46)+1,DAY(B46)),"-") -> - | D47: 33 | E47: =1+E46 -> 9 | F47: =IFERROR(IF(B47<$C$9,IF('[29]Proforma-Input'!$C$108="Yes",K46,K46),0),) -> 0 | G47: =IFERROR(IF(D47=$C$7,K46,IF(AND($D$10="Yes",D47<=$C$10),I47,IF(F47>0,$C$8,))),) -> 0 | H47: =IFERROR(IF(B47<$C$9,IF('[29]Proforma-Input'!$C$108="Yes",H46,),0),) -> 0 | I47: =(H47/12)*F47 -> 0 | J47: =IF(D47=$C$7,0,G47-I47) -> 0 | K47: =IFERROR(F47-J47,) -> 0 | L47: =IF(C47>0,SUM(I47:I58),"-") -> - | M47: =IF(C47>0,SUM(J47:J58),"-") -> - | O47: =IFERROR(DATE(YEAR(O46),MONTH(O46)+1,DAY(O46)),"-") -> 46907 | Q47: =IF(S47>0,1+Q46,) -> 33 | R47: =1+R46 -> 9 | S47: =IF('[29]Proforma-Input'!$C$108="No",X46,IF(AF47=TRUE,$P$3,X46)) -> 9410740.1 | T47: =IF(AND($N$8="Yes",Q47<=$P$8),V47,IF(S47>0,$P$7,)) -> 63236.743 | U47: =$P$4 -> 0.068 | V47: =IF(S47>0,U47/12*S47,0) -> 53327.527 | W47: =T47-V47 -> 9909.2162 | X47: =S47-W47 -> 9400830.8 | Y47: =IF(Q47=1,V47,Y46+V47) -> 1787643.4 | Z47: =IF(Q47=1,W47,Z46+W47) -> 299169.16 | AA47: =$P$9*S47/12 -> 784.22834 | AB47: =$P$10*AA47 -> 196.05708 | AC47: =IF(P47>0,SUM(V47:V58),"-") -> - | AD47: =IF(P47>0,SUM(W47:W58),"-") -> - | AF47: =IF('[29]Proforma-Input'!$C$108="Yes",MONTH(O47)&YEAR(O47)=MONTH($C$9)&YEAR($C$9),0) -> 0 | AG47: 3
B48: =IFERROR(DATE(YEAR(B47),MONTH(B47)+1,DAY(B47)),"-") -> - | D48: 34 | E48: =1+E47 -> 10 | F48: =IFERROR(IF(B48<$C$9,IF('[29]Proforma-Input'!$C$108="Yes",K47,K47),0),) -> 0 | G48: =IFERROR(IF(D48=$C$7,K47,IF(AND($D$10="Yes",D48<=$C$10),I48,IF(F48>0,$C$8,))),) -> 0 | H48: =IFERROR(IF(B48<$C$9,IF('[29]Proforma-Input'!$C$108="Yes",H47,),0),) -> 0 | I48: =(H48/12)*F48 -> 0 | J48: =IF(D48=$C$7,0,G48-I48) -> 0 | K48: =IFERROR(F48-J48,) -> 0 | L48: =IF(C48>0,SUM(I48:I59),"-") -> - | M48: =IF(C48>0,SUM(J48:J59),"-") -> - | O48: =IFERROR(DATE(YEAR(O47),MONTH(O47)+1,DAY(O47)),"-") -> 46937 | Q48: =IF(S48>0,1+Q47,) -> 34 | R48: =1+R47 -> 10 | S48: =IF('[29]Proforma-Input'!$C$108="No",X47,IF(AF48=TRUE,$P$3,X47)) -> 9400830.8 | T48: =IF(AND($N$8="Yes",Q48<=$P$8),V48,IF(S48>0,$P$7,)) -> 63236.743 | U48: =$P$4 -> 0.068 | V48: =IF(S48>0,U48/12*S48,0) -> 53271.375 | W48: =T48-V48 -> 9965.3685 | X48: =S48-W48 -> 9390865.5 | Y48: =IF(Q48=1,V48,Y47+V48) -> 1840914.7 | Z48: =IF(Q48=1,W48,Z47+W48) -> 309134.52 | AA48: =$P$9*S48/12 -> 783.40257 | AB48: =$P$10*AA48 -> 195.85064 | AC48: =IF(P48>0,SUM(V48:V59),"-") -> - | AD48: =IF(P48>0,SUM(W48:W59),"-") -> - | AF48: =IF('[29]Proforma-Input'!$C$108="Yes",MONTH(O48)&YEAR(O48)=MONTH($C$9)&YEAR($C$9),0) -> 0 | AG48: 3
B49: =IFERROR(DATE(YEAR(B48),MONTH(B48)+1,DAY(B48)),"-") -> - | D49: 35 | E49: =1+E48 -> 11 | F49: =IFERROR(IF(B49<$C$9,IF('[29]Proforma-Input'!$C$108="Yes",K48,K48),0),) -> 0 | G49: =IFERROR(IF(D49=$C$7,K48,IF(AND($D$10="Yes",D49<=$C$10),I49,IF(F49>0,$C$8,))),) -> 0 | H49: =IFERROR(IF(B49<$C$9,IF('[29]Proforma-Input'!$C$108="Yes",H48,),0),) -> 0 | I49: =(H49/12)*F49 -> 0 | J49: =IF(D49=$C$7,0,G49-I49) -> 0 | K49: =IFERROR(F49-J49,) -> 0 | L49: =IF(C49>0,SUM(I49:I60),"-") -> - | M49: =IF(C49>0,SUM(J49:J60),"-") -> - | O49: =IFERROR(DATE(YEAR(O48),MONTH(O48)+1,DAY(O48)),"-") -> 46968 | Q49: =IF(S49>0,1+Q48,) -> 35 | R49: =1+R48 -> 11 | S49: =IF('[29]Proforma-Input'!$C$108="No",X48,IF(AF49=TRUE,$P$3,X48)) -> 9390865.5 | T49: =IF(AND($N$8="Yes",Q49<=$P$8),V49,IF(S49>0,$P$7,)) -> 63236.743 | U49: =$P$4 -> 0.068 | V49: =IF(S49>0,U49/12*S49,0) -> 53214.904 | W49: =T49-V49 -> 10021.839 | X49: =S49-W49 -> 9380843.6 | Y49: =IF(Q49=1,V49,Y48+V49) -> 1894129.7 | Z49: =IF(Q49=1,W49,Z48+W49) -> 319156.36 | AA49: =$P$9*S49/12 -> 782.57212 | AB49: =$P$10*AA49 -> 195.64303 | AC49: =IF(P49>0,SUM(V49:V60),"-") -> - | AD49: =IF(P49>0,SUM(W49:W60),"-") -> - | AF49: =IF('[29]Proforma-Input'!$C$108="Yes",MONTH(O49)&YEAR(O49)=MONTH($C$9)&YEAR($C$9),0) -> 0 | AG49: 3
B50: =IFERROR(DATE(YEAR(B49),MONTH(B49)+1,DAY(B49)),"-") -> - | D50: 36 | E50: =1+E49 -> 12 | F50: =IFERROR(IF(B50<$C$9,IF('[29]Proforma-Input'!$C$108="Yes",K49,K49),0),) -> 0 | G50: =IFERROR(IF(D50=$C$7,K49,IF(AND($D$10="Yes",D50<=$C$10),I50,IF(F50>0,$C$8,))),) -> 0 | H50: =IFERROR(IF(B50<$C$9,IF('[29]Proforma-Input'!$C$108="Yes",H49,),0),) -> 0 | I50: =(H50/12)*F50 -> 0 | J50: =IF(D50=$C$7,0,G50-I50) -> 0 | K50: =IFERROR(F50-J50,) -> 0 | L50: =IF(C50>0,SUM(I50:I61),"-") -> - | M50: =IF(C50>0,SUM(J50:J61),"-") -> - | O50: =IFERROR(DATE(YEAR(O49),MONTH(O49)+1,DAY(O49)),"-") -> 46999 | Q50: =IF(S50>0,1+Q49,) -> 36 | R50: =1+R49 -> 12 | S50: =IF('[29]Proforma-Input'!$C$108="No",X49,IF(AF50=TRUE,$P$3,X49)) -> 9380843.6 | T50: =IF(AND($N$8="Yes",Q50<=$P$8),V50,IF(S50>0,$P$7,)) -> 63236.743 | U50: =$P$4 -> 0.068 | V50: =IF(S50>0,U50/12*S50,0) -> 53158.114 | W50: =T50-V50 -> 10078.629 | X50: =S50-W50 -> 9370765 | Y50: =IF(Q50=1,V50,Y49+V50) -> 1947287.8 | Z50: =IF(Q50=1,W50,Z49+W50) -> 329234.99 | AA50: =$P$9*S50/12 -> 781.73697 | AB50: =$P$10*AA50 -> 195.43424 | AC50: =IF(P50>0,SUM(V50:V61),"-") -> - | AD50: =IF(P50>0,SUM(W50:W61),"-") -> - | AF50: =IF('[29]Proforma-Input'!$C$108="Yes",MONTH(O50)&YEAR(O50)=MONTH($C$9)&YEAR($C$9),0) -> 0 | AG50: 3
B51: =IFERROR(DATE(YEAR(B50),MONTH(B50)+1,DAY(B50)),"-") -> - | C51: 4 | D51: 37 | E51: 1 | F51: =IFERROR(IF(B51<$C$9,IF('[29]Proforma-Input'!$C$108="Yes",K50,K50),0),) -> 0 | G51: =IFERROR(IF(D51=$C$7,K50,IF(AND($D$10="Yes",D51<=$C$10),I51,IF(F51>0,$C$8,))),) -> 0 | H51: =IFERROR(IF(B51<$C$9,IF('[29]Proforma-Input'!$C$108="Yes",H50,),0),) -> 0 | I51: =(H51/12)*F51 -> 0 | J51: =IF(D51=$C$7,0,G51-I51) -> 0 | K51: =IFERROR(F51-J51,) -> 0 | L51: =IF(C51>0,SUM(I51:I62),"-") -> 0 | M51: =IF(C51>0,SUM(J51:J62),"-") -> 0 | O51: =IFERROR(DATE(YEAR(O50),MONTH(O50)+1,DAY(O50)),"-") -> 47029 | P51: 4 | Q51: =IF(S51>0,1+Q50,) -> 37 | R51: 1 | S51: =IF('[29]Proforma-Input'!$C$108="No",X50,IF(AF51=TRUE,$P$3,X50)) -> 9370765 | T51: =IF(AND($N$8="Yes",Q51<=$P$8),V51,IF(S51>0,$P$7,)) -> 63236.743 | U51: =$P$4 -> 0.068 | V51: =IF(S51>0,U51/12*S51,0) -> 53101.002 | W51: =T51-V51 -> 10135.742 | X51: =S51-W51 -> 9360629.3 | Y51: =IF(Q51=1,V51,Y50+V51) -> 2000388.8 | Z51: =IF(Q51=1,W51,Z50+W51) -> 339370.73 | AA51: =$P$9*S51/12 -> 780.89708 | AB51: =$P$10*AA51 -> 195.22427 | AC51: =IF(P51>0,SUM(V51:V62),"-") -> 633348.73 | AD51: =IF(P51>0,SUM(W51:W62),"-") -> 125492.19 | AF51: =IF('[29]Proforma-Input'!$C$108="Yes",MONTH(O51)&YEAR(O51)=MONTH($C$9)&YEAR($C$9),0) -> 0 | AG51: 4
B52: =IFERROR(DATE(YEAR(B51),MONTH(B51)+1,DAY(B51)),"-") -> - | D52: 38 | E52: =1+E51 -> 2 | F52: =IFERROR(IF(B52<$C$9,IF('[29]Proforma-Input'!$C$108="Yes",K51,K51),0),) -> 0 | G52: =IFERROR(IF(D52=$C$7,K51,IF(AND($D$10="Yes",D52<=$C$10),I52,IF(F52>0,$C$8,))),) -> 0 | H52: =IFERROR(IF(B52<$C$9,IF('[29]Proforma-Input'!$C$108="Yes",H51,),0),) -> 0 | I52: =(H52/12)*F52 -> 0 | J52: =IF(D52=$C$7,0,G52-I52) -> 0 | K52: =IFERROR(F52-J52,) -> 0 | L52: =IF(C52>0,SUM(I52:I63),"-") -> - | M52: =IF(C52>0,SUM(J52:J63),"-") -> - | O52: =IFERROR(DATE(YEAR(O51),MONTH(O51)+1,DAY(O51)),"-") -> 47060 | Q52: =IF(S52>0,1+Q51,) -> 38 | R52: =1+R51 -> 2 | S52: =IF('[29]Proforma-Input'!$C$108="No",X51,IF(AF52=TRUE,$P$3,X51)) -> 9360629.3 | T52: =IF(AND($N$8="Yes",Q52<=$P$8),V52,IF(S52>0,$P$7,)) -> 63236.743 | U52: =$P$4 -> 0.068 | V52: =IF(S52>0,U52/12*S52,0) -> 53043.566 | W52: =T52-V52 -> 10193.177 | X52: =S52-W52 -> 9350436.1 | Y52: =IF(Q52=1,V52,Y51+V52) -> 2053432.3 | Z52: =IF(Q52=1,W52,Z51+W52) -> 349563.91 | AA52: =$P$9*S52/12 -> 780.05244 | AB52: =$P$10*AA52 -> 195.01311 | AC52: =IF(P52>0,SUM(V52:V63),"-") -> - | AD52: =IF(P52>0,SUM(W52:W63),"-") -> - | AF52: =IF('[29]Proforma-Input'!$C$108="Yes",MONTH(O52)&YEAR(O52)=MONTH($C$9)&YEAR($C$9),0) -> 0 | AG52: 4
B53: =IFERROR(DATE(YEAR(B52),MONTH(B52)+1,DAY(B52)),"-") -> - | D53: 39 | E53: =1+E52 -> 3 | F53: =IFERROR(IF(B53<$C$9,IF('[29]Proforma-Input'!$C$108="Yes",K52,K52),0),) -> 0 | G53: =IFERROR(IF(D53=$C$7,K52,IF(AND($D$10="Yes",D53<=$C$10),I53,IF(F53>0,$C$8,))),) -> 0 | H53: =IFERROR(IF(B53<$C$9,IF('[29]Proforma-Input'!$C$108="Yes",H52,),0),) -> 0 | I53: =(H53/12)*F53 -> 0 | J53: =IF(D53=$C$7,0,G53-I53) -> 0 | K53: =IFERROR(F53-J53,) -> 0 | L53: =IF(C53>0,SUM(I53:I64),"-") -> - | M53: =IF(C53>0,SUM(J53:J64),"-") -> - | O53: =IFERROR(DATE(YEAR(O52),MONTH(O52)+1,DAY(O52)),"-") -> 47090 | Q53: =IF(S53>0,1+Q52,) -> 39 | R53: =1+R52 -> 3 | S53: =IF('[29]Proforma-Input'!$C$108="No",X52,IF(AF53=TRUE,$P$3,X52)) -> 9350436.1 | T53: =IF(AND($N$8="Yes",Q53<=$P$8),V53,IF(S53>0,$P$7,)) -> 63236.743 | U53: =$P$4 -> 0.068 | V53: =IF(S53>0,U53/12*S53,0) -> 52985.805 | W53: =T53-V53 -> 10250.939 | X53: =S53-W53 -> 9340185.1 | Y53: =IF(Q53=1,V53,Y52+V53) -> 2106418.1 | Z53: =IF(Q53=1,W53,Z52+W53) -> 359814.85 | AA53: =$P$9*S53/12 -> 779.20301 | AB53: =$P$10*AA53 -> 194.80075 | AC53: =IF(P53>0,SUM(V53:V64),"-") -> - | AD53: =IF(P53>0,SUM(W53:W64),"-") -> - | AF53: =IF('[29]Proforma-Input'!$C$108="Yes",MONTH(O53)&YEAR(O53)=MONTH($C$9)&YEAR($C$9),0) -> 0 | AG53: 4
B54: =IFERROR(DATE(YEAR(B53),MONTH(B53)+1,DAY(B53)),"-") -> - | D54: 40 | E54: =1+E53 -> 4 | F54: =IFERROR(IF(B54<$C$9,IF('[29]Proforma-Input'!$C$108="Yes",K53,K53),0),) -> 0 | G54: =IFERROR(IF(D54=$C$7,K53,IF(AND($D$10="Yes",D54<=$C$10),I54,IF(F54>0,$C$8,))),) -> 0 | H54: =IFERROR(IF(B54<$C$9,IF('[29]Proforma-Input'!$C$108="Yes",H53,),0),) -> 0 | I54: =(H54/12)*F54 -> 0 | J54: =IF(D54=$C$7,0,G54-I54) -> 0 | K54: =IFERROR(F54-J54,) -> 0 | L54: =IF(C54>0,SUM(I54:I65),"-") -> - | M54: =IF(C54>0,SUM(J54:J65),"-") -> - | O54: =IFERROR(DATE(YEAR(O53),MONTH(O53)+1,DAY(O53)),"-") -> 47121 | Q54: =IF(S54>0,1+Q53,) -> 40 | R54: =1+R53 -> 4 | S54: =IF('[29]Proforma-Input'!$C$108="No",X53,IF(AF54=TRUE,$P$3,X53)) -> 9340185.1 | T54: =IF(AND($N$8="Yes",Q54<=$P$8),V54,IF(S54>0,$P$7,)) -> 63236.743 | U54: =$P$4 -> 0.068 | V54: =IF(S54>0,U54/12*S54,0) -> 52927.716 | W54: =T54-V54 -> 10309.027 | X54: =S54-W54 -> 9329876.1 | Y54: =IF(Q54=1,V54,Y53+V54) -> 2159345.9 | Z54: =IF(Q54=1,W54,Z53+W54) -> 370123.88 | AA54: =$P$9*S54/12 -> 778.34876 | AB54: =$P$10*AA54 -> 194.58719 | AC54: =IF(P54>0,SUM(V54:V65),"-") -> - | AD54: =IF(P54>0,SUM(W54:W65),"-") -> - | AF54: =IF('[29]Proforma-Input'!$C$108="Yes",MONTH(O54)&YEAR(O54)=MONTH($C$9)&YEAR($C$9),0) -> 0 | AG54: 4
B55: =IFERROR(DATE(YEAR(B54),MONTH(B54)+1,DAY(B54)),"-") -> - | D55: 41 | E55: =1+E54 -> 5 | F55: =IFERROR(IF(B55<$C$9,IF('[29]Proforma-Input'!$C$108="Yes",K54,K54),0),) -> 0 | G55: =IFERROR(IF(D55=$C$7,K54,IF(AND($D$10="Yes",D55<=$C$10),I55,IF(F55>0,$C$8,))),) -> 0 | H55: =IFERROR(IF(B55<$C$9,IF('[29]Proforma-Input'!$C$108="Yes",H54,),0),) -> 0 | I55: =(H55/12)*F55 -> 0 | J55: =IF(D55=$C$7,0,G55-I55) -> 0 | K55: =IFERROR(F55-J55,) -> 0 | L55: =IF(C55>0,SUM(I55:I66),"-") -> - | M55: =IF(C55>0,SUM(J55:J66),"-") -> - | O55: =IFERROR(DATE(YEAR(O54),MONTH(O54)+1,DAY(O54)),"-") -> 47152 | Q55: =IF(S55>0,1+Q54,) -> 41 | R55: =1+R54 -> 5 | S55: =IF('[29]Proforma-Input'!$C$108="No",X54,IF(AF55=TRUE,$P$3,X54)) -> 9329876.1 | T55: =IF(AND($N$8="Yes",Q55<=$P$8),V55,IF(S55>0,$P$7,)) -> 63236.743 | U55: =$P$4 -> 0.068 | V55: =IF(S55>0,U55/12*S55,0) -> 52869.298 | W55: =T55-V55 -> 10367.445 | X55: =S55-W55 -> 9319508.7 | Y55: =IF(Q55=1,V55,Y54+V55) -> 2212215.2 | Z55: =IF(Q55=1,W55,Z54+W55) -> 380491.32 | AA55: =$P$9*S55/12 -> 777.48968 | AB55: =$P$10*AA55 -> 194.37242 | AC55: =IF(P55>0,SUM(V55:V66),"-") -> - | AD55: =IF(P55>0,SUM(W55:W66),"-") -> - | AF55: =IF('[29]Proforma-Input'!$C$108="Yes",MONTH(O55)&YEAR(O55)=MONTH($C$9)&YEAR($C$9),0) -> 0 | AG55: 4
B56: =IFERROR(DATE(YEAR(B55),MONTH(B55)+1,DAY(B55)),"-") -> - | D56: 42 | E56: =1+E55 -> 6 | F56: =IFERROR(IF(B56<$C$9,IF('[29]Proforma-Input'!$C$108="Yes",K55,K55),0),) -> 0 | G56: =IFERROR(IF(D56=$C$7,K55,IF(AND($D$10="Yes",D56<=$C$10),I56,IF(F56>0,$C$8,))),) -> 0 | H56: =IFERROR(IF(B56<$C$9,IF('[29]Proforma-Input'!$C$108="Yes",H55,),0),) -> 0 | I56: =(H56/12)*F56 -> 0 | J56: =IF(D56=$C$7,0,G56-I56) -> 0 | K56: =IFERROR(F56-J56,) -> 0 | L56: =IF(C56>0,SUM(I56:I67),"-") -> - | M56: =IF(C56>0,SUM(J56:J67),"-") -> - | O56: =IFERROR(DATE(YEAR(O55),MONTH(O55)+1,DAY(O55)),"-") -> 47180 | Q56: =IF(S56>0,1+Q55,) -> 42 | R56: =1+R55 -> 6 | S56: =IF('[29]Proforma-Input'!$C$108="No",X55,IF(AF56=TRUE,$P$3,X55)) -> 9319508.7 | T56: =IF(AND($N$8="Yes",Q56<=$P$8),V56,IF(S56>0,$P$7,)) -> 63236.743 | U56: =$P$4 -> 0.068 | V56: =IF(S56>0,U56/12*S56,0) -> 52810.549 | W56: =T56-V56 -> 10426.194 | X56: =S56-W56 -> 9309082.5 | Y56: =IF(Q56=1,V56,Y55+V56) -> 2265025.7 | Z56: =IF(Q56=1,W56,Z55+W56) -> 390917.52 | AA56: =$P$9*S56/12 -> 776.62572 | AB56: =$P$10*AA56 -> 194.15643 | AC56: =IF(P56>0,SUM(V56:V67),"-") -> - | AD56: =IF(P56>0,SUM(W56:W67),"-") -> - | AF56: =IF('[29]Proforma-Input'!$C$108="Yes",MONTH(O56)&YEAR(O56)=MONTH($C$9)&YEAR($C$9),0) -> 0 | AG56: 4
B57: =IFERROR(DATE(YEAR(B56),MONTH(B56)+1,DAY(B56)),"-") -> - | D57: 43 | E57: =1+E56 -> 7 | F57: =IFERROR(IF(B57<$C$9,IF('[29]Proforma-Input'!$C$108="Yes",K56,K56),0),) -> 0 | G57: =IFERROR(IF(D57=$C$7,K56,IF(AND($D$10="Yes",D57<=$C$10),I57,IF(F57>0,$C$8,))),) -> 0 | H57: =IFERROR(IF(B57<$C$9,IF('[29]Proforma-Input'!$C$108="Yes",H56,),0),) -> 0 | I57: =(H57/12)*F57 -> 0 | J57: =IF(D57=$C$7,0,G57-I57) -> 0 | K57: =IFERROR(F57-J57,) -> 0 | L57: =IF(C57>0,SUM(I57:I68),"-") -> - | M57: =IF(C57>0,SUM(J57:J68),"-") -> - | O57: =IFERROR(DATE(YEAR(O56),MONTH(O56)+1,DAY(O56)),"-") -> 47211 | Q57: =IF(S57>0,1+Q56,) -> 43 | R57: =1+R56 -> 7 | S57: =IF('[29]Proforma-Input'!$C$108="No",X56,IF(AF57=TRUE,$P$3,X56)) -> 9309082.5 | T57: =IF(AND($N$8="Yes",Q57<=$P$8),V57,IF(S57>0,$P$7,)) -> 63236.743 | U57: =$P$4 -> 0.068 | V57: =IF(S57>0,U57/12*S57,0) -> 52751.467 | W57: =T57-V57 -> 10485.276 | X57: =S57-W57 -> 9298597.2 | Y57: =IF(Q57=1,V57,Y56+V57) -> 2317777.2 | Z57: =IF(Q57=1,W57,Z56+W57) -> 401402.79 | AA57: =$P$9*S57/12 -> 775.75687 | AB57: =$P$10*AA57 -> 193.93922 | AC57: =IF(P57>0,SUM(V57:V68),"-") -> - | AD57: =IF(P57>0,SUM(W57:W68),"-") -> - | AF57: =IF('[29]Proforma-Input'!$C$108="Yes",MONTH(O57)&YEAR(O57)=MONTH($C$9)&YEAR($C$9),0) -> 0 | AG57: 4
B58: =IFERROR(DATE(YEAR(B57),MONTH(B57)+1,DAY(B57)),"-") -> - | D58: 44 | E58: =1+E57 -> 8 | F58: =IFERROR(IF(B58<$C$9,IF('[29]Proforma-Input'!$C$108="Yes",K57,K57),0),) -> 0 | G58: =IFERROR(IF(D58=$C$7,K57,IF(AND($D$10="Yes",D58<=$C$10),I58,IF(F58>0,$C$8,))),) -> 0 | H58: =IFERROR(IF(B58<$C$9,IF('[29]Proforma-Input'!$C$108="Yes",H57,),0),) -> 0 | I58: =(H58/12)*F58 -> 0 | J58: =IF(D58=$C$7,0,G58-I58) -> 0 | K58: =IFERROR(F58-J58,) -> 0 | L58: =IF(C58>0,SUM(I58:I69),"-") -> - | M58: =IF(C58>0,SUM(J58:J69),"-") -> - | O58: =IFERROR(DATE(YEAR(O57),MONTH(O57)+1,DAY(O57)),"-") -> 47241 | Q58: =IF(S58>0,1+Q57,) -> 44 | R58: =1+R57 -> 8 | S58: =IF('[29]Proforma-Input'!$C$108="No",X57,IF(AF58=TRUE,$P$3,X57)) -> 9298597.2 | T58: =IF(AND($N$8="Yes",Q58<=$P$8),V58,IF(S58>0,$P$7,)) -> 63236.743 | U58: =$P$4 -> 0.068 | V58: =IF(S58>0,U58/12*S58,0) -> 52692.051 | W58: =T58-V58 -> 10544.692 | X58: =S58-W58 -> 9288052.5 | Y58: =IF(Q58=1,V58,Y57+V58) -> 2370469.2 | Z58: =IF(Q58=1,W58,Z57+W58) -> 411947.49 | AA58: =$P$9*S58/12 -> 774.8831 | AB58: =$P$10*AA58 -> 193.72078 | AC58: =IF(P58>0,SUM(V58:V69),"-") -> - | AD58: =IF(P58>0,SUM(W58:W69),"-") -> - | AF58: =IF('[29]Proforma-Input'!$C$108="Yes",MONTH(O58)&YEAR(O58)=MONTH($C$9)&YEAR($C$9),0) -> 0 | AG58: 4
B59: =IFERROR(DATE(YEAR(B58),MONTH(B58)+1,DAY(B58)),"-") -> - | D59: 45 | E59: =1+E58 -> 9 | F59: =IFERROR(IF(B59<$C$9,IF('[29]Proforma-Input'!$C$108="Yes",K58,K58),0),) -> 0 | G59: =IFERROR(IF(D59=$C$7,K58,IF(AND($D$10="Yes",D59<=$C$10),I59,IF(F59>0,$C$8,))),) -> 0 | H59: =IFERROR(IF(B59<$C$9,IF('[29]Proforma-Input'!$C$108="Yes",H58,),0),) -> 0 | I59: =(H59/12)*F59 -> 0 | J59: =IF(D59=$C$7,0,G59-I59) -> 0 | K59: =IFERROR(F59-J59,) -> 0 | L59: =IF(C59>0,SUM(I59:I70),"-") -> - | M59: =IF(C59>0,SUM(J59:J70),"-") -> - | O59: =IFERROR(DATE(YEAR(O58),MONTH(O58)+1,DAY(O58)),"-") -> 47272 | Q59: =IF(S59>0,1+Q58,) -> 45 | R59: =1+R58 -> 9 | S59: =IF('[29]Proforma-Input'!$C$108="No",X58,IF(AF59=TRUE,$P$3,X58)) -> 9288052.5 | T59: =IF(AND($N$8="Yes",Q59<=$P$8),V59,IF(S59>0,$P$7,)) -> 63236.743 | U59: =$P$4 -> 0.068 | V59: =IF(S59>0,U59/12*S59,0) -> 52632.298 | W59: =T59-V59 -> 10604.446 | X59: =S59-W59 -> 9277448.1 | Y59: =IF(Q59=1,V59,Y58+V59) -> 2423101.5 | Z59: =IF(Q59=1,W59,Z58+W59) -> 422551.93 | AA59: =$P$9*S59/12 -> 774.00438 | AB59: =$P$10*AA59 -> 193.50109 | AC59: =IF(P59>0,SUM(V59:V70),"-") -> - | AD59: =IF(P59>0,SUM(W59:W70),"-") -> - | AF59: =IF('[29]Proforma-Input'!$C$108="Yes",MONTH(O59)&YEAR(O59)=MONTH($C$9)&YEAR($C$9),0) -> 0 | AG59: 4
B60: =IFERROR(DATE(YEAR(B59),MONTH(B59)+1,DAY(B59)),"-") -> - | D60: 46 | E60: =1+E59 -> 10 | F60: =IFERROR(IF(B60<$C$9,IF('[29]Proforma-Input'!$C$108="Yes",K59,K59),0),) -> 0 | G60: =IFERROR(IF(D60=$C$7,K59,IF(AND($D$10="Yes",D60<=$C$10),I60,IF(F60>0,$C$8,))),) -> 0 | H60: =IFERROR(IF(B60<$C$9,IF('[29]Proforma-Input'!$C$108="Yes",H59,),0),) -> 0 | I60: =(H60/12)*F60 -> 0 | J60: =IF(D60=$C$7,0,G60-I60) -> 0 | K60: =IFERROR(F60-J60,) -> 0 | L60: =IF(C60>0,SUM(I60:I71),"-") -> - | M60: =IF(C60>0,SUM(J60:J71),"-") -> - | O60: =IFERROR(DATE(YEAR(O59),MONTH(O59)+1,DAY(O59)),"-") -> 47302 | Q60: =IF(S60>0,1+Q59,) -> 46 | R60: =1+R59 -> 10 | S60: =IF('[29]Proforma-Input'!$C$108="No",X59,IF(AF60=TRUE,$P$3,X59)) -> 9277448.1 | T60: =IF(AND($N$8="Yes",Q60<=$P$8),V60,IF(S60>0,$P$7,)) -> 63236.743 | U60: =$P$4 -> 0.068 | V60: =IF(S60>0,U60/12*S60,0) -> 52572.206 | W60: =T60-V60 -> 10664.538 | X60: =S60-W60 -> 9266783.5 | Y60: =IF(Q60=1,V60,Y59+V60) -> 2475673.7 | Z60: =IF(Q60=1,W60,Z59+W60) -> 433216.47 | AA60: =$P$9*S60/12 -> 773.12067 | AB60: =$P$10*AA60 -> 193.28017 | AC60: =IF(P60>0,SUM(V60:V71),"-") -> - | AD60: =IF(P60>0,SUM(W60:W71),"-") -> - | AF60: =IF('[29]Proforma-Input'!$C$108="Yes",MONTH(O60)&YEAR(O60)=MONTH($C$9)&YEAR($C$9),0) -> 0 | AG60: 4
B61: =IFERROR(DATE(YEAR(B60),MONTH(B60)+1,DAY(B60)),"-") -> - | D61: 47 | E61: =1+E60 -> 11 | F61: =IFERROR(IF(B61<$C$9,IF('[29]Proforma-Input'!$C$108="Yes",K60,K60),0),) -> 0 | G61: =IFERROR(IF(D61=$C$7,K60,IF(AND($D$10="Yes",D61<=$C$10),I61,IF(F61>0,$C$8,))),) -> 0 | H61: =IFERROR(IF(B61<$C$9,IF('[29]Proforma-Input'!$C$108="Yes",H60,),0),) -> 0 | I61: =(H61/12)*F61 -> 0 | J61: =IF(D61=$C$7,0,G61-I61) -> 0 | K61: =IFERROR(F61-J61,) -> 0 | L61: =IF(C61>0,SUM(I61:I72),"-") -> - | M61: =IF(C61>0,SUM(J61:J72),"-") -> - | O61: =IFERROR(DATE(YEAR(O60),MONTH(O60)+1,DAY(O60)),"-") -> 47333 | Q61: =IF(S61>0,1+Q60,) -> 47 | R61: =1+R60 -> 11 | S61: =IF('[29]Proforma-Input'!$C$108="No",X60,IF(AF61=TRUE,$P$3,X60)) -> 9266783.5 | T61: =IF(AND($N$8="Yes",Q61<=$P$8),V61,IF(S61>0,$P$7,)) -> 63236.743 | U61: =$P$4 -> 0.068 | V61: =IF(S61>0,U61/12*S61,0) -> 52511.773 | W61: =T61-V61 -> 10724.97 | X61: =S61-W61 -> 9256058.6 | Y61: =IF(Q61=1,V61,Y60+V61) -> 2528185.5 | Z61: =IF(Q61=1,W61,Z60+W61) -> 443941.44 | AA61: =$P$9*S61/12 -> 772.23196 | AB61: =$P$10*AA61 -> 193.05799 | AC61: =IF(P61>0,SUM(V61:V72),"-") -> - | AD61: =IF(P61>0,SUM(W61:W72),"-") -> - | AF61: =IF('[29]Proforma-Input'!$C$108="Yes",MONTH(O61)&YEAR(O61)=MONTH($C$9)&YEAR($C$9),0) -> 0 | AG61: 4
B62: =IFERROR(DATE(YEAR(B61),MONTH(B61)+1,DAY(B61)),"-") -> - | D62: 48 | E62: =1+E61 -> 12 | F62: =IFERROR(IF(B62<$C$9,IF('[29]Proforma-Input'!$C$108="Yes",K61,K61),0),) -> 0 | G62: =IFERROR(IF(D62=$C$7,K61,IF(AND($D$10="Yes",D62<=$C$10),I62,IF(F62>0,$C$8,))),) -> 0 | H62: =IFERROR(IF(B62<$C$9,IF('[29]Proforma-Input'!$C$108="Yes",H61,),0),) -> 0 | I62: =(H62/12)*F62 -> 0 | J62: =IF(D62=$C$7,0,G62-I62) -> 0 | K62: =IFERROR(F62-J62,) -> 0 | L62: =IF(C62>0,SUM(I62:I73),"-") -> - | M62: =IF(C62>0,SUM(J62:J73),"-") -> - | O62: =IFERROR(DATE(YEAR(O61),MONTH(O61)+1,DAY(O61)),"-") -> 47364 | Q62: =IF(S62>0,1+Q61,) -> 48 | R62: =1+R61 -> 12 | S62: =IF('[29]Proforma-Input'!$C$108="No",X61,IF(AF62=TRUE,$P$3,X61)) -> 9256058.6 | T62: =IF(AND($N$8="Yes",Q62<=$P$8),V62,IF(S62>0,$P$7,)) -> 63236.743 | U62: =$P$4 -> 0.068 | V62: =IF(S62>0,U62/12*S62,0) -> 52450.999 | W62: =T62-V62 -> 10785.745 | X62: =S62-W62 -> 9245272.8 | Y62: =IF(Q62=1,V62,Y61+V62) -> 2580636.5 | Z62: =IF(Q62=1,W62,Z61+W62) -> 454727.18 | AA62: =$P$9*S62/12 -> 771.33821 | AB62: =$P$10*AA62 -> 192.83455 | AC62: =IF(P62>0,SUM(V62:V73),"-") -> - | AD62: =IF(P62>0,SUM(W62:W73),"-") -> - | AF62: =IF('[29]Proforma-Input'!$C$108="Yes",MONTH(O62)&YEAR(O62)=MONTH($C$9)&YEAR($C$9),0) -> 0 | AG62: 4
B63: =IFERROR(DATE(YEAR(B62),MONTH(B62)+1,DAY(B62)),"-") -> - | C63: 5 | D63: 49 | E63: 1 | F63: =IFERROR(IF(B63<$C$9,IF('[29]Proforma-Input'!$C$108="Yes",K62,K62),0),) -> 0 | G63: =IFERROR(IF(D63=$C$7,K62,IF(AND($D$10="Yes",D63<=$C$10),I63,IF(F63>0,$C$8,))),) -> 0 | H63: =IFERROR(IF(B63<$C$9,IF('[29]Proforma-Input'!$C$108="Yes",H62,),0),) -> 0 | I63: =(H63/12)*F63 -> 0 | J63: =IF(D63=$C$7,0,G63-I63) -> 0 | K63: =IFERROR(F63-J63,) -> 0 | L63: =IF(C63>0,SUM(I63:I74),"-") -> 0 | M63: =IF(C63>0,SUM(J63:J74),"-") -> 0 | O63: =IFERROR(DATE(YEAR(O62),MONTH(O62)+1,DAY(O62)),"-") -> 47394 | P63: 5 | Q63: =IF(S63>0,1+Q62,) -> 49 | R63: 1 | S63: =IF('[29]Proforma-Input'!$C$108="No",X62,IF(AF63=TRUE,$P$3,X62)) -> 9245272.8 | T63: =IF(AND($N$8="Yes",Q63<=$P$8),V63,IF(S63>0,$P$7,)) -> 63236.743 | U63: =$P$4 -> 0.068 | V63: =IF(S63>0,U63/12*S63,0) -> 52389.879 | W63: =T63-V63 -> 10846.864 | X63: =S63-W63 -> 9234426 | Y63: =IF(Q63=1,V63,Y62+V63) -> 2633026.4 | Z63: =IF(Q63=1,W63,Z62+W63) -> 465574.05 | AA63: =$P$9*S63/12 -> 770.4394 | AB63: =$P$10*AA63 -> 192.60985 | AC63: =IF(P63>0,SUM(V63:V74),"-") -> 624544.21 | AD63: =IF(P63>0,SUM(W63:W74),"-") -> 134296.71 | AF63: =IF('[29]Proforma-Input'!$C$108="Yes",MONTH(O63)&YEAR(O63)=MONTH($C$9)&YEAR($C$9),0) -> 0 | AG63: 5
B64: =IFERROR(DATE(YEAR(B63),MONTH(B63)+1,DAY(B63)),"-") -> - | D64: 50 | E64: =1+E63 -> 2 | F64: =IFERROR(IF(B64<$C$9,IF('[29]Proforma-Input'!$C$108="Yes",K63,K63),0),) -> 0 | G64: =IFERROR(IF(D64=$C$7,K63,IF(AND($D$10="Yes",D64<=$C$10),I64,IF(F64>0,$C$8,))),) -> 0 | H64: =IFERROR(IF(B64<$C$9,IF('[29]Proforma-Input'!$C$108="Yes",H63,),0),) -> 0 | I64: =(H64/12)*F64 -> 0 | J64: =IF(D64=$C$7,0,G64-I64) -> 0 | K64: =IFERROR(F64-J64,) -> 0 | L64: =IF(C64>0,SUM(I64:I75),"-") -> - | M64: =IF(C64>0,SUM(J64:J75),"-") -> - | O64: =IFERROR(DATE(YEAR(O63),MONTH(O63)+1,DAY(O63)),"-") -> 47425 | Q64: =IF(S64>0,1+Q63,) -> 50 | R64: =1+R63 -> 2 | S64: =IF('[29]Proforma-Input'!$C$108="No",X63,IF(AF64=TRUE,$P$3,X63)) -> 9234426 | T64: =IF(AND($N$8="Yes",Q64<=$P$8),V64,IF(S64>0,$P$7,)) -> 63236.743 | U64: =$P$4 -> 0.068 | V64: =IF(S64>0,U64/12*S64,0) -> 52328.414 | W64: =T64-V64 -> 10908.33 | X64: =S64-W64 -> 9223517.6 | Y64: =IF(Q64=1,V64,Y63+V64) -> 2685354.8 | Z64: =IF(Q64=1,W64,Z63+W64) -> 476482.38 | AA64: =$P$9*S64/12 -> 769.5355 | AB64: =$P$10*AA64 -> 192.38387 | AC64: =IF(P64>0,SUM(V64:V75),"-") -> - | AD64: =IF(P64>0,SUM(W64:W75),"-") -> - | AF64: =IF('[29]Proforma-Input'!$C$108="Yes",MONTH(O64)&YEAR(O64)=MONTH($C$9)&YEAR($C$9),0) -> 0 | AG64: 5
B65: =IFERROR(DATE(YEAR(B64),MONTH(B64)+1,DAY(B64)),"-") -> - | D65: 51 | E65: =1+E64 -> 3 | F65: =IFERROR(IF(B65<$C$9,IF('[29]Proforma-Input'!$C$108="Yes",K64,K64),0),) -> 0 | G65: =IFERROR(IF(D65=$C$7,K64,IF(AND($D$10="Yes",D65<=$C$10),I65,IF(F65>0,$C$8,))),) -> 0 | H65: =IFERROR(IF(B65<$C$9,IF('[29]Proforma-Input'!$C$108="Yes",H64,),0),) -> 0 | I65: =(H65/12)*F65 -> 0 | J65: =IF(D65=$C$7,0,G65-I65) -> 0 | K65: =IFERROR(F65-J65,) -> 0 | L65: =IF(C65>0,SUM(I65:I76),"-") -> - | M65: =IF(C65>0,SUM(J65:J76),"-") -> - | O65: =IFERROR(DATE(YEAR(O64),MONTH(O64)+1,DAY(O64)),"-") -> 47455 | Q65: =IF(S65>0,1+Q64,) -> 51 | R65: =1+R64 -> 3 | S65: =IF('[29]Proforma-Input'!$C$108="No",X64,IF(AF65=TRUE,$P$3,X64)) -> 9223517.6 | T65: =IF(AND($N$8="Yes",Q65<=$P$8),V65,IF(S65>0,$P$7,)) -> 63236.743 | U65: =$P$4 -> 0.068 | V65: =IF(S65>0,U65/12*S65,0) -> 52266.6 | W65: =T65-V65 -> 10970.143 | X65: =S65-W65 -> 9212547.5 | Y65: =IF(Q65=1,V65,Y64+V65) -> 2737621.4 | Z65: =IF(Q65=1,W65,Z64+W65) -> 487452.52 | AA65: =$P$9*S65/12 -> 768.62647 | AB65: =$P$10*AA65 -> 192.15662 | AC65: =IF(P65>0,SUM(V65:V76),"-") -> - | AD65: =IF(P65>0,SUM(W65:W76),"-") -> - | AF65: =IF('[29]Proforma-Input'!$C$108="Yes",MONTH(O65)&YEAR(O65)=MONTH($C$9)&YEAR($C$9),0) -> 0 | AG65: 5
B66: =IFERROR(DATE(YEAR(B65),MONTH(B65)+1,DAY(B65)),"-") -> - | D66: 52 | E66: =1+E65 -> 4 | F66: =IFERROR(IF(B66<$C$9,IF('[29]Proforma-Input'!$C$108="Yes",K65,K65),0),) -> 0 | G66: =IFERROR(IF(D66=$C$7,K65,IF(AND($D$10="Yes",D66<=$C$10),I66,IF(F66>0,$C$8,))),) -> 0 | H66: =IFERROR(IF(B66<$C$9,IF('[29]Proforma-Input'!$C$108="Yes",H65,),0),) -> 0 | I66: =(H66/12)*F66 -> 0 | J66: =IF(D66=$C$7,0,G66-I66) -> 0 | K66: =IFERROR(F66-J66,) -> 0 | L66: =IF(C66>0,SUM(I66:I77),"-") -> - | M66: =IF(C66>0,SUM(J66:J77),"-") -> - | O66: =IFERROR(DATE(YEAR(O65),MONTH(O65)+1,DAY(O65)),"-") -> 47486 | Q66: =IF(S66>0,1+Q65,) -> 52 | R66: =1+R65 -> 4 | S66: =IF('[29]Proforma-Input'!$C$108="No",X65,IF(AF66=TRUE,$P$3,X65)) -> 9212547.5 | T66: =IF(AND($N$8="Yes",Q66<=$P$8),V66,IF(S66>0,$P$7,)) -> 63236.743 | U66: =$P$4 -> 0.068 | V66: =IF(S66>0,U66/12*S66,0) -> 52204.436 | W66: =T66-V66 -> 11032.308 | X66: =S66-W66 -> 9201515.2 | Y66: =IF(Q66=1,V66,Y65+V66) -> 2789825.8 | Z66: =IF(Q66=1,W66,Z65+W66) -> 498484.83 | AA66: =$P$9*S66/12 -> 767.71229 | AB66: =$P$10*AA66 -> 191.92807 | AC66: =IF(P66>0,SUM(V66:V77),"-") -> - | AD66: =IF(P66>0,SUM(W66:W77),"-") -> - | AF66: =IF('[29]Proforma-Input'!$C$108="Yes",MONTH(O66)&YEAR(O66)=MONTH($C$9)&YEAR($C$9),0) -> 0 | AG66: 5
B67: =IFERROR(DATE(YEAR(B66),MONTH(B66)+1,DAY(B66)),"-") -> - | D67: 53 | E67: =1+E66 -> 5 | F67: =IFERROR(IF(B67<$C$9,IF('[29]Proforma-Input'!$C$108="Yes",K66,K66),0),) -> 0 | G67: =IFERROR(IF(D67=$C$7,K66,IF(AND($D$10="Yes",D67<=$C$10),I67,IF(F67>0,$C$8,))),) -> 0 | H67: =IFERROR(IF(B67<$C$9,IF('[29]Proforma-Input'!$C$108="Yes",H66,),0),) -> 0 | I67: =(H67/12)*F67 -> 0 | J67: =IF(D67=$C$7,0,G67-I67) -> 0 | K67: =IFERROR(F67-J67,) -> 0 | L67: =IF(C67>0,SUM(I67:I78),"-") -> - | M67: =IF(C67>0,SUM(J67:J78),"-") -> - | O67: =IFERROR(DATE(YEAR(O66),MONTH(O66)+1,DAY(O66)),"-") -> 47517 | Q67: =IF(S67>0,1+Q66,) -> 53 | R67: =1+R66 -> 5 | S67: =IF('[29]Proforma-Input'!$C$108="No",X66,IF(AF67=TRUE,$P$3,X66)) -> 9201515.2 | T67: =IF(AND($N$8="Yes",Q67<=$P$8),V67,IF(S67>0,$P$7,)) -> 63236.743 | U67: =$P$4 -> 0.068 | V67: =IF(S67>0,U67/12*S67,0) -> 52141.919 | W67: =T67-V67 -> 11094.824 | X67: =S67-W67 -> 9190420.3 | Y67: =IF(Q67=1,V67,Y66+V67) -> 2841967.7 | Z67: =IF(Q67=1,W67,Z66+W67) -> 509579.65 | AA67: =$P$9*S67/12 -> 766.79293 | AB67: =$P$10*AA67 -> 191.69823 | AC67: =IF(P67>0,SUM(V67:V78),"-") -> - | AD67: =IF(P67>0,SUM(W67:W78),"-") -> - | AF67: =IF('[29]Proforma-Input'!$C$108="Yes",MONTH(O67)&YEAR(O67)=MONTH($C$9)&YEAR($C$9),0) -> 0 | AG67: 5
B68: =IFERROR(DATE(YEAR(B67),MONTH(B67)+1,DAY(B67)),"-") -> - | D68: 54 | E68: =1+E67 -> 6 | F68: =IFERROR(IF(B68<$C$9,IF('[29]Proforma-Input'!$C$108="Yes",K67,K67),0),) -> 0 | G68: =IFERROR(IF(D68=$C$7,K67,IF(AND($D$10="Yes",D68<=$C$10),I68,IF(F68>0,$C$8,))),) -> 0 | H68: =IFERROR(IF(B68<$C$9,IF('[29]Proforma-Input'!$C$108="Yes",H67,),0),) -> 0 | I68: =(H68/12)*F68 -> 0 | J68: =IF(D68=$C$7,0,G68-I68) -> 0 | K68: =IFERROR(F68-J68,) -> 0 | L68: =IF(C68>0,SUM(I68:I79),"-") -> - | M68: =IF(C68>0,SUM(J68:J79),"-") -> - | O68: =IFERROR(DATE(YEAR(O67),MONTH(O67)+1,DAY(O67)),"-") -> 47545 | Q68: =IF(S68>0,1+Q67,) -> 54 | R68: =1+R67 -> 6 | S68: =IF('[29]Proforma-Input'!$C$108="No",X67,IF(AF68=TRUE,$P$3,X67)) -> 9190420.3 | T68: =IF(AND($N$8="Yes",Q68<=$P$8),V68,IF(S68>0,$P$7,)) -> 63236.743 | U68: =$P$4 -> 0.068 | V68: =IF(S68>0,U68/12*S68,0) -> 52079.049 | W68: =T68-V68 -> 11157.695 | X68: =S68-W68 -> 9179262.7 | Y68: =IF(Q68=1,V68,Y67+V68) -> 2894046.8 | Z68: =IF(Q68=1,W68,Z67+W68) -> 520737.35 | AA68: =$P$9*S68/12 -> 765.86836 | AB68: =$P$10*AA68 -> 191.46709 | AC68: =IF(P68>0,SUM(V68:V79),"-") -> - | AD68: =IF(P68>0,SUM(W68:W79),"-") -> - | AF68: =IF('[29]Proforma-Input'!$C$108="Yes",MONTH(O68)&YEAR(O68)=MONTH($C$9)&YEAR($C$9),0) -> 0 | AG68: 5
B69: =IFERROR(DATE(YEAR(B68),MONTH(B68)+1,DAY(B68)),"-") -> - | D69: 55 | E69: =1+E68 -> 7 | F69: =IFERROR(IF(B69<$C$9,IF('[29]Proforma-Input'!$C$108="Yes",K68,K68),0),) -> 0 | G69: =IFERROR(IF(D69=$C$7,K68,IF(AND($D$10="Yes",D69<=$C$10),I69,IF(F69>0,$C$8,))),) -> 0 | H69: =IFERROR(IF(B69<$C$9,IF('[29]Proforma-Input'!$C$108="Yes",H68,),0),) -> 0 | I69: =(H69/12)*F69 -> 0 | J69: =IF(D69=$C$7,0,G69-I69) -> 0 | K69: =IFERROR(F69-J69,) -> 0 | L69: =IF(C69>0,SUM(I69:I80),"-") -> - | M69: =IF(C69>0,SUM(J69:J80),"-") -> - | O69: =IFERROR(DATE(YEAR(O68),MONTH(O68)+1,DAY(O68)),"-") -> 47576 | Q69: =IF(S69>0,1+Q68,) -> 55 | R69: =1+R68 -> 7 | S69: =IF('[29]Proforma-Input'!$C$108="No",X68,IF(AF69=TRUE,$P$3,X68)) -> 9179262.7 | T69: =IF(AND($N$8="Yes",Q69<=$P$8),V69,IF(S69>0,$P$7,)) -> 63236.743 | U69: =$P$4 -> 0.068 | V69: =IF(S69>0,U69/12*S69,0) -> 52015.822 | W69: =T69-V69 -> 11220.922 | X69: =S69-W69 -> 9168041.7 | Y69: =IF(Q69=1,V69,Y68+V69) -> 2946062.6 | Z69: =IF(Q69=1,W69,Z68+W69) -> 531958.27 | AA69: =$P$9*S69/12 -> 764.93855 | AB69: =$P$10*AA69 -> 191.23464 | AC69: =IF(P69>0,SUM(V69:V80),"-") -> - | AD69: =IF(P69>0,SUM(W69:W80),"-") -> - | AF69: =IF('[29]Proforma-Input'!$C$108="Yes",MONTH(O69)&YEAR(O69)=MONTH($C$9)&YEAR($C$9),0) -> 0 | AG69: 5
B70: =IFERROR(DATE(YEAR(B69),MONTH(B69)+1,DAY(B69)),"-") -> - | D70: 56 | E70: =1+E69 -> 8 | F70: =IFERROR(IF(B70<$C$9,IF('[29]Proforma-Input'!$C$108="Yes",K69,K69),0),) -> 0 | G70: =IFERROR(IF(D70=$C$7,K69,IF(AND($D$10="Yes",D70<=$C$10),I70,IF(F70>0,$C$8,))),) -> 0 | H70: =IFERROR(IF(B70<$C$9,IF('[29]Proforma-Input'!$C$108="Yes",H69,),0),) -> 0 | I70: =(H70/12)*F70 -> 0 | J70: =IF(D70=$C$7,0,G70-I70) -> 0 | K70: =IFERROR(F70-J70,) -> 0 | L70: =IF(C70>0,SUM(I70:I81),"-") -> - | M70: =IF(C70>0,SUM(J70:J81),"-") -> - | O70: =IFERROR(DATE(YEAR(O69),MONTH(O69)+1,DAY(O69)),"-") -> 47606 | Q70: =IF(S70>0,1+Q69,) -> 56 | R70: =1+R69 -> 8 | S70: =IF('[29]Proforma-Input'!$C$108="No",X69,IF(AF70=TRUE,$P$3,X69)) -> 9168041.7 | T70: =IF(AND($N$8="Yes",Q70<=$P$8),V70,IF(S70>0,$P$7,)) -> 63236.743 | U70: =$P$4 -> 0.068 | V70: =IF(S70>0,U70/12*S70,0) -> 51952.236 | W70: =T70-V70 -> 11284.507 | X70: =S70-W70 -> 9156757.2 | Y70: =IF(Q70=1,V70,Y69+V70) -> 2998014.8 | Z70: =IF(Q70=1,W70,Z69+W70) -> 543242.77 | AA70: =$P$9*S70/12 -> 764.00348 | AB70: =$P$10*AA70 -> 191.00087 | AC70: =IF(P70>0,SUM(V70:V81),"-") -> - | AD70: =IF(P70>0,SUM(W70:W81),"-") -> - | AF70: =IF('[29]Proforma-Input'!$C$108="Yes",MONTH(O70)&YEAR(O70)=MONTH($C$9)&YEAR($C$9),0) -> 0 | AG70: 5
B71: =IFERROR(DATE(YEAR(B70),MONTH(B70)+1,DAY(B70)),"-") -> - | D71: 57 | E71: =1+E70 -> 9 | F71: =IFERROR(IF(B71<$C$9,IF('[29]Proforma-Input'!$C$108="Yes",K70,K70),0),) -> 0 | G71: =IFERROR(IF(D71=$C$7,K70,IF(AND($D$10="Yes",D71<=$C$10),I71,IF(F71>0,$C$8,))),) -> 0 | H71: =IFERROR(IF(B71<$C$9,IF('[29]Proforma-Input'!$C$108="Yes",H70,),0),) -> 0 | I71: =(H71/12)*F71 -> 0 | J71: =IF(D71=$C$7,0,G71-I71) -> 0 | K71: =IFERROR(F71-J71,) -> 0 | L71: =IF(C71>0,SUM(I71:I82),"-") -> - | M71: =IF(C71>0,SUM(J71:J82),"-") -> - | O71: =IFERROR(DATE(YEAR(O70),MONTH(O70)+1,DAY(O70)),"-") -> 47637 | Q71: =IF(S71>0,1+Q70,) -> 57 | R71: =1+R70 -> 9 | S71: =IF('[29]Proforma-Input'!$C$108="No",X70,IF(AF71=TRUE,$P$3,X70)) -> 9156757.2 | T71: =IF(AND($N$8="Yes",Q71<=$P$8),V71,IF(S71>0,$P$7,)) -> 63236.743 | U71: =$P$4 -> 0.068 | V71: =IF(S71>0,U71/12*S71,0) -> 51888.291 | W71: =T71-V71 -> 11348.452 | X71: =S71-W71 -> 9145408.8 | Y71: =IF(Q71=1,V71,Y70+V71) -> 3049903.1 | Z71: =IF(Q71=1,W71,Z70+W71) -> 554591.23 | AA71: =$P$9*S71/12 -> 763.0631 | AB71: =$P$10*AA71 -> 190.76578 | AC71: =IF(P71>0,SUM(V71:V82),"-") -> - | AD71: =IF(P71>0,SUM(W71:W82),"-") -> - | AF71: =IF('[29]Proforma-Input'!$C$108="Yes",MONTH(O71)&YEAR(O71)=MONTH($C$9)&YEAR($C$9),0) -> 0 | AG71: 5
B72: =IFERROR(DATE(YEAR(B71),MONTH(B71)+1,DAY(B71)),"-") -> - | D72: 58 | E72: =1+E71 -> 10 | F72: =IFERROR(IF(B72<$C$9,IF('[29]Proforma-Input'!$C$108="Yes",K71,K71),0),) -> 0 | G72: =IFERROR(IF(D72=$C$7,K71,IF(AND($D$10="Yes",D72<=$C$10),I72,IF(F72>0,$C$8,))),) -> 0 | H72: =IFERROR(IF(B72<$C$9,IF('[29]Proforma-Input'!$C$108="Yes",H71,),0),) -> 0 | I72: =(H72/12)*F72 -> 0 | J72: =IF(D72=$C$7,0,G72-I72) -> 0 | K72: =IFERROR(F72-J72,) -> 0 | L72: =IF(C72>0,SUM(I72:I83),"-") -> - | M72: =IF(C72>0,SUM(J72:J83),"-") -> - | O72: =IFERROR(DATE(YEAR(O71),MONTH(O71)+1,DAY(O71)),"-") -> 47667 | Q72: =IF(S72>0,1+Q71,) -> 58 | R72: =1+R71 -> 10 | S72: =IF('[29]Proforma-Input'!$C$108="No",X71,IF(AF72=TRUE,$P$3,X71)) -> 9145408.8 | T72: =IF(AND($N$8="Yes",Q72<=$P$8),V72,IF(S72>0,$P$7,)) -> 63236.743 | U72: =$P$4 -> 0.068 | V72: =IF(S72>0,U72/12*S72,0) -> 51823.983 | W72: =T72-V72 -> 11412.76 | X72: =S72-W72 -> 9133996 | Y72: =IF(Q72=1,V72,Y71+V72) -> 3101727.1 | Z72: =IF(Q72=1,W72,Z71+W72) -> 566003.99 | AA72: =$P$9*S72/12 -> 762.1174 | AB72: =$P$10*AA72 -> 190.52935 | AC72: =IF(P72>0,SUM(V72:V83),"-") -> - | AD72: =IF(P72>0,SUM(W72:W83),"-") -> - | AF72: =IF('[29]Proforma-Input'!$C$108="Yes",MONTH(O72)&YEAR(O72)=MONTH($C$9)&YEAR($C$9),0) -> 0 | AG72: 5
B73: =IFERROR(DATE(YEAR(B72),MONTH(B72)+1,DAY(B72)),"-") -> - | D73: 59 | E73: =1+E72 -> 11 | F73: =IFERROR(IF(B73<$C$9,IF('[29]Proforma-Input'!$C$108="Yes",K72,K72),0),) -> 0 | G73: =IFERROR(IF(D73=$C$7,K72,IF(AND($D$10="Yes",D73<=$C$10),I73,IF(F73>0,$C$8,))),) -> 0 | H73: =IFERROR(IF(B73<$C$9,IF('[29]Proforma-Input'!$C$108="Yes",H72,),0),) -> 0 | I73: =(H73/12)*F73 -> 0 | J73: =IF(D73=$C$7,0,G73-I73) -> 0 | K73: =IFERROR(F73-J73,) -> 0 | L73: =IF(C73>0,SUM(I73:I84),"-") -> - | M73: =IF(C73>0,SUM(J73:J84),"-") -> - | O73: =IFERROR(DATE(YEAR(O72),MONTH(O72)+1,DAY(O72)),"-") -> 47698 | Q73: =IF(S73>0,1+Q72,) -> 59 | R73: =1+R72 -> 11 | S73: =IF('[29]Proforma-Input'!$C$108="No",X72,IF(AF73=TRUE,$P$3,X72)) -> 9133996 | T73: =IF(AND($N$8="Yes",Q73<=$P$8),V73,IF(S73>0,$P$7,)) -> 63236.743 | U73: =$P$4 -> 0.068 | V73: =IF(S73>0,U73/12*S73,0) -> 51759.311 | W73: =T73-V73 -> 11477.433 | X73: =S73-W73 -> 9122518.6 | Y73: =IF(Q73=1,V73,Y72+V73) -> 3153486.4 | Z73: =IF(Q73=1,W73,Z72+W73) -> 577481.42 | AA73: =$P$9*S73/12 -> 761.16633 | AB73: =$P$10*AA73 -> 190.29158 | AC73: =IF(P73>0,SUM(V73:V84),"-") -> - | AD73: =IF(P73>0,SUM(W73:W84),"-") -> - | AF73: =IF('[29]Proforma-Input'!$C$108="Yes",MONTH(O73)&YEAR(O73)=MONTH($C$9)&YEAR($C$9),0) -> 0 | AG73: 5
B74: =IFERROR(DATE(YEAR(B73),MONTH(B73)+1,DAY(B73)),"-") -> - | D74: 60 | E74: =1+E73 -> 12 | F74: =IFERROR(IF(B74<$C$9,IF('[29]Proforma-Input'!$C$108="Yes",K73,K73),0),) -> 0 | G74: =IFERROR(IF(D74=$C$7,K73,IF(AND($D$10="Yes",D74<=$C$10),I74,IF(F74>0,$C$8,))),) -> 0 | H74: =IFERROR(IF(B74<$C$9,IF('[29]Proforma-Input'!$C$108="Yes",H73,),0),) -> 0 | I74: =(H74/12)*F74 -> 0 | J74: =IF(D74=$C$7,0,G74-I74) -> 0 | K74: =IFERROR(F74-J74,) -> 0 | L74: =IF(C74>0,SUM(I74:I85),"-") -> - | M74: =IF(C74>0,SUM(J74:J85),"-") -> - | O74: =IFERROR(DATE(YEAR(O73),MONTH(O73)+1,DAY(O73)),"-") -> 47729 | Q74: =IF(S74>0,1+Q73,) -> 60 | R74: =1+R73 -> 12 | S74: =IF('[29]Proforma-Input'!$C$108="No",X73,IF(AF74=TRUE,$P$3,X73)) -> 9122518.6 | T74: =IF(AND($N$8="Yes",Q74<=$P$8),V74,IF(S74>0,$P$7,)) -> 63236.743 | U74: =$P$4 -> 0.068 | V74: =IF(S74>0,U74/12*S74,0) -> 51694.272 | W74: =T74-V74 -> 11542.471 | X74: =S74-W74 -> 9110976.1 | Y74: =IF(Q74=1,V74,Y73+V74) -> 3205180.7 | Z74: =IF(Q74=1,W74,Z73+W74) -> 589023.89 | AA74: =$P$9*S74/12 -> 760.20988 | AB74: =$P$10*AA74 -> 190.05247 | AC74: =IF(P74>0,SUM(V74:V85),"-") -> - | AD74: =IF(P74>0,SUM(W74:W85),"-") -> - | AF74: =IF('[29]Proforma-Input'!$C$108="Yes",MONTH(O74)&YEAR(O74)=MONTH($C$9)&YEAR($C$9),0) -> 0 | AG74: 5
B75: =IFERROR(DATE(YEAR(B74),MONTH(B74)+1,DAY(B74)),"-") -> - | C75: 6 | D75: 61 | E75: 1 | F75: =IFERROR(IF(B75<$C$9,IF('[29]Proforma-Input'!$C$108="Yes",K74,K74),0),) -> 0 | G75: =IFERROR(IF(D75=$C$7,K74,IF(AND($D$10="Yes",D75<=$C$10),I75,IF(F75>0,$C$8,))),) -> 0 | H75: =IFERROR(IF(B75<$C$9,IF('[29]Proforma-Input'!$C$108="Yes",H74,),0),) -> 0 | I75: =(H75/12)*F75 -> 0 | J75: =IF(D75=$C$7,0,G75-I75) -> 0 | K75: =IFERROR(F75-J75,) -> 0 | L75: =IF(C75>0,SUM(I75:I86),"-") -> 0 | M75: =IF(C75>0,SUM(J75:J86),"-") -> 0 | O75: =IFERROR(DATE(YEAR(O74),MONTH(O74)+1,DAY(O74)),"-") -> 47759 | P75: 6 | Q75: =IF(S75>0,1+Q74,) -> 61 | R75: 1 | S75: =IF('[29]Proforma-Input'!$C$108="No",X74,IF(AF75=TRUE,$P$3,X74)) -> 9110976.1 | T75: =IF(AND($N$8="Yes",Q75<=$P$8),V75,IF(S75>0,$P$7,)) -> 63236.743 | U75: =$P$4 -> 0.068 | V75: =IF(S75>0,U75/12*S75,0) -> 51628.865 | W75: =T75-V75 -> 11607.879 | X75: =S75-W75 -> 9099368.2 | Y75: =IF(Q75=1,V75,Y74+V75) -> 3256809.6 | Z75: =IF(Q75=1,W75,Z74+W75) -> 600631.77 | AA75: =$P$9*S75/12 -> 759.24801 | AB75: =$P$10*AA75 -> 189.812 | AC75: =IF(P75>0,SUM(V75:V86),"-") -> 615121.97 | AD75: =IF(P75>0,SUM(W75:W86),"-") -> 143718.95 | AF75: =IF('[29]Proforma-Input'!$C$108="Yes",MONTH(O75)&YEAR(O75)=MONTH($C$9)&YEAR($C$9),0) -> 0 | AG75: 6
B76: =IFERROR(DATE(YEAR(B75),MONTH(B75)+1,DAY(B75)),"-") -> - | D76: 62 | E76: =1+E75 -> 2 | F76: =IFERROR(IF(B76<$C$9,IF('[29]Proforma-Input'!$C$108="Yes",K75,K75),0),) -> 0 | G76: =IFERROR(IF(D76=$C$7,K75,IF(AND($D$10="Yes",D76<=$C$10),I76,IF(F76>0,$C$8,))),) -> 0 | H76: =IFERROR(IF(B76<$C$9,IF('[29]Proforma-Input'!$C$108="Yes",H75,),0),) -> 0 | I76: =(H76/12)*F76 -> 0 | J76: =IF(D76=$C$7,0,G76-I76) -> 0 | K76: =IFERROR(F76-J76,) -> 0 | L76: =IF(C76>0,SUM(I76:I87),"-") -> - | M76: =IF(C76>0,SUM(J76:J87),"-") -> - | O76: =IFERROR(DATE(YEAR(O75),MONTH(O75)+1,DAY(O75)),"-") -> 47790 | Q76: =IF(S76>0,1+Q75,) -> 62 | R76: =1+R75 -> 2 | S76: =IF('[29]Proforma-Input'!$C$108="No",X75,IF(AF76=TRUE,$P$3,X75)) -> 9099368.2 | T76: =IF(AND($N$8="Yes",Q76<=$P$8),V76,IF(S76>0,$P$7,)) -> 63236.743 | U76: =$P$4 -> 0.068 | V76: =IF(S76>0,U76/12*S76,0) -> 51563.087 | W76: =T76-V76 -> 11673.657 | X76: =S76-W76 -> 9087694.6 | Y76: =IF(Q76=1,V76,Y75+V76) -> 3308372.7 | Z76: =IF(Q76=1,W76,Z75+W76) -> 612305.43 | AA76: =$P$9*S76/12 -> 758.28069 | AB76: =$P$10*AA76 -> 189.57017 | AC76: =IF(P76>0,SUM(V76:V87),"-") -> - | AD76: =IF(P76>0,SUM(W76:W87),"-") -> - | AF76: =IF('[29]Proforma-Input'!$C$108="Yes",MONTH(O76)&YEAR(O76)=MONTH($C$9)&YEAR($C$9),0) -> 0 | AG76: 6
B77: =IFERROR(DATE(YEAR(B76),MONTH(B76)+1,DAY(B76)),"-") -> - | D77: 63 | E77: =1+E76 -> 3 | F77: =IFERROR(IF(B77<$C$9,IF('[29]Proforma-Input'!$C$108="Yes",K76,K76),0),) -> 0 | G77: =IFERROR(IF(D77=$C$7,K76,IF(AND($D$10="Yes",D77<=$C$10),I77,IF(F77>0,$C$8,))),) -> 0 | H77: =IFERROR(IF(B77<$C$9,IF('[29]Proforma-Input'!$C$108="Yes",H76,),0),) -> 0 | I77: =(H77/12)*F77 -> 0 | J77: =IF(D77=$C$7,0,G77-I77) -> 0 | K77: =IFERROR(F77-J77,) -> 0 | L77: =IF(C77>0,SUM(I77:I88),"-") -> - | M77: =IF(C77>0,SUM(J77:J88),"-") -> - | O77: =IFERROR(DATE(YEAR(O76),MONTH(O76)+1,DAY(O76)),"-") -> 47820 | Q77: =IF(S77>0,1+Q76,) -> 63 | R77: =1+R76 -> 3 | S77: =IF('[29]Proforma-Input'!$C$108="No",X76,IF(AF77=TRUE,$P$3,X76)) -> 9087694.6 | T77: =IF(AND($N$8="Yes",Q77<=$P$8),V77,IF(S77>0,$P$7,)) -> 63236.743 | U77: =$P$4 -> 0.068 | V77: =IF(S77>0,U77/12*S77,0) -> 51496.936 | W77: =T77-V77 -> 11739.807 | X77: =S77-W77 -> 9075954.8 | Y77: =IF(Q77=1,V77,Y76+V77) -> 3359869.6 | Z77: =IF(Q77=1,W77,Z76+W77) -> 624045.23 | AA77: =$P$9*S77/12 -> 757.30788 | AB77: =$P$10*AA77 -> 189.32697 | AC77: =IF(P77>0,SUM(V77:V88),"-") -> - | AD77: =IF(P77>0,SUM(W77:W88),"-") -> - | AF77: =IF('[29]Proforma-Input'!$C$108="Yes",MONTH(O77)&YEAR(O77)=MONTH($C$9)&YEAR($C$9),0) -> 0 | AG77: 6
B78: =IFERROR(DATE(YEAR(B77),MONTH(B77)+1,DAY(B77)),"-") -> - | D78: 64 | E78: =1+E77 -> 4 | F78: =IFERROR(IF(B78<$C$9,IF('[29]Proforma-Input'!$C$108="Yes",K77,K77),0),) -> 0 | G78: =IFERROR(IF(D78=$C$7,K77,IF(AND($D$10="Yes",D78<=$C$10),I78,IF(F78>0,$C$8,))),) -> 0 | H78: =IFERROR(IF(B78<$C$9,IF('[29]Proforma-Input'!$C$108="Yes",H77,),0),) -> 0 | I78: =(H78/12)*F78 -> 0 | J78: =IF(D78=$C$7,0,G78-I78) -> 0 | K78: =IFERROR(F78-J78,) -> 0 | L78: =IF(C78>0,SUM(I78:I89),"-") -> - | M78: =IF(C78>0,SUM(J78:J89),"-") -> - | O78: =IFERROR(DATE(YEAR(O77),MONTH(O77)+1,DAY(O77)),"-") -> 47851 | Q78: =IF(S78>0,1+Q77,) -> 64 | R78: =1+R77 -> 4 | S78: =IF('[29]Proforma-Input'!$C$108="No",X77,IF(AF78=TRUE,$P$3,X77)) -> 9075954.8 | T78: =IF(AND($N$8="Yes",Q78<=$P$8),V78,IF(S78>0,$P$7,)) -> 63236.743 | U78: =$P$4 -> 0.068 | V78: =IF(S78>0,U78/12*S78,0) -> 51430.41 | W78: =T78-V78 -> 11806.333 | X78: =S78-W78 -> 9064148.4 | Y78: =IF(Q78=1,V78,Y77+V78) -> 3411300 | Z78: =IF(Q78=1,W78,Z77+W78) -> 635851.57 | AA78: =$P$9*S78/12 -> 756.32956 | AB78: =$P$10*AA78 -> 189.08239 | AC78: =IF(P78>0,SUM(V78:V89),"-") -> - | AD78: =IF(P78>0,SUM(W78:W89),"-") -> - | AF78: =IF('[29]Proforma-Input'!$C$108="Yes",MONTH(O78)&YEAR(O78)=MONTH($C$9)&YEAR($C$9),0) -> 0 | AG78: 6
B79: =IFERROR(DATE(YEAR(B78),MONTH(B78)+1,DAY(B78)),"-") -> - | D79: 65 | E79: =1+E78 -> 5 | F79: =IFERROR(IF(B79<$C$9,IF('[29]Proforma-Input'!$C$108="Yes",K78,K78),0),) -> 0 | G79: =IFERROR(IF(D79=$C$7,K78,IF(AND($D$10="Yes",D79<=$C$10),I79,IF(F79>0,$C$8,))),) -> 0 | H79: =IFERROR(IF(B79<$C$9,IF('[29]Proforma-Input'!$C$108="Yes",H78,),0),) -> 0 | I79: =(H79/12)*F79 -> 0 | J79: =IF(D79=$C$7,0,G79-I79) -> 0 | K79: =IFERROR(F79-J79,) -> 0 | L79: =IF(C79>0,SUM(I79:I90),"-") -> - | M79: =IF(C79>0,SUM(J79:J90),"-") -> - | O79: =IFERROR(DATE(YEAR(O78),MONTH(O78)+1,DAY(O78)),"-") -> 47882 | Q79: =IF(S79>0,1+Q78,) -> 65 | R79: =1+R78 -> 5 | S79: =IF('[29]Proforma-Input'!$C$108="No",X78,IF(AF79=TRUE,$P$3,X78)) -> 9064148.4 | T79: =IF(AND($N$8="Yes",Q79<=$P$8),V79,IF(S79>0,$P$7,)) -> 63236.743 | U79: =$P$4 -> 0.068 | V79: =IF(S79>0,U79/12*S79,0) -> 51363.508 | W79: =T79-V79 -> 11873.235 | X79: =S79-W79 -> 9052275.2 | Y79: =IF(Q79=1,V79,Y78+V79) -> 3462663.5 | Z79: =IF(Q79=1,W79,Z78+W79) -> 647724.8 | AA79: =$P$9*S79/12 -> 755.3457 | AB79: =$P$10*AA79 -> 188.83643 | AC79: =IF(P79>0,SUM(V79:V90),"-") -> - | AD79: =IF(P79>0,SUM(W79:W90),"-") -> - | AF79: =IF('[29]Proforma-Input'!$C$108="Yes",MONTH(O79)&YEAR(O79)=MONTH($C$9)&YEAR($C$9),0) -> 0 | AG79: 6
B80: =IFERROR(DATE(YEAR(B79),MONTH(B79)+1,DAY(B79)),"-") -> - | D80: 66 | E80: =1+E79 -> 6 | F80: =IFERROR(IF(B80<$C$9,IF('[29]Proforma-Input'!$C$108="Yes",K79,K79),0),) -> 0 | G80: =IFERROR(IF(D80=$C$7,K79,IF(AND($D$10="Yes",D80<=$C$10),I80,IF(F80>0,$C$8,))),) -> 0 | H80: =IFERROR(IF(B80<$C$9,IF('[29]Proforma-Input'!$C$108="Yes",H79,),0),) -> 0 | I80: =(H80/12)*F80 -> 0 | J80: =IF(D80=$C$7,0,G80-I80) -> 0 | K80: =IFERROR(F80-J80,) -> 0 | L80: =IF(C80>0,SUM(I80:I91),"-") -> - | M80: =IF(C80>0,SUM(J80:J91),"-") -> - | O80: =IFERROR(DATE(YEAR(O79),MONTH(O79)+1,DAY(O79)),"-") -> 47910 | Q80: =IF(S80>0,1+Q79,) -> 66 | R80: =1+R79 -> 6 | S80: =IF('[29]Proforma-Input'!$C$108="No",X79,IF(AF80=TRUE,$P$3,X79)) -> 9052275.2 | T80: =IF(AND($N$8="Yes",Q80<=$P$8),V80,IF(S80>0,$P$7,)) -> 63236.743 | U80: =$P$4 -> 0.068 | V80: =IF(S80>0,U80/12*S80,0) -> 51296.226 | W80: =T80-V80 -> 11940.517 | X80: =S80-W80 -> 9040334.7 | Y80: =IF(Q80=1,V80,Y79+V80) -> 3513959.7 | Z80: =IF(Q80=1,W80,Z79+W80) -> 659665.32 | AA80: =$P$9*S80/12 -> 754.35627 | AB80: =$P$10*AA80 -> 188.58907 | AC80: =IF(P80>0,SUM(V80:V91),"-") -> - | AD80: =IF(P80>0,SUM(W80:W91),"-") -> - | AF80: =IF('[29]Proforma-Input'!$C$108="Yes",MONTH(O80)&YEAR(O80)=MONTH($C$9)&YEAR($C$9),0) -> 0 | AG80: 6
B81: =IFERROR(DATE(YEAR(B80),MONTH(B80)+1,DAY(B80)),"-") -> - | D81: 67 | E81: =1+E80 -> 7 | F81: =IFERROR(IF(B81<$C$9,IF('[29]Proforma-Input'!$C$108="Yes",K80,K80),0),) -> 0 | G81: =IFERROR(IF(D81=$C$7,K80,IF(AND($D$10="Yes",D81<=$C$10),I81,IF(F81>0,$C$8,))),) -> 0 | H81: =IFERROR(IF(B81<$C$9,IF('[29]Proforma-Input'!$C$108="Yes",H80,),0),) -> 0 | I81: =(H81/12)*F81 -> 0 | J81: =IF(D81=$C$7,0,G81-I81) -> 0 | K81: =IFERROR(F81-J81,) -> 0 | L81: =IF(C81>0,SUM(I81:I92),"-") -> - | M81: =IF(C81>0,SUM(J81:J92),"-") -> - | O81: =IFERROR(DATE(YEAR(O80),MONTH(O80)+1,DAY(O80)),"-") -> 47941 | Q81: =IF(S81>0,1+Q80,) -> 67 | R81: =1+R80 -> 7 | S81: =IF('[29]Proforma-Input'!$C$108="No",X80,IF(AF81=TRUE,$P$3,X80)) -> 9040334.7 | T81: =IF(AND($N$8="Yes",Q81<=$P$8),V81,IF(S81>0,$P$7,)) -> 63236.743 | U81: =$P$4 -> 0.068 | V81: =IF(S81>0,U81/12*S81,0) -> 51228.563 | W81: =T81-V81 -> 12008.18 | X81: =S81-W81 -> 9028326.5 | Y81: =IF(Q81=1,V81,Y80+V81) -> 3565188.3 | Z81: =IF(Q81=1,W81,Z80+W81) -> 671673.5 | AA81: =$P$9*S81/12 -> 753.36122 | AB81: =$P$10*AA81 -> 188.34031 | AC81: =IF(P81>0,SUM(V81:V92),"-") -> - | AD81: =IF(P81>0,SUM(W81:W92),"-") -> - | AF81: =IF('[29]Proforma-Input'!$C$108="Yes",MONTH(O81)&YEAR(O81)=MONTH($C$9)&YEAR($C$9),0) -> 0 | AG81: 6
B82: =IFERROR(DATE(YEAR(B81),MONTH(B81)+1,DAY(B81)),"-") -> - | D82: 68 | E82: =1+E81 -> 8 | F82: =IFERROR(IF(B82<$C$9,IF('[29]Proforma-Input'!$C$108="Yes",K81,K81),0),) -> 0 | G82: =IFERROR(IF(D82=$C$7,K81,IF(AND($D$10="Yes",D82<=$C$10),I82,IF(F82>0,$C$8,))),) -> 0 | H82: =IFERROR(IF(B82<$C$9,IF('[29]Proforma-Input'!$C$108="Yes",H81,),0),) -> 0 | I82: =(H82/12)*F82 -> 0 | J82: =IF(D82=$C$7,0,G82-I82) -> 0 | K82: =IFERROR(F82-J82,) -> 0 | L82: =IF(C82>0,SUM(I82:I93),"-") -> - | M82: =IF(C82>0,SUM(J82:J93),"-") -> - | O82: =IFERROR(DATE(YEAR(O81),MONTH(O81)+1,DAY(O81)),"-") -> 47971 | Q82: =IF(S82>0,1+Q81,) -> 68 | R82: =1+R81 -> 8 | S82: =IF('[29]Proforma-Input'!$C$108="No",X81,IF(AF82=TRUE,$P$3,X81)) -> 9028326.5 | T82: =IF(AND($N$8="Yes",Q82<=$P$8),V82,IF(S82>0,$P$7,)) -> 63236.743 | U82: =$P$4 -> 0.068 | V82: =IF(S82>0,U82/12*S82,0) -> 51160.517 | W82: =T82-V82 -> 12076.226 | X82: =S82-W82 -> 9016250.3 | Y82: =IF(Q82=1,V82,Y81+V82) -> 3616348.8 | Z82: =IF(Q82=1,W82,Z81+W82) -> 683749.73 | AA82: =$P$9*S82/12 -> 752.36054 | AB82: =$P$10*AA82 -> 188.09014 | AC82: =IF(P82>0,SUM(V82:V93),"-") -> - | AD82: =IF(P82>0,SUM(W82:W93),"-") -> - | AF82: =IF('[29]Proforma-Input'!$C$108="Yes",MONTH(O82)&YEAR(O82)=MONTH($C$9)&YEAR($C$9),0) -> 0 | AG82: 6
B83: =IFERROR(DATE(YEAR(B82),MONTH(B82)+1,DAY(B82)),"-") -> - | D83: 69 | E83: =1+E82 -> 9 | F83: =IFERROR(IF(B83<$C$9,IF('[29]Proforma-Input'!$C$108="Yes",K82,K82),0),) -> 0 | G83: =IFERROR(IF(D83=$C$7,K82,IF(AND($D$10="Yes",D83<=$C$10),I83,IF(F83>0,$C$8,))),) -> 0 | H83: =IFERROR(IF(B83<$C$9,IF('[29]Proforma-Input'!$C$108="Yes",H82,),0),) -> 0 | I83: =(H83/12)*F83 -> 0 | J83: =IF(D83=$C$7,0,G83-I83) -> 0 | K83: =IFERROR(F83-J83,) -> 0 | L83: =IF(C83>0,SUM(I83:I94),"-") -> - | M83: =IF(C83>0,SUM(J83:J94),"-") -> - | O83: =IFERROR(DATE(YEAR(O82),MONTH(O82)+1,DAY(O82)),"-") -> 48002 | Q83: =IF(S83>0,1+Q82,) -> 69 | R83: =1+R82 -> 9 | S83: =IF('[29]Proforma-Input'!$C$108="No",X82,IF(AF83=TRUE,$P$3,X82)) -> 9016250.3 | T83: =IF(AND($N$8="Yes",Q83<=$P$8),V83,IF(S83>0,$P$7,)) -> 63236.743 | U83: =$P$4 -> 0.068 | V83: =IF(S83>0,U83/12*S83,0) -> 51092.085 | W83: =T83-V83 -> 12144.658 | X83: =S83-W83 -> 9004105.6 | Y83: =IF(Q83=1,V83,Y82+V83) -> 3667440.9 | Z83: =IF(Q83=1,W83,Z82+W83) -> 695894.38 | AA83: =$P$9*S83/12 -> 751.35419 | AB83: =$P$10*AA83 -> 187.83855 | AC83: =IF(P83>0,SUM(V83:V94),"-") -> - | AD83: =IF(P83>0,SUM(W83:W94),"-") -> - | AF83: =IF('[29]Proforma-Input'!$C$108="Yes",MONTH(O83)&YEAR(O83)=MONTH($C$9)&YEAR($C$9),0) -> 0 | AG83: 6
B84: =IFERROR(DATE(YEAR(B83),MONTH(B83)+1,DAY(B83)),"-") -> - | D84: 70 | E84: =1+E83 -> 10 | F84: =IFERROR(IF(B84<$C$9,IF('[29]Proforma-Input'!$C$108="Yes",K83,K83),0),) -> 0 | G84: =IFERROR(IF(D84=$C$7,K83,IF(AND($D$10="Yes",D84<=$C$10),I84,IF(F84>0,$C$8,))),) -> 0 | H84: =IFERROR(IF(B84<$C$9,IF('[29]Proforma-Input'!$C$108="Yes",H83,),0),) -> 0 | I84: =(H84/12)*F84 -> 0 | J84: =IF(D84=$C$7,0,G84-I84) -> 0 | K84: =IFERROR(F84-J84,) -> 0 | L84: =IF(C84>0,SUM(I84:I95),"-") -> - | M84: =IF(C84>0,SUM(J84:J95),"-") -> - | O84: =IFERROR(DATE(YEAR(O83),MONTH(O83)+1,DAY(O83)),"-") -> 48032 | Q84: =IF(S84>0,1+Q83,) -> 70 | R84: =1+R83 -> 10 | S84: =IF('[29]Proforma-Input'!$C$108="No",X83,IF(AF84=TRUE,$P$3,X83)) -> 9004105.6 | T84: =IF(AND($N$8="Yes",Q84<=$P$8),V84,IF(S84>0,$P$7,)) -> 63236.743 | U84: =$P$4 -> 0.068 | V84: =IF(S84>0,U84/12*S84,0) -> 51023.265 | W84: =T84-V84 -> 12213.478 | X84: =S84-W84 -> 8991892.1 | Y84: =IF(Q84=1,V84,Y83+V84) -> 3718464.2 | Z84: =IF(Q84=1,W84,Z83+W84) -> 708107.86 | AA84: =$P$9*S84/12 -> 750.34213 | AB84: =$P$10*AA84 -> 187.58553 | AC84: =IF(P84>0,SUM(V84:V95),"-") -> - | AD84: =IF(P84>0,SUM(W84:W95),"-") -> - | AF84: =IF('[29]Proforma-Input'!$C$108="Yes",MONTH(O84)&YEAR(O84)=MONTH($C$9)&YEAR($C$9),0) -> 0 | AG84: 6
B85: =IFERROR(DATE(YEAR(B84),MONTH(B84)+1,DAY(B84)),"-") -> - | D85: 71 | E85: =1+E84 -> 11 | F85: =IFERROR(IF(B85<$C$9,IF('[29]Proforma-Input'!$C$108="Yes",K84,K84),0),) -> 0 | G85: =IFERROR(IF(D85=$C$7,K84,IF(AND($D$10="Yes",D85<=$C$10),I85,IF(F85>0,$C$8,))),) -> 0 | H85: =IFERROR(IF(B85<$C$9,IF('[29]Proforma-Input'!$C$108="Yes",H84,),0),) -> 0 | I85: =(H85/12)*F85 -> 0 | J85: =IF(D85=$C$7,0,G85-I85) -> 0 | K85: =IFERROR(F85-J85,) -> 0 | L85: =IF(C85>0,SUM(I85:I96),"-") -> - | M85: =IF(C85>0,SUM(J85:J96),"-") -> - | O85: =IFERROR(DATE(YEAR(O84),MONTH(O84)+1,DAY(O84)),"-") -> 48063 | Q85: =IF(S85>0,1+Q84,) -> 71 | R85: =1+R84 -> 11 | S85: =IF('[29]Proforma-Input'!$C$108="No",X84,IF(AF85=TRUE,$P$3,X84)) -> 8991892.1 | T85: =IF(AND($N$8="Yes",Q85<=$P$8),V85,IF(S85>0,$P$7,)) -> 63236.743 | U85: =$P$4 -> 0.068 | V85: =IF(S85>0,U85/12*S85,0) -> 50954.055 | W85: =T85-V85 -> 12282.688 | X85: =S85-W85 -> 8979609.5 | Y85: =IF(Q85=1,V85,Y84+V85) -> 3769418.2 | Z85: =IF(Q85=1,W85,Z84+W85) -> 720390.55 | AA85: =$P$9*S85/12 -> 749.32434 | AB85: =$P$10*AA85 -> 187.33109 | AC85: =IF(P85>0,SUM(V85:V96),"-") -> - | AD85: =IF(P85>0,SUM(W85:W96),"-") -> - | AF85: =IF('[29]Proforma-Input'!$C$108="Yes",MONTH(O85)&YEAR(O85)=MONTH($C$9)&YEAR($C$9),0) -> 0 | AG85: 6
B86: =IFERROR(DATE(YEAR(B85),MONTH(B85)+1,DAY(B85)),"-") -> - | D86: 72 | E86: =1+E85 -> 12 | F86: =IFERROR(IF(B86<$C$9,IF('[29]Proforma-Input'!$C$108="Yes",K85,K85),0),) -> 0 | G86: =IFERROR(IF(D86=$C$7,K85,IF(AND($D$10="Yes",D86<=$C$10),I86,IF(F86>0,$C$8,))),) -> 0 | H86: =IFERROR(IF(B86<$C$9,IF('[29]Proforma-Input'!$C$108="Yes",H85,),0),) -> 0 | I86: =(H86/12)*F86 -> 0 | J86: =IF(D86=$C$7,0,G86-I86) -> 0 | K86: =IFERROR(F86-J86,) -> 0 | L86: =IF(C86>0,SUM(I86:I97),"-") -> - | M86: =IF(C86>0,SUM(J86:J97),"-") -> - | O86: =IFERROR(DATE(YEAR(O85),MONTH(O85)+1,DAY(O85)),"-") -> 48094 | Q86: =IF(S86>0,1+Q85,) -> 72 | R86: =1+R85 -> 12 | S86: =IF('[29]Proforma-Input'!$C$108="No",X85,IF(AF86=TRUE,$P$3,X85)) -> 8979609.5 | T86: =IF(AND($N$8="Yes",Q86<=$P$8),V86,IF(S86>0,$P$7,)) -> 63236.743 | U86: =$P$4 -> 0.068 | V86: =IF(S86>0,U86/12*S86,0) -> 50884.454 | W86: =T86-V86 -> 12352.29 | X86: =S86-W86 -> 8967257.2 | Y86: =IF(Q86=1,V86,Y85+V86) -> 3820302.7 | Z86: =IF(Q86=1,W86,Z85+W86) -> 732742.84 | AA86: =$P$9*S86/12 -> 748.30079 | AB86: =$P$10*AA86 -> 187.0752 | AC86: =IF(P86>0,SUM(V86:V97),"-") -> - | AD86: =IF(P86>0,SUM(W86:W97),"-") -> - | AF86: =IF('[29]Proforma-Input'!$C$108="Yes",MONTH(O86)&YEAR(O86)=MONTH($C$9)&YEAR($C$9),0) -> 0 | AG86: 6
B87: =IFERROR(DATE(YEAR(B86),MONTH(B86)+1,DAY(B86)),"-") -> - | C87: 7 | D87: 73 | E87: 1 | F87: =IFERROR(IF(B87<$C$9,IF('[29]Proforma-Input'!$C$108="Yes",K86,K86),0),) -> 0 | G87: =IFERROR(IF(D87=$C$7,K86,IF(AND($D$10="Yes",D87<=$C$10),I87,IF(F87>0,$C$8,))),) -> 0 | H87: =IFERROR(IF(B87<$C$9,IF('[29]Proforma-Input'!$C$108="Yes",H86,),0),) -> 0 | I87: =(H87/12)*F87 -> 0 | J87: =IF(D87=$C$7,0,G87-I87) -> 0 | K87: =IFERROR(F87-J87,) -> 0 | L87: =IF(C87>0,SUM(I87:I98),"-") -> 0 | M87: =IF(C87>0,SUM(J87:J98),"-") -> 0 | O87: =IFERROR(DATE(YEAR(O86),MONTH(O86)+1,DAY(O86)),"-") -> 48124 | P87: 7 | Q87: =IF(S87>0,1+Q86,) -> 73 | R87: 1 | S87: =IF('[29]Proforma-Input'!$C$108="No",X86,IF(AF87=TRUE,$P$3,X86)) -> 8967257.2 | T87: =IF(AND($N$8="Yes",Q87<=$P$8),V87,IF(S87>0,$P$7,)) -> 63236.743 | U87: =$P$4 -> 0.068 | V87: =IF(S87>0,U87/12*S87,0) -> 50814.457 | W87: =T87-V87 -> 12422.286 | X87: =S87-W87 -> 8954834.9 | Y87: =IF(Q87=1,V87,Y86+V87) -> 3871117.1 | Z87: =IF(Q87=1,W87,Z86+W87) -> 745165.13 | AA87: =$P$9*S87/12 -> 747.27143 | AB87: =$P$10*AA87 -> 186.81786 | AC87: =IF(P87>0,SUM(V87:V98),"-") -> 605038.67 | AD87: =IF(P87>0,SUM(W87:W98),"-") -> 153802.25 | AF87: =IF('[29]Proforma-Input'!$C$108="Yes",MONTH(O87)&YEAR(O87)=MONTH($C$9)&YEAR($C$9),0) -> 0 | AG87: 7
B88: =IFERROR(DATE(YEAR(B87),MONTH(B87)+1,DAY(B87)),"-") -> - | D88: 74 | E88: =1+E87 -> 2 | F88: =IFERROR(IF(B88<$C$9,IF('[29]Proforma-Input'!$C$108="Yes",K87,K87),0),) -> 0 | G88: =IFERROR(IF(D88=$C$7,K87,IF(AND($D$10="Yes",D88<=$C$10),I88,IF(F88>0,$C$8,))),) -> 0 | H88: =IFERROR(IF(B88<$C$9,IF('[29]Proforma-Input'!$C$108="Yes",H87,),0),) -> 0 | I88: =(H88/12)*F88 -> 0 | J88: =IF(D88=$C$7,0,G88-I88) -> 0 | K88: =IFERROR(F88-J88,) -> 0 | L88: =IF(C88>0,SUM(I88:I99),"-") -> - | M88: =IF(C88>0,SUM(J88:J99),"-") -> - | O88: =IFERROR(DATE(YEAR(O87),MONTH(O87)+1,DAY(O87)),"-") -> 48155 | Q88: =IF(S88>0,1+Q87,) -> 74 | R88: =1+R87 -> 2 | S88: =IF('[29]Proforma-Input'!$C$108="No",X87,IF(AF88=TRUE,$P$3,X87)) -> 8954834.9 | T88: =IF(AND($N$8="Yes",Q88<=$P$8),V88,IF(S88>0,$P$7,)) -> 63236.743 | U88: =$P$4 -> 0.068 | V88: =IF(S88>0,U88/12*S88,0) -> 50744.064 | W88: =T88-V88 -> 12492.679 | X88: =S88-W88 -> 8942342.2 | Y88: =IF(Q88=1,V88,Y87+V88) -> 3921861.2 | Z88: =IF(Q88=1,W88,Z87+W88) -> 757657.8 | AA88: =$P$9*S88/12 -> 746.23624 | AB88: =$P$10*AA88 -> 186.55906 | AC88: =IF(P88>0,SUM(V88:V99),"-") -> - | AD88: =IF(P88>0,SUM(W88:W99),"-") -> - | AF88: =IF('[29]Proforma-Input'!$C$108="Yes",MONTH(O88)&YEAR(O88)=MONTH($C$9)&YEAR($C$9),0) -> 0 | AG88: 7
B89: =IFERROR(DATE(YEAR(B88),MONTH(B88)+1,DAY(B88)),"-") -> - | D89: 75 | E89: =1+E88 -> 3 | F89: =IFERROR(IF(B89<$C$9,IF('[29]Proforma-Input'!$C$108="Yes",K88,K88),0),) -> 0 | G89: =IFERROR(IF(D89=$C$7,K88,IF(AND($D$10="Yes",D89<=$C$10),I89,IF(F89>0,$C$8,))),) -> 0 | H89: =IFERROR(IF(B89<$C$9,IF('[29]Proforma-Input'!$C$108="Yes",H88,),0),) -> 0 | I89: =(H89/12)*F89 -> 0 | J89: =IF(D89=$C$7,0,G89-I89) -> 0 | K89: =IFERROR(F89-J89,) -> 0 | L89: =IF(C89>0,SUM(I89:I100),"-") -> - | M89: =IF(C89>0,SUM(J89:J100),"-") -> - | O89: =IFERROR(DATE(YEAR(O88),MONTH(O88)+1,DAY(O88)),"-") -> 48185 | Q89: =IF(S89>0,1+Q88,) -> 75 | R89: =1+R88 -> 3 | S89: =IF('[29]Proforma-Input'!$C$108="No",X88,IF(AF89=TRUE,$P$3,X88)) -> 8942342.2 | T89: =IF(AND($N$8="Yes",Q89<=$P$8),V89,IF(S89>0,$P$7,)) -> 63236.743 | U89: =$P$4 -> 0.068 | V89: =IF(S89>0,U89/12*S89,0) -> 50673.272 | W89: =T89-V89 -> 12563.471 | X89: =S89-W89 -> 8929778.7 | Y89: =IF(Q89=1,V89,Y88+V89) -> 3972534.5 | Z89: =IF(Q89=1,W89,Z88+W89) -> 770221.28 | AA89: =$P$9*S89/12 -> 745.19518 | AB89: =$P$10*AA89 -> 186.2988 | AC89: =IF(P89>0,SUM(V89:V100),"-") -> - | AD89: =IF(P89>0,SUM(W89:W100),"-") -> - | AF89: =IF('[29]Proforma-Input'!$C$108="Yes",MONTH(O89)&YEAR(O89)=MONTH($C$9)&YEAR($C$9),0) -> 0 | AG89: 7
B90: =IFERROR(DATE(YEAR(B89),MONTH(B89)+1,DAY(B89)),"-") -> - | D90: 76 | E90: =1+E89 -> 4 | F90: =IFERROR(IF(B90<$C$9,IF('[29]Proforma-Input'!$C$108="Yes",K89,K89),0),) -> 0 | G90: =IFERROR(IF(D90=$C$7,K89,IF(AND($D$10="Yes",D90<=$C$10),I90,IF(F90>0,$C$8,))),) -> 0 | H90: =IFERROR(IF(B90<$C$9,IF('[29]Proforma-Input'!$C$108="Yes",H89,),0),) -> 0 | I90: =(H90/12)*F90 -> 0 | J90: =IF(D90=$C$7,0,G90-I90) -> 0 | K90: =IFERROR(F90-J90,) -> 0 | L90: =IF(C90>0,SUM(I90:I101),"-") -> - | M90: =IF(C90>0,SUM(J90:J101),"-") -> - | O90: =IFERROR(DATE(YEAR(O89),MONTH(O89)+1,DAY(O89)),"-") -> 48216 | Q90: =IF(S90>0,1+Q89,) -> 76 | R90: =1+R89 -> 4 | S90: =IF('[29]Proforma-Input'!$C$108="No",X89,IF(AF90=TRUE,$P$3,X89)) -> 8929778.7 | T90: =IF(AND($N$8="Yes",Q90<=$P$8),V90,IF(S90>0,$P$7,)) -> 63236.743 | U90: =$P$4 -> 0.068 | V90: =IF(S90>0,U90/12*S90,0) -> 50602.079 | W90: =T90-V90 -> 12634.664 | X90: =S90-W90 -> 8917144.1 | Y90: =IF(Q90=1,V90,Y89+V90) -> 4023136.5 | Z90: =IF(Q90=1,W90,Z89+W90) -> 782855.94 | AA90: =$P$9*S90/12 -> 744.14823 | AB90: =$P$10*AA90 -> 186.03706 | AC90: =IF(P90>0,SUM(V90:V101),"-") -> - | AD90: =IF(P90>0,SUM(W90:W101),"-") -> - | AF90: =IF('[29]Proforma-Input'!$C$108="Yes",MONTH(O90)&YEAR(O90)=MONTH($C$9)&YEAR($C$9),0) -> 0 | AG90: 7
B91: =IFERROR(DATE(YEAR(B90),MONTH(B90)+1,DAY(B90)),"-") -> - | D91: 77 | E91: =1+E90 -> 5 | F91: =IFERROR(IF(B91<$C$9,IF('[29]Proforma-Input'!$C$108="Yes",K90,K90),0),) -> 0 | G91: =IFERROR(IF(D91=$C$7,K90,IF(AND($D$10="Yes",D91<=$C$10),I91,IF(F91>0,$C$8,))),) -> 0 | H91: =IFERROR(IF(B91<$C$9,IF('[29]Proforma-Input'!$C$108="Yes",H90,),0),) -> 0 | I91: =(H91/12)*F91 -> 0 | J91: =IF(D91=$C$7,0,G91-I91) -> 0 | K91: =IFERROR(F91-J91,) -> 0 | L91: =IF(C91>0,SUM(I91:I102),"-") -> - | M91: =IF(C91>0,SUM(J91:J102),"-") -> - | O91: =IFERROR(DATE(YEAR(O90),MONTH(O90)+1,DAY(O90)),"-") -> 48247 | Q91: =IF(S91>0,1+Q90,) -> 77 | R91: =1+R90 -> 5 | S91: =IF('[29]Proforma-Input'!$C$108="No",X90,IF(AF91=TRUE,$P$3,X90)) -> 8917144.1 | T91: =IF(AND($N$8="Yes",Q91<=$P$8),V91,IF(S91>0,$P$7,)) -> 63236.743 | U91: =$P$4 -> 0.068 | V91: =IF(S91>0,U91/12*S91,0) -> 50530.483 | W91: =T91-V91 -> 12706.26 | X91: =S91-W91 -> 8904437.8 | Y91: =IF(Q91=1,V91,Y90+V91) -> 4073667 | Z91: =IF(Q91=1,W91,Z90+W91) -> 795562.2 | AA91: =$P$9*S91/12 -> 743.09534 | AB91: =$P$10*AA91 -> 185.77383 | AC91: =IF(P91>0,SUM(V91:V102),"-") -> - | AD91: =IF(P91>0,SUM(W91:W102),"-") -> - | AF91: =IF('[29]Proforma-Input'!$C$108="Yes",MONTH(O91)&YEAR(O91)=MONTH($C$9)&YEAR($C$9),0) -> 0 | AG91: 7
B92: =IFERROR(DATE(YEAR(B91),MONTH(B91)+1,DAY(B91)),"-") -> - | D92: 78 | E92: =1+E91 -> 6 | F92: =IFERROR(IF(B92<$C$9,IF('[29]Proforma-Input'!$C$108="Yes",K91,K91),0),) -> 0 | G92: =IFERROR(IF(D92=$C$7,K91,IF(AND($D$10="Yes",D92<=$C$10),I92,IF(F92>0,$C$8,))),) -> 0 | H92: =IFERROR(IF(B92<$C$9,IF('[29]Proforma-Input'!$C$108="Yes",H91,),0),) -> 0 | I92: =(H92/12)*F92 -> 0 | J92: =IF(D92=$C$7,0,G92-I92) -> 0 | K92: =IFERROR(F92-J92,) -> 0 | L92: =IF(C92>0,SUM(I92:I103),"-") -> - | M92: =IF(C92>0,SUM(J92:J103),"-") -> - | O92: =IFERROR(DATE(YEAR(O91),MONTH(O91)+1,DAY(O91)),"-") -> 48276 | Q92: =IF(S92>0,1+Q91,) -> 78 | R92: =1+R91 -> 6 | S92: =IF('[29]Proforma-Input'!$C$108="No",X91,IF(AF92=TRUE,$P$3,X91)) -> 8904437.8 | T92: =IF(AND($N$8="Yes",Q92<=$P$8),V92,IF(S92>0,$P$7,)) -> 63236.743 | U92: =$P$4 -> 0.068 | V92: =IF(S92>0,U92/12*S92,0) -> 50458.481 | W92: =T92-V92 -> 12778.262 | X92: =S92-W92 -> 8891659.5 | Y92: =IF(Q92=1,V92,Y91+V92) -> 4124125.5 | Z92: =IF(Q92=1,W92,Z91+W92) -> 808340.46 | AA92: =$P$9*S92/12 -> 742.03648 | AB92: =$P$10*AA92 -> 185.50912 | AC92: =IF(P92>0,SUM(V92:V103),"-") -> - | AD92: =IF(P92>0,SUM(W92:W103),"-") -> - | AF92: =IF('[29]Proforma-Input'!$C$108="Yes",MONTH(O92)&YEAR(O92)=MONTH($C$9)&YEAR($C$9),0) -> 0 | AG92: 7
B93: =IFERROR(DATE(YEAR(B92),MONTH(B92)+1,DAY(B92)),"-") -> - | D93: 79 | E93: =1+E92 -> 7 | F93: =IFERROR(IF(B93<$C$9,IF('[29]Proforma-Input'!$C$108="Yes",K92,K92),0),) -> 0 | G93: =IFERROR(IF(D93=$C$7,K92,IF(AND($D$10="Yes",D93<=$C$10),I93,IF(F93>0,$C$8,))),) -> 0 | H93: =IFERROR(IF(B93<$C$9,IF('[29]Proforma-Input'!$C$108="Yes",H92,),0),) -> 0 | I93: =(H93/12)*F93 -> 0 | J93: =IF(D93=$C$7,0,G93-I93) -> 0 | K93: =IFERROR(F93-J93,) -> 0 | L93: =IF(C93>0,SUM(I93:I104),"-") -> - | M93: =IF(C93>0,SUM(J93:J104),"-") -> - | O93: =IFERROR(DATE(YEAR(O92),MONTH(O92)+1,DAY(O92)),"-") -> 48307 | Q93: =IF(S93>0,1+Q92,) -> 79 | R93: =1+R92 -> 7 | S93: =IF('[29]Proforma-Input'!$C$108="No",X92,IF(AF93=TRUE,$P$3,X92)) -> 8891659.5 | T93: =IF(AND($N$8="Yes",Q93<=$P$8),V93,IF(S93>0,$P$7,)) -> 63236.743 | U93: =$P$4 -> 0.068 | V93: =IF(S93>0,U93/12*S93,0) -> 50386.071 | W93: =T93-V93 -> 12850.673 | X93: =S93-W93 -> 8878808.9 | Y93: =IF(Q93=1,V93,Y92+V93) -> 4174511.6 | Z93: =IF(Q93=1,W93,Z92+W93) -> 821191.13 | AA93: =$P$9*S93/12 -> 740.97163 | AB93: =$P$10*AA93 -> 185.24291 | AC93: =IF(P93>0,SUM(V93:V104),"-") -> - | AD93: =IF(P93>0,SUM(W93:W104),"-") -> - | AF93: =IF('[29]Proforma-Input'!$C$108="Yes",MONTH(O93)&YEAR(O93)=MONTH($C$9)&YEAR($C$9),0) -> 0 | AG93: 7
B94: =IFERROR(DATE(YEAR(B93),MONTH(B93)+1,DAY(B93)),"-") -> - | D94: 80 | E94: =1+E93 -> 8 | F94: =IFERROR(IF(B94<$C$9,IF('[29]Proforma-Input'!$C$108="Yes",K93,K93),0),) -> 0 | G94: =IFERROR(IF(D94=$C$7,K93,IF(AND($D$10="Yes",D94<=$C$10),I94,IF(F94>0,$C$8,))),) -> 0 | H94: =IFERROR(IF(B94<$C$9,IF('[29]Proforma-Input'!$C$108="Yes",H93,),0),) -> 0 | I94: =(H94/12)*F94 -> 0 | J94: =IF(D94=$C$7,0,G94-I94) -> 0 | K94: =IFERROR(F94-J94,) -> 0 | L94: =IF(C94>0,SUM(I94:I105),"-") -> - | M94: =IF(C94>0,SUM(J94:J105),"-") -> - | O94: =IFERROR(DATE(YEAR(O93),MONTH(O93)+1,DAY(O93)),"-") -> 48337 | Q94: =IF(S94>0,1+Q93,) -> 80 | R94: =1+R93 -> 8 | S94: =IF('[29]Proforma-Input'!$C$108="No",X93,IF(AF94=TRUE,$P$3,X93)) -> 8878808.9 | T94: =IF(AND($N$8="Yes",Q94<=$P$8),V94,IF(S94>0,$P$7,)) -> 63236.743 | U94: =$P$4 -> 0.068 | V94: =IF(S94>0,U94/12*S94,0) -> 50313.25 | W94: =T94-V94 -> 12923.493 | X94: =S94-W94 -> 8865885.4 | Y94: =IF(Q94=1,V94,Y93+V94) -> 4224824.8 | Z94: =IF(Q94=1,W94,Z93+W94) -> 834114.63 | AA94: =$P$9*S94/12 -> 739.90074 | AB94: =$P$10*AA94 -> 184.97518 | AC94: =IF(P94>0,SUM(V94:V105),"-") -> - | AD94: =IF(P94>0,SUM(W94:W105),"-") -> - | AF94: =IF('[29]Proforma-Input'!$C$108="Yes",MONTH(O94)&YEAR(O94)=MONTH($C$9)&YEAR($C$9),0) -> 0 | AG94: 7
B95: =IFERROR(DATE(YEAR(B94),MONTH(B94)+1,DAY(B94)),"-") -> - | D95: 81 | E95: =1+E94 -> 9 | F95: =IFERROR(IF(B95<$C$9,IF('[29]Proforma-Input'!$C$108="Yes",K94,K94),0),) -> 0 | G95: =IFERROR(IF(D95=$C$7,K94,IF(AND($D$10="Yes",D95<=$C$10),I95,IF(F95>0,$C$8,))),) -> 0 | H95: =IFERROR(IF(B95<$C$9,IF('[29]Proforma-Input'!$C$108="Yes",H94,),0),) -> 0 | I95: =(H95/12)*F95 -> 0 | J95: =IF(D95=$C$7,0,G95-I95) -> 0 | K95: =IFERROR(F95-J95,) -> 0 | L95: =IF(C95>0,SUM(I95:I106),"-") -> - | M95: =IF(C95>0,SUM(J95:J106),"-") -> - | O95: =IFERROR(DATE(YEAR(O94),MONTH(O94)+1,DAY(O94)),"-") -> 48368 | Q95: =IF(S95>0,1+Q94,) -> 81 | R95: =1+R94 -> 9 | S95: =IF('[29]Proforma-Input'!$C$108="No",X94,IF(AF95=TRUE,$P$3,X94)) -> 8865885.4 | T95: =IF(AND($N$8="Yes",Q95<=$P$8),V95,IF(S95>0,$P$7,)) -> 63236.743 | U95: =$P$4 -> 0.068 | V95: =IF(S95>0,U95/12*S95,0) -> 50240.017 | W95: =T95-V95 -> 12996.726 | X95: =S95-W95 -> 8852888.6 | Y95: =IF(Q95=1,V95,Y94+V95) -> 4275064.9 | Z95: =IF(Q95=1,W95,Z94+W95) -> 847111.35 | AA95: =$P$9*S95/12 -> 738.82378 | AB95: =$P$10*AA95 -> 184.70595 | AC95: =IF(P95>0,SUM(V95:V106),"-") -> - | AD95: =IF(P95>0,SUM(W95:W106),"-") -> - | AF95: =IF('[29]Proforma-Input'!$C$108="Yes",MONTH(O95)&YEAR(O95)=MONTH($C$9)&YEAR($C$9),0) -> 0 | AG95: 7
B96: =IFERROR(DATE(YEAR(B95),MONTH(B95)+1,DAY(B95)),"-") -> - | D96: 82 | E96: =1+E95 -> 10 | F96: =IFERROR(IF(B96<$C$9,IF('[29]Proforma-Input'!$C$108="Yes",K95,K95),0),) -> 0 | G96: =IFERROR(IF(D96=$C$7,K95,IF(AND($D$10="Yes",D96<=$C$10),I96,IF(F96>0,$C$8,))),) -> 0 | H96: =IFERROR(IF(B96<$C$9,IF('[29]Proforma-Input'!$C$108="Yes",H95,),0),) -> 0 | I96: =(H96/12)*F96 -> 0 | J96: =IF(D96=$C$7,0,G96-I96) -> 0 | K96: =IFERROR(F96-J96,) -> 0 | L96: =IF(C96>0,SUM(I96:I107),"-") -> - | M96: =IF(C96>0,SUM(J96:J107),"-") -> - | O96: =IFERROR(DATE(YEAR(O95),MONTH(O95)+1,DAY(O95)),"-") -> 48398 | Q96: =IF(S96>0,1+Q95,) -> 82 | R96: =1+R95 -> 10 | S96: =IF('[29]Proforma-Input'!$C$108="No",X95,IF(AF96=TRUE,$P$3,X95)) -> 8852888.6 | T96: =IF(AND($N$8="Yes",Q96<=$P$8),V96,IF(S96>0,$P$7,)) -> 63236.743 | U96: =$P$4 -> 0.068 | V96: =IF(S96>0,U96/12*S96,0) -> 50166.369 | W96: =T96-V96 -> 13070.374 | X96: =S96-W96 -> 8839818.3 | Y96: =IF(Q96=1,V96,Y95+V96) -> 4325231.2 | Z96: =IF(Q96=1,W96,Z95+W96) -> 860181.73 | AA96: =$P$9*S96/12 -> 737.74072 | AB96: =$P$10*AA96 -> 184.43518 | AC96: =IF(P96>0,SUM(V96:V107),"-") -> - | AD96: =IF(P96>0,SUM(W96:W107),"-") -> - | AF96: =IF('[29]Proforma-Input'!$C$108="Yes",MONTH(O96)&YEAR(O96)=MONTH($C$9)&YEAR($C$9),0) -> 0 | AG96: 7
B97: =IFERROR(DATE(YEAR(B96),MONTH(B96)+1,DAY(B96)),"-") -> - | D97: 83 | E97: =1+E96 -> 11 | F97: =IFERROR(IF(B97<$C$9,IF('[29]Proforma-Input'!$C$108="Yes",K96,K96),0),) -> 0 | G97: =IFERROR(IF(D97=$C$7,K96,IF(AND($D$10="Yes",D97<=$C$10),I97,IF(F97>0,$C$8,))),) -> 0 | H97: =IFERROR(IF(B97<$C$9,IF('[29]Proforma-Input'!$C$108="Yes",H96,),0),) -> 0 | I97: =(H97/12)*F97 -> 0 | J97: =IF(D97=$C$7,0,G97-I97) -> 0 | K97: =IFERROR(F97-J97,) -> 0 | L97: =IF(C97>0,SUM(I97:I108),"-") -> - | M97: =IF(C97>0,SUM(J97:J108),"-") -> - | O97: =IFERROR(DATE(YEAR(O96),MONTH(O96)+1,DAY(O96)),"-") -> 48429 | Q97: =IF(S97>0,1+Q96,) -> 83 | R97: =1+R96 -> 11 | S97: =IF('[29]Proforma-Input'!$C$108="No",X96,IF(AF97=TRUE,$P$3,X96)) -> 8839818.3 | T97: =IF(AND($N$8="Yes",Q97<=$P$8),V97,IF(S97>0,$P$7,)) -> 63236.743 | U97: =$P$4 -> 0.068 | V97: =IF(S97>0,U97/12*S97,0) -> 50092.304 | W97: =T97-V97 -> 13144.44 | X97: =S97-W97 -> 8826673.8 | Y97: =IF(Q97=1,V97,Y96+V97) -> 4375323.5 | Z97: =IF(Q97=1,W97,Z96+W97) -> 873326.17 | AA97: =$P$9*S97/12 -> 736.65152 | AB97: =$P$10*AA97 -> 184.16288 | AC97: =IF(P97>0,SUM(V97:V108),"-") -> - | AD97: =IF(P97>0,SUM(W97:W108),"-") -> - | AF97: =IF('[29]Proforma-Input'!$C$108="Yes",MONTH(O97)&YEAR(O97)=MONTH($C$9)&YEAR($C$9),0) -> 0 | AG97: 7
B98: =IFERROR(DATE(YEAR(B97),MONTH(B97)+1,DAY(B97)),"-") -> - | D98: 84 | E98: =1+E97 -> 12 | F98: =IFERROR(IF(B98<$C$9,IF('[29]Proforma-Input'!$C$108="Yes",K97,K97),0),) -> 0 | G98: =IFERROR(IF(D98=$C$7,K97,IF(AND($D$10="Yes",D98<=$C$10),I98,IF(F98>0,$C$8,))),) -> 0 | H98: =IFERROR(IF(B98<$C$9,IF('[29]Proforma-Input'!$C$108="Yes",H97,),0),) -> 0 | I98: =(H98/12)*F98 -> 0 | J98: =IF(D98=$C$7,0,G98-I98) -> 0 | K98: =IFERROR(F98-J98,) -> 0 | L98: =IF(C98>0,SUM(I98:I109),"-") -> - | M98: =IF(C98>0,SUM(J98:J109),"-") -> - | O98: =IFERROR(DATE(YEAR(O97),MONTH(O97)+1,DAY(O97)),"-") -> 48460 | Q98: =IF(S98>0,1+Q97,) -> 84 | R98: =1+R97 -> 12 | S98: =IF('[29]Proforma-Input'!$C$108="No",X97,IF(AF98=TRUE,$P$3,X97)) -> 8826673.8 | T98: =IF(AND($N$8="Yes",Q98<=$P$8),V98,IF(S98>0,$P$7,)) -> 63236.743 | U98: =$P$4 -> 0.068 | V98: =IF(S98>0,U98/12*S98,0) -> 50017.818 | W98: =T98-V98 -> 13218.925 | X98: =S98-W98 -> 8813454.9 | Y98: =IF(Q98=1,V98,Y97+V98) -> 4425341.3 | Z98: =IF(Q98=1,W98,Z97+W98) -> 886545.09 | AA98: =$P$9*S98/12 -> 735.55615 | AB98: =$P$10*AA98 -> 183.88904 | AC98: =IF(P98>0,SUM(V98:V109),"-") -> - | AD98: =IF(P98>0,SUM(W98:W109),"-") -> - | AF98: =IF('[29]Proforma-Input'!$C$108="Yes",MONTH(O98)&YEAR(O98)=MONTH($C$9)&YEAR($C$9),0) -> 0 | AG98: 7
B99: =IFERROR(DATE(YEAR(B98),MONTH(B98)+1,DAY(B98)),"-") -> - | C99: 8 | D99: 85 | E99: 1 | F99: =IFERROR(IF(B99<$C$9,IF('[29]Proforma-Input'!$C$108="Yes",K98,K98),0),) -> 0 | G99: =IFERROR(IF(D99=$C$7,K98,IF(AND($D$10="Yes",D99<=$C$10),I99,IF(F99>0,$C$8,))),) -> 0 | H99: =IFERROR(IF(B99<$C$9,IF('[29]Proforma-Input'!$C$108="Yes",H98,),0),) -> 0 | I99: =(H99/12)*F99 -> 0 | J99: =IF(D99=$C$7,0,G99-I99) -> 0 | K99: =IFERROR(F99-J99,) -> 0 | L99: =IF(C99>0,SUM(I99:I110),"-") -> 0 | M99: =IF(C99>0,SUM(J99:J110),"-") -> 0 | O99: =IFERROR(DATE(YEAR(O98),MONTH(O98)+1,DAY(O98)),"-") -> 48490 | P99: 8 | Q99: =IF(S99>0,1+Q98,) -> 85 | R99: 1 | S99: =IF('[29]Proforma-Input'!$C$108="No",X98,IF(AF99=TRUE,$P$3,X98)) -> 8813454.9 | T99: =IF(AND($N$8="Yes",Q99<=$P$8),V99,IF(S99>0,$P$7,)) -> 63236.743 | U99: =$P$4 -> 0.068 | V99: =IF(S99>0,U99/12*S99,0) -> 49942.911 | W99: =T99-V99 -> 13293.832 | X99: =S99-W99 -> 8800161.1 | Y99: =IF(Q99=1,V99,Y98+V99) -> 4475284.3 | Z99: =IF(Q99=1,W99,Z98+W99) -> 899838.92 | AA99: =$P$9*S99/12 -> 734.45458 | AB99: =$P$10*AA99 -> 183.61364 | AC99: =IF(P99>0,SUM(V99:V110),"-") -> 594247.92 | AD99: =IF(P99>0,SUM(W99:W110),"-") -> 164593 | AF99: =IF('[29]Proforma-Input'!$C$108="Yes",MONTH(O99)&YEAR(O99)=MONTH($C$9)&YEAR($C$9),0) -> 0 | AG99: 8
B100: =IFERROR(DATE(YEAR(B99),MONTH(B99)+1,DAY(B99)),"-") -> - | D100: 86 | E100: =1+E99 -> 2 | F100: =IFERROR(IF(B100<$C$9,IF('[29]Proforma-Input'!$C$108="Yes",K99,K99),0),) -> 0 | G100: =IFERROR(IF(D100=$C$7,K99,IF(AND($D$10="Yes",D100<=$C$10),I100,IF(F100>0,$C$8,))),) -> 0 | H100: =IFERROR(IF(B100<$C$9,IF('[29]Proforma-Input'!$C$108="Yes",H99,),0),) -> 0 | I100: =(H100/12)*F100 -> 0 | J100: =IF(D100=$C$7,0,G100-I100) -> 0 | K100: =IFERROR(F100-J100,) -> 0 | L100: =IF(C100>0,SUM(I100:I111),"-") -> - | M100: =IF(C100>0,SUM(J100:J111),"-") -> - | O100: =IFERROR(DATE(YEAR(O99),MONTH(O99)+1,DAY(O99)),"-") -> 48521 | Q100: =IF(S100>0,1+Q99,) -> 86 | R100: =1+R99 -> 2 | S100: =IF('[29]Proforma-Input'!$C$108="No",X99,IF(AF100=TRUE,$P$3,X99)) -> 8800161.1 | T100: =IF(AND($N$8="Yes",Q100<=$P$8),V100,IF(S100>0,$P$7,)) -> 63236.743 | U100: =$P$4 -> 0.068 | V100: =IF(S100>0,U100/12*S100,0) -> 49867.579 | W100: =T100-V100 -> 13369.164 | X100: =S100-W100 -> 8786791.9 | Y100: =IF(Q100=1,V100,Y99+V100) -> 4525151.8 | Z100: =IF(Q100=1,W100,Z99+W100) -> 913208.09 | AA100: =$P$9*S100/12 -> 733.34676 | AB100: =$P$10*AA100 -> 183.33669 | AC100: =IF(P100>0,SUM(V100:V111),"-") -> - | AD100: =IF(P100>0,SUM(W100:W111),"-") -> - | AF100: =IF('[29]Proforma-Input'!$C$108="Yes",MONTH(O100)&YEAR(O100)=MONTH($C$9)&YEAR($C$9),0) -> 0 | AG100: 8
B101: =IFERROR(DATE(YEAR(B100),MONTH(B100)+1,DAY(B100)),"-") -> - | D101: 87 | E101: =1+E100 -> 3 | F101: =IFERROR(IF(B101<$C$9,IF('[29]Proforma-Input'!$C$108="Yes",K100,K100),0),) -> 0 | G101: =IFERROR(IF(D101=$C$7,K100,IF(AND($D$10="Yes",D101<=$C$10),I101,IF(F101>0,$C$8,))),) -> 0 | H101: =IFERROR(IF(B101<$C$9,IF('[29]Proforma-Input'!$C$108="Yes",H100,),0),) -> 0 | I101: =(H101/12)*F101 -> 0 | J101: =IF(D101=$C$7,0,G101-I101) -> 0 | K101: =IFERROR(F101-J101,) -> 0 | L101: =IF(C101>0,SUM(I101:I112),"-") -> - | M101: =IF(C101>0,SUM(J101:J112),"-") -> - | O101: =IFERROR(DATE(YEAR(O100),MONTH(O100)+1,DAY(O100)),"-") -> 48551 | Q101: =IF(S101>0,1+Q100,) -> 87 | R101: =1+R100 -> 3 | S101: =IF('[29]Proforma-Input'!$C$108="No",X100,IF(AF101=TRUE,$P$3,X100)) -> 8786791.9 | T101: =IF(AND($N$8="Yes",Q101<=$P$8),V101,IF(S101>0,$P$7,)) -> 63236.743 | U101: =$P$4 -> 0.068 | V101: =IF(S101>0,U101/12*S101,0) -> 49791.821 | W101: =T101-V101 -> 13444.922 | X101: =S101-W101 -> 8773347 | Y101: =IF(Q101=1,V101,Y100+V101) -> 4574943.7 | Z101: =IF(Q101=1,W101,Z100+W101) -> 926653.01 | AA101: =$P$9*S101/12 -> 732.23266 | AB101: =$P$10*AA101 -> 183.05816 | AC101: =IF(P101>0,SUM(V101:V112),"-") -> - | AD101: =IF(P101>0,SUM(W101:W112),"-") -> - | AF101: =IF('[29]Proforma-Input'!$C$108="Yes",MONTH(O101)&YEAR(O101)=MONTH($C$9)&YEAR($C$9),0) -> 0 | AG101: 8
B102: =IFERROR(DATE(YEAR(B101),MONTH(B101)+1,DAY(B101)),"-") -> - | D102: 88 | E102: =1+E101 -> 4 | F102: =IFERROR(IF(B102<$C$9,IF('[29]Proforma-Input'!$C$108="Yes",K101,K101),0),) -> 0 | G102: =IFERROR(IF(D102=$C$7,K101,IF(AND($D$10="Yes",D102<=$C$10),I102,IF(F102>0,$C$8,))),) -> 0 | H102: =IFERROR(IF(B102<$C$9,IF('[29]Proforma-Input'!$C$108="Yes",H101,),0),) -> 0 | I102: =(H102/12)*F102 -> 0 | J102: =IF(D102=$C$7,0,G102-I102) -> 0 | K102: =IFERROR(F102-J102,) -> 0 | L102: =IF(C102>0,SUM(I102:I113),"-") -> - | M102: =IF(C102>0,SUM(J102:J113),"-") -> - | O102: =IFERROR(DATE(YEAR(O101),MONTH(O101)+1,DAY(O101)),"-") -> 48582 | Q102: =IF(S102>0,1+Q101,) -> 88 | R102: =1+R101 -> 4 | S102: =IF('[29]Proforma-Input'!$C$108="No",X101,IF(AF102=TRUE,$P$3,X101)) -> 8773347 | T102: =IF(AND($N$8="Yes",Q102<=$P$8),V102,IF(S102>0,$P$7,)) -> 63236.743 | U102: =$P$4 -> 0.068 | V102: =IF(S102>0,U102/12*S102,0) -> 49715.633 | W102: =T102-V102 -> 13521.11 | X102: =S102-W102 -> 8759825.9 | Y102: =IF(Q102=1,V102,Y101+V102) -> 4624659.3 | Z102: =IF(Q102=1,W102,Z101+W102) -> 940174.12 | AA102: =$P$9*S102/12 -> 731.11225 | AB102: =$P$10*AA102 -> 182.77806 | AC102: =IF(P102>0,SUM(V102:V113),"-") -> - | AD102: =IF(P102>0,SUM(W102:W113),"-") -> - | AF102: =IF('[29]Proforma-Input'!$C$108="Yes",MONTH(O102)&YEAR(O102)=MONTH($C$9)&YEAR($C$9),0) -> 0 | AG102: 8
B103: =IFERROR(DATE(YEAR(B102),MONTH(B102)+1,DAY(B102)),"-") -> - | D103: 89 | E103: =1+E102 -> 5 | F103: =IFERROR(IF(B103<$C$9,IF('[29]Proforma-Input'!$C$108="Yes",K102,K102),0),) -> 0 | G103: =IFERROR(IF(D103=$C$7,K102,IF(AND($D$10="Yes",D103<=$C$10),I103,IF(F103>0,$C$8,))),) -> 0 | H103: =IFERROR(IF(B103<$C$9,IF('[29]Proforma-Input'!$C$108="Yes",H102,),0),) -> 0 | I103: =(H103/12)*F103 -> 0 | J103: =IF(D103=$C$7,0,G103-I103) -> 0 | K103: =IFERROR(F103-J103,) -> 0 | L103: =IF(C103>0,SUM(I103:I114),"-") -> - | M103: =IF(C103>0,SUM(J103:J114),"-") -> - | O103: =IFERROR(DATE(YEAR(O102),MONTH(O102)+1,DAY(O102)),"-") -> 48613 | Q103: =IF(S103>0,1+Q102,) -> 89 | R103: =1+R102 -> 5 | S103: =IF('[29]Proforma-Input'!$C$108="No",X102,IF(AF103=TRUE,$P$3,X102)) -> 8759825.9 | T103: =IF(AND($N$8="Yes",Q103<=$P$8),V103,IF(S103>0,$P$7,)) -> 63236.743 | U103: =$P$4 -> 0.068 | V103: =IF(S103>0,U103/12*S103,0) -> 49639.013 | W103: =T103-V103 -> 13597.73 | X103: =S103-W103 -> 8746228.1 | Y103: =IF(Q103=1,V103,Y102+V103) -> 4674298.3 | Z103: =IF(Q103=1,W103,Z102+W103) -> 953771.85 | AA103: =$P$9*S103/12 -> 729.98549 | AB103: =$P$10*AA103 -> 182.49637 | AC103: =IF(P103>0,SUM(V103:V114),"-") -> - | AD103: =IF(P103>0,SUM(W103:W114),"-") -> - | AF103: =IF('[29]Proforma-Input'!$C$108="Yes",MONTH(O103)&YEAR(O103)=MONTH($C$9)&YEAR($C$9),0) -> 0 | AG103: 8
...

Sheet 0-5M
B2: Assumable Loan Info | O2: New Loan Info | T2: Annual Service Fee | U2: Matthews Split | V2: 10 Loans
B3: Original Loan Balance | C3: ='[29]Proforma-Input'!E113 -> #REF! | O3: New Loan Balance | P3: 5000000 | S3: Year 1 | T3: =SUM(AA16:AA27) -> 4974.6852 | U3: =SUM(AB16:AB27) -> 497.46852 | V3: =U3*10 -> 4974.6852
B4: Existing Loan Balance | C4: ='[29]Proforma-Input'!E114 -> 0 | O4: Interest Rate | P4: 0.065 | S4: Year 2 | T4: =SUM(AA28:AA39) -> 4917.1036 | U4: =SUM(AB28:AB39) -> 491.71036 | V4: =U4*10 -> 4917.1036
B5: Interest Rate | C5: ='[29]Proforma-Input'!K113 -> #REF! | O5: Amortization (In Years) | P5: 30 | S5: Year 3 | T5: =SUM(AA40:AA51) -> 4855.6656 | U5: =SUM(AB40:AB51) -> 485.56656 | V5: =U5*10 -> 4855.6656
B6: Amortization (In Years) | C6: ='[29]Proforma-Input'!K110 -> #REF! | O6: Term(Years) | P6: 5 | S6: Year 4 | T6: =SUM(AA52:AA63) -> 4790.113 | U6: =SUM(AB52:AB63) -> 479.0113 | V6: =U6*10 -> 4790.113
B7: Remaining Term in Months | C7: ='[29]Optimistic Return Calculation'!E54 -> 0 | O7: Monthly Payment | P7: =PMT(P4/12,P5*12,-P3,0) -> 31603.401 | S7: Year 5 | T7: =SUM(AA64:AA75) -> 4720.1702 | U7: =SUM(AB64:AB75) -> 472.01702 | V7: =U7*10 -> 4720.1702
B8: Monthly Payment | C8: ='[29]Proforma-Input'!K114 -> 0 | N8: Yes | O8: I/O(Monthly): | P8: 0 | Q8: Total(Term)
B9: Final Payment Date | C9: =IFERROR('[29]Proforma-Input'!E111+(C7*30),"-") -> - | O9: Service Fee | P9: 0.001 | Q9: =SUMIFS($AA$16:$AA$375, $Q$16:$Q$375, "<=" & 12 * $P$6) -> 24257.738
B10: IO: | C10: =IFERROR('[29]Proforma-Input'!K116*12,"-") -> - | D10: =IF(C10>0,"Yes","No") -> Yes | O10: Matthews Split | P10: 0.1 | Q10: =SUMIFS($AB$16:$AB$375, $Q$16:$Q$375, "<=" & 12 * $P$6) -> 2425.7738
C14: Assumable Loan Table | P14: Loan Calculations
B15: Month | C15: Year | D15: # of Months | E15: Month/Year | F15: Beg. Balance | G15: Payment | H15: Rate | I15: Interest | J15: Principal | K15: End Balance | L15: Interest/Year | M15: Principal/Year | O15: Month | P15: Year | Q15: # of Months | R15: Month/Year | S15: Beg. Balance | T15: Payment | U15: Rate | V15: Interest | W15: Principal | X15: End Balance | Y15: Cumulative Interest | Z15: Cumulative Principal | AA15: Service Fee | AB15: Matthews Split | AC15: Interest/Year | AD15: Principal/Year | AF15: Input Data
B16: ='[29]Proforma-Input'!$E$111 -> - | C16: 1 | D16: 1 | E16: 1 | F16: =IF('[29]Proforma-Input'!$C$108="Yes",$C$4,) -> 0 | G16: =IF(AND($D$10="Yes",D16<=$C$10),I16,IF(F16>0,$C$8,)) -> 0 | H16: =IF('[29]Proforma-Input'!$C$108="Yes",C5,) -> 0 | I16: =(H16/12)*F16 -> 0 | J16: =IF(D16=$C$7,0,G16-I16) -> 0 | K16: =IFERROR(F16-J16,) -> 0 | L16: =IF(C16>0,SUM(I16:I27),"-") -> 0 | M16: =IF(C16>0,SUM(J16:J27),"-") -> 0 | O16: =NOW() -> 45933.485 | P16: 1 | Q16: =IF(S16>0,1,) -> 1 | R16: 1 | S16: =IF('[29]Proforma-Input'!$C$108="No",$P$3,IF(AF16="True",$P$3,)) -> 5000000 | T16: =IF(AND($N$8="Yes",Q16<=$P$8),V16,IF(S16>0,$P$7,)) -> 31603.401 | U16: =$P$4 -> 0.065 | V16: =IF(S16>0,U16/12*S16,0) -> 27083.333 | W16: =T16-V16 -> 4520.0678 | X16: =S16-W16 -> 4995479.9 | Y16: =IF(Q16=1,V16,Y15+V16) -> 27083.333 | Z16: =IF(Q16=1,W16,Z15+W16) -> 4520.0678 | AA16: =$P$9*S16/12 -> 416.66667 | AB16: =$P$10*AA16 -> 41.666667 | AC16: =IF(P16>0,SUM(V16:V27),"-") -> 323354.54 | AD16: =IF(P16>0,SUM(W16:W27),"-") -> 55886.273 | AF16: =IF('[29]Proforma-Input'!$C$108="Yes",MONTH(O16)&YEAR(O16)=MONTH($C$9)&YEAR($C$9),0) -> 0 | AG16: 1
B17: =IFERROR(DATE(YEAR(B16),MONTH(B16)+1,DAY(B16)),"-") -> - | D17: 2 | E17: =1+E16 -> 2 | F17: =IFERROR(IF(B17<$C$9,IF('[29]Proforma-Input'!$C$108="Yes",K16,K16),0),) -> 0 | G17: =IFERROR(IF(D17=$C$7,K16,IF(AND($D$10="Yes",D17<=$C$10),I17,IF(F17>0,$C$8,))),) -> 0 | H17: =IFERROR(IF(B17<$C$9,IF('[29]Proforma-Input'!$C$108="Yes",H16,),0),) -> 0 | I17: =(H17/12)*F17 -> 0 | J17: =IF(D17=$C$7,0,G17-I17) -> 0 | K17: =IFERROR(F17-J17,) -> 0 | L17: =IF(C17>0,SUM(I17:I28),"-") -> - | M17: =IF(C17>0,SUM(J17:J28),"-") -> - | O17: =IFERROR(DATE(YEAR(O16),MONTH(O16)+1,DAY(O16)),"-") -> 45964 | Q17: =IF(S17>0,1+Q16,) -> 2 | R17: =1+R16 -> 2 | S17: =IF('[29]Proforma-Input'!$C$108="No",X16,IF(AF17=TRUE,$P$3,X16)) -> 4995479.9 | T17: =IF(AND($N$8="Yes",Q17<=$P$8),V17,IF(S17>0,$P$7,)) -> 31603.401 | U17: =$P$4 -> 0.065 | V17: =IF(S17>0,U17/12*S17,0) -> 27058.85 | W17: =T17-V17 -> 4544.5515 | X17: =S17-W17 -> 4990935.4 | Y17: =IF(Q17=1,V17,Y16+V17) -> 54142.183 | Z17: =IF(Q17=1,W17,Z16+W17) -> 9064.6194 | AA17: =$P$9*S17/12 -> 416.28999 | AB17: =$P$10*AA17 -> 41.628999 | AC17: =IF(P17>0,SUM(V17:V28),"-") -> - | AD17: =IF(P17>0,SUM(W17:W28),"-") -> - | AF17: =IF('[29]Proforma-Input'!$C$108="Yes",MONTH(O17)&YEAR(O17)=MONTH($C$9)&YEAR($C$9),0) -> 0 | AG17: 1
B18: =IFERROR(DATE(YEAR(B17),MONTH(B17)+1,DAY(B17)),"-") -> - | D18: 3 | E18: =1+E17 -> 3 | F18: =IFERROR(IF(B18<$C$9,IF('[29]Proforma-Input'!$C$108="Yes",K17,K17),0),) -> 0 | G18: =IFERROR(IF(D18=$C$7,K17,IF(AND($D$10="Yes",D18<=$C$10),I18,IF(F18>0,$C$8,))),) -> 0 | H18: =IFERROR(IF(B18<$C$9,IF('[29]Proforma-Input'!$C$108="Yes",H17,),0),) -> 0 | I18: =(H18/12)*F18 -> 0 | J18: =IF(D18=$C$7,0,G18-I18) -> 0 | K18: =IFERROR(F18-J18,) -> 0 | L18: =IF(C18>0,SUM(I18:I29),"-") -> - | M18: =IF(C18>0,SUM(J18:J29),"-") -> - | O18: =IFERROR(DATE(YEAR(O17),MONTH(O17)+1,DAY(O17)),"-") -> 45994 | Q18: =IF(S18>0,1+Q17,) -> 3 | R18: =1+R17 -> 3 | S18: =IF('[29]Proforma-Input'!$C$108="No",X17,IF(AF18=TRUE,$P$3,X17)) -> 4990935.4 | T18: =IF(AND($N$8="Yes",Q18<=$P$8),V18,IF(S18>0,$P$7,)) -> 31603.401 | U18: =$P$4 -> 0.065 | V18: =IF(S18>0,U18/12*S18,0) -> 27034.233 | W18: =T18-V18 -> 4569.1679 | X18: =S18-W18 -> 4986366.2 | Y18: =IF(Q18=1,V18,Y17+V18) -> 81176.416 | Z18: =IF(Q18=1,W18,Z17+W18) -> 13633.787 | AA18: =$P$9*S18/12 -> 415.91128 | AB18: =$P$10*AA18 -> 41.591128 | AC18: =IF(P18>0,SUM(V18:V29),"-") -> - | AD18: =IF(P18>0,SUM(W18:W29),"-") -> - | AF18: =IF('[29]Proforma-Input'!$C$108="Yes",MONTH(O18)&YEAR(O18)=MONTH($C$9)&YEAR($C$9),0) -> 0 | AG18: 1
B19: =IFERROR(DATE(YEAR(B18),MONTH(B18)+1,DAY(B18)),"-") -> - | D19: 4 | E19: =1+E18 -> 4 | F19: =IFERROR(IF(B19<$C$9,IF('[29]Proforma-Input'!$C$108="Yes",K18,K18),0),) -> 0 | G19: =IFERROR(IF(D19=$C$7,K18,IF(AND($D$10="Yes",D19<=$C$10),I19,IF(F19>0,$C$8,))),) -> 0 | H19: =IFERROR(IF(B19<$C$9,IF('[29]Proforma-Input'!$C$108="Yes",H18,),0),) -> 0 | I19: =(H19/12)*F19 -> 0 | J19: =IF(D19=$C$7,0,G19-I19) -> 0 | K19: =IFERROR(F19-J19,) -> 0 | L19: =IF(C19>0,SUM(I19:I30),"-") -> - | M19: =IF(C19>0,SUM(J19:J30),"-") -> - | O19: =IFERROR(DATE(YEAR(O18),MONTH(O18)+1,DAY(O18)),"-") -> 46025 | Q19: =IF(S19>0,1+Q18,) -> 4 | R19: =1+R18 -> 4 | S19: =IF('[29]Proforma-Input'!$C$108="No",X18,IF(AF19=TRUE,$P$3,X18)) -> 4986366.2 | T19: =IF(AND($N$8="Yes",Q19<=$P$8),V19,IF(S19>0,$P$7,)) -> 31603.401 | U19: =$P$4 -> 0.065 | V19: =IF(S19>0,U19/12*S19,0) -> 27009.484 | W19: =T19-V19 -> 4593.9175 | X19: =S19-W19 -> 4981772.3 | Y19: =IF(Q19=1,V19,Y18+V19) -> 108185.9 | Z19: =IF(Q19=1,W19,Z18+W19) -> 18227.705 | AA19: =$P$9*S19/12 -> 415.53052 | AB19: =$P$10*AA19 -> 41.553052 | AC19: =IF(P19>0,SUM(V19:V30),"-") -> - | AD19: =IF(P19>0,SUM(W19:W30),"-") -> - | AF19: =IF('[29]Proforma-Input'!$C$108="Yes",MONTH(O19)&YEAR(O19)=MONTH($C$9)&YEAR($C$9),0) -> 0 | AG19: 1
B20: =IFERROR(DATE(YEAR(B19),MONTH(B19)+1,DAY(B19)),"-") -> - | D20: 5 | E20: =1+E19 -> 5 | F20: =IFERROR(IF(B20<$C$9,IF('[29]Proforma-Input'!$C$108="Yes",K19,K19),0),) -> 0 | G20: =IFERROR(IF(D20=$C$7,K19,IF(AND($D$10="Yes",D20<=$C$10),I20,IF(F20>0,$C$8,))),) -> 0 | H20: =IFERROR(IF(B20<$C$9,IF('[29]Proforma-Input'!$C$108="Yes",H19,),0),) -> 0 | I20: =(H20/12)*F20 -> 0 | J20: =IF(D20=$C$7,0,G20-I20) -> 0 | K20: =IFERROR(F20-J20,) -> 0 | L20: =IF(C20>0,SUM(I20:I31),"-") -> - | M20: =IF(C20>0,SUM(J20:J31),"-") -> - | O20: =IFERROR(DATE(YEAR(O19),MONTH(O19)+1,DAY(O19)),"-") -> 46056 | Q20: =IF(S20>0,1+Q19,) -> 5 | R20: =1+R19 -> 5 | S20: =IF('[29]Proforma-Input'!$C$108="No",X19,IF(AF20=TRUE,$P$3,X19)) -> 4981772.3 | T20: =IF(AND($N$8="Yes",Q20<=$P$8),V20,IF(S20>0,$P$7,)) -> 31603.401 | U20: =$P$4 -> 0.065 | V20: =IF(S20>0,U20/12*S20,0) -> 26984.6 | W20: =T20-V20 -> 4618.8012 | X20: =S20-W20 -> 4977153.5 | Y20: =IF(Q20=1,V20,Y19+V20) -> 135170.5 | Z20: =IF(Q20=1,W20,Z19+W20) -> 22846.506 | AA20: =$P$9*S20/12 -> 415.14769 | AB20: =$P$10*AA20 -> 41.514769 | AC20: =IF(P20>0,SUM(V20:V31),"-") -> - | AD20: =IF(P20>0,SUM(W20:W31),"-") -> - | AF20: =IF('[29]Proforma-Input'!$C$108="Yes",MONTH(O20)&YEAR(O20)=MONTH($C$9)&YEAR($C$9),0) -> 0 | AG20: 1
B21: =IFERROR(DATE(YEAR(B20),MONTH(B20)+1,DAY(B20)),"-") -> - | D21: 6 | E21: =1+E20 -> 6 | F21: =IFERROR(IF(B21<$C$9,IF('[29]Proforma-Input'!$C$108="Yes",K20,K20),0),) -> 0 | G21: =IFERROR(IF(D21=$C$7,K20,IF(AND($D$10="Yes",D21<=$C$10),I21,IF(F21>0,$C$8,))),) -> 0 | H21: =IFERROR(IF(B21<$C$9,IF('[29]Proforma-Input'!$C$108="Yes",H20,),0),) -> 0 | I21: =(H21/12)*F21 -> 0 | J21: =IF(D21=$C$7,0,G21-I21) -> 0 | K21: =IFERROR(F21-J21,) -> 0 | L21: =IF(C21>0,SUM(I21:I32),"-") -> - | M21: =IF(C21>0,SUM(J21:J32),"-") -> - | O21: =IFERROR(DATE(YEAR(O20),MONTH(O20)+1,DAY(O20)),"-") -> 46084 | Q21: =IF(S21>0,1+Q20,) -> 6 | R21: =1+R20 -> 6 | S21: =IF('[29]Proforma-Input'!$C$108="No",X20,IF(AF21=TRUE,$P$3,X20)) -> 4977153.5 | T21: =IF(AND($N$8="Yes",Q21<=$P$8),V21,IF(S21>0,$P$7,)) -> 31603.401 | U21: =$P$4 -> 0.065 | V21: =IF(S21>0,U21/12*S21,0) -> 26959.581 | W21: =T21-V21 -> 4643.8197 | X21: =S21-W21 -> 4972509.7 | Y21: =IF(Q21=1,V21,Y20+V21) -> 162130.08 | Z21: =IF(Q21=1,W21,Z20+W21) -> 27490.326 | AA21: =$P$9*S21/12 -> 414.76279 | AB21: =$P$10*AA21 -> 41.476279 | AC21: =IF(P21>0,SUM(V21:V32),"-") -> - | AD21: =IF(P21>0,SUM(W21:W32),"-") -> - | AF21: =IF('[29]Proforma-Input'!$C$108="Yes",MONTH(O21)&YEAR(O21)=MONTH($C$9)&YEAR($C$9),0) -> 0 | AG21: 1
B22: =IFERROR(DATE(YEAR(B21),MONTH(B21)+1,DAY(B21)),"-") -> - | D22: 7 | E22: =1+E21 -> 7 | F22: =IFERROR(IF(B22<$C$9,IF('[29]Proforma-Input'!$C$108="Yes",K21,K21),0),) -> 0 | G22: =IFERROR(IF(D22=$C$7,K21,IF(AND($D$10="Yes",D22<=$C$10),I22,IF(F22>0,$C$8,))),) -> 0 | H22: =IFERROR(IF(B22<$C$9,IF('[29]Proforma-Input'!$C$108="Yes",H21,),0),) -> 0 | I22: =(H22/12)*F22 -> 0 | J22: =IF(D22=$C$7,0,G22-I22) -> 0 | K22: =IFERROR(F22-J22,) -> 0 | L22: =IF(C22>0,SUM(I22:I33),"-") -> - | M22: =IF(C22>0,SUM(J22:J33),"-") -> - | O22: =IFERROR(DATE(YEAR(O21),MONTH(O21)+1,DAY(O21)),"-") -> 46115 | Q22: =IF(S22>0,1+Q21,) -> 7 | R22: =1+R21 -> 7 | S22: =IF('[29]Proforma-Input'!$C$108="No",X21,IF(AF22=TRUE,$P$3,X21)) -> 4972509.7 | T22: =IF(AND($N$8="Yes",Q22<=$P$8),V22,IF(S22>0,$P$7,)) -> 31603.401 | U22: =$P$4 -> 0.065 | V22: =IF(S22>0,U22/12*S22,0) -> 26934.427 | W22: =T22-V22 -> 4668.9738 | X22: =S22-W22 -> 4967840.7 | Y22: =IF(Q22=1,V22,Y21+V22) -> 189064.51 | Z22: =IF(Q22=1,W22,Z21+W22) -> 32159.3 | AA22: =$P$9*S22/12 -> 414.37581 | AB22: =$P$10*AA22 -> 41.437581 | AC22: =IF(P22>0,SUM(V22:V33),"-") -> - | AD22: =IF(P22>0,SUM(W22:W33),"-") -> - | AF22: =IF('[29]Proforma-Input'!$C$108="Yes",MONTH(O22)&YEAR(O22)=MONTH($C$9)&YEAR($C$9),0) -> 0 | AG22: 1
B23: =IFERROR(DATE(YEAR(B22),MONTH(B22)+1,DAY(B22)),"-") -> - | D23: 8 | E23: =1+E22 -> 8 | F23: =IFERROR(IF(B23<$C$9,IF('[29]Proforma-Input'!$C$108="Yes",K22,K22),0),) -> 0 | G23: =IFERROR(IF(D23=$C$7,K22,IF(AND($D$10="Yes",D23<=$C$10),I23,IF(F23>0,$C$8,))),) -> 0 | H23: =IFERROR(IF(B23<$C$9,IF('[29]Proforma-Input'!$C$108="Yes",H22,),0),) -> 0 | I23: =(H23/12)*F23 -> 0 | J23: =IF(D23=$C$7,0,G23-I23) -> 0 | K23: =IFERROR(F23-J23,) -> 0 | L23: =IF(C23>0,SUM(I23:I34),"-") -> - | M23: =IF(C23>0,SUM(J23:J34),"-") -> - | O23: =IFERROR(DATE(YEAR(O22),MONTH(O22)+1,DAY(O22)),"-") -> 46145 | Q23: =IF(S23>0,1+Q22,) -> 8 | R23: =1+R22 -> 8 | S23: =IF('[29]Proforma-Input'!$C$108="No",X22,IF(AF23=TRUE,$P$3,X22)) -> 4967840.7 | T23: =IF(AND($N$8="Yes",Q23<=$P$8),V23,IF(S23>0,$P$7,)) -> 31603.401 | U23: =$P$4 -> 0.065 | V23: =IF(S23>0,U23/12*S23,0) -> 26909.137 | W23: =T23-V23 -> 4694.264 | X23: =S23-W23 -> 4963146.4 | Y23: =IF(Q23=1,V23,Y22+V23) -> 215973.65 | Z23: =IF(Q23=1,W23,Z22+W23) -> 36853.564 | AA23: =$P$9*S23/12 -> 413.98673 | AB23: =$P$10*AA23 -> 41.398673 | AC23: =IF(P23>0,SUM(V23:V34),"-") -> - | AD23: =IF(P23>0,SUM(W23:W34),"-") -> - | AF23: =IF('[29]Proforma-Input'!$C$108="Yes",MONTH(O23)&YEAR(O23)=MONTH($C$9)&YEAR($C$9),0) -> 0 | AG23: 1
B24: =IFERROR(DATE(YEAR(B23),MONTH(B23)+1,DAY(B23)),"-") -> - | D24: 9 | E24: =1+E23 -> 9 | F24: =IFERROR(IF(B24<$C$9,IF('[29]Proforma-Input'!$C$108="Yes",K23,K23),0),) -> 0 | G24: =IFERROR(IF(D24=$C$7,K23,IF(AND($D$10="Yes",D24<=$C$10),I24,IF(F24>0,$C$8,))),) -> 0 | H24: =IFERROR(IF(B24<$C$9,IF('[29]Proforma-Input'!$C$108="Yes",H23,),0),) -> 0 | I24: =(H24/12)*F24 -> 0 | J24: =IF(D24=$C$7,0,G24-I24) -> 0 | K24: =IFERROR(F24-J24,) -> 0 | L24: =IF(C24>0,SUM(I24:I35),"-") -> - | M24: =IF(C24>0,SUM(J24:J35),"-") -> - | O24: =IFERROR(DATE(YEAR(O23),MONTH(O23)+1,DAY(O23)),"-") -> 46176 | Q24: =IF(S24>0,1+Q23,) -> 9 | R24: =1+R23 -> 9 | S24: =IF('[29]Proforma-Input'!$C$108="No",X23,IF(AF24=TRUE,$P$3,X23)) -> 4963146.4 | T24: =IF(AND($N$8="Yes",Q24<=$P$8),V24,IF(S24>0,$P$7,)) -> 31603.401 | U24: =$P$4 -> 0.065 | V24: =IF(S24>0,U24/12*S24,0) -> 26883.71 | W24: =T24-V24 -> 4719.6913 | X24: =S24-W24 -> 4958426.7 | Y24: =IF(Q24=1,V24,Y23+V24) -> 242857.36 | Z24: =IF(Q24=1,W24,Z23+W24) -> 41573.255 | AA24: =$P$9*S24/12 -> 413.59554 | AB24: =$P$10*AA24 -> 41.359554 | AC24: =IF(P24>0,SUM(V24:V35),"-") -> - | AD24: =IF(P24>0,SUM(W24:W35),"-") -> - | AF24: =IF('[29]Proforma-Input'!$C$108="Yes",MONTH(O24)&YEAR(O24)=MONTH($C$9)&YEAR($C$9),0) -> 0 | AG24: 1
B25: =IFERROR(DATE(YEAR(B24),MONTH(B24)+1,DAY(B24)),"-") -> - | D25: 10 | E25: =1+E24 -> 10 | F25: =IFERROR(IF(B25<$C$9,IF('[29]Proforma-Input'!$C$108="Yes",K24,K24),0),) -> 0 | G25: =IFERROR(IF(D25=$C$7,K24,IF(AND($D$10="Yes",D25<=$C$10),I25,IF(F25>0,$C$8,))),) -> 0 | H25: =IFERROR(IF(B25<$C$9,IF('[29]Proforma-Input'!$C$108="Yes",H24,),0),) -> 0 | I25: =(H25/12)*F25 -> 0 | J25: =IF(D25=$C$7,0,G25-I25) -> 0 | K25: =IFERROR(F25-J25,) -> 0 | L25: =IF(C25>0,SUM(I25:I36),"-") -> - | M25: =IF(C25>0,SUM(J25:J36),"-") -> - | O25: =IFERROR(DATE(YEAR(O24),MONTH(O24)+1,DAY(O24)),"-") -> 46206 | Q25: =IF(S25>0,1+Q24,) -> 10 | R25: =1+R24 -> 10 | S25: =IF('[29]Proforma-Input'!$C$108="No",X24,IF(AF25=TRUE,$P$3,X24)) -> 4958426.7 | T25: =IF(AND($N$8="Yes",Q25<=$P$8),V25,IF(S25>0,$P$7,)) -> 31603.401 | U25: =$P$4 -> 0.065 | V25: =IF(S25>0,U25/12*S25,0) -> 26858.145 | W25: =T25-V25 -> 4745.2563 | X25: =S25-W25 -> 4953681.5 | Y25: =IF(Q25=1,V25,Y24+V25) -> 269715.5 | Z25: =IF(Q25=1,W25,Z24+W25) -> 46318.511 | AA25: =$P$9*S25/12 -> 413.20223 | AB25: =$P$10*AA25 -> 41.320223 | AC25: =IF(P25>0,SUM(V25:V36),"-") -> - | AD25: =IF(P25>0,SUM(W25:W36),"-") -> - | AF25: =IF('[29]Proforma-Input'!$C$108="Yes",MONTH(O25)&YEAR(O25)=MONTH($C$9)&YEAR($C$9),0) -> 0 | AG25: 1
B26: =IFERROR(DATE(YEAR(B25),MONTH(B25)+1,DAY(B25)),"-") -> - | D26: 11 | E26: =1+E25 -> 11 | F26: =IFERROR(IF(B26<$C$9,IF('[29]Proforma-Input'!$C$108="Yes",K25,K25),0),) -> 0 | G26: =IFERROR(IF(D26=$C$7,K25,IF(AND($D$10="Yes",D26<=$C$10),I26,IF(F26>0,$C$8,))),) -> 0 | H26: =IFERROR(IF(B26<$C$9,IF('[29]Proforma-Input'!$C$108="Yes",H25,),0),) -> 0 | I26: =(H26/12)*F26 -> 0 | J26: =IF(D26=$C$7,0,G26-I26) -> 0 | K26: =IFERROR(F26-J26,) -> 0 | L26: =IF(C26>0,SUM(I26:I37),"-") -> - | M26: =IF(C26>0,SUM(J26:J37),"-") -> - | O26: =IFERROR(DATE(YEAR(O25),MONTH(O25)+1,DAY(O25)),"-") -> 46237 | Q26: =IF(S26>0,1+Q25,) -> 11 | R26: =1+R25 -> 11 | S26: =IF('[29]Proforma-Input'!$C$108="No",X25,IF(AF26=TRUE,$P$3,X25)) -> 4953681.5 | T26: =IF(AND($N$8="Yes",Q26<=$P$8),V26,IF(S26>0,$P$7,)) -> 31603.401 | U26: =$P$4 -> 0.065 | V26: =IF(S26>0,U26/12*S26,0) -> 26832.441 | W26: =T26-V26 -> 4770.9598 | X26: =S26-W26 -> 4948910.5 | Y26: =IF(Q26=1,V26,Y25+V26) -> 296547.94 | Z26: =IF(Q26=1,W26,Z25+W26) -> 51089.471 | AA26: =$P$9*S26/12 -> 412.80679 | AB26: =$P$10*AA26 -> 41.280679 | AC26: =IF(P26>0,SUM(V26:V37),"-") -> - | AD26: =IF(P26>0,SUM(W26:W37),"-") -> - | AF26: =IF('[29]Proforma-Input'!$C$108="Yes",MONTH(O26)&YEAR(O26)=MONTH($C$9)&YEAR($C$9),0) -> 0 | AG26: 1
B27: =IFERROR(DATE(YEAR(B26),MONTH(B26)+1,DAY(B26)),"-") -> - | D27: 12 | E27: =1+E26 -> 12 | F27: =IFERROR(IF(B27<$C$9,IF('[29]Proforma-Input'!$C$108="Yes",K26,K26),0),) -> 0 | G27: =IFERROR(IF(D27=$C$7,K26,IF(AND($D$10="Yes",D27<=$C$10),I27,IF(F27>0,$C$8,))),) -> 0 | H27: =IFERROR(IF(B27<$C$9,IF('[29]Proforma-Input'!$C$108="Yes",H26,),0),) -> 0 | I27: =(H27/12)*F27 -> 0 | J27: =IF(D27=$C$7,0,G27-I27) -> 0 | K27: =IFERROR(F27-J27,) -> 0 | L27: =IF(C27>0,SUM(I27:I38),"-") -> - | M27: =IF(C27>0,SUM(J27:J38),"-") -> - | O27: =IFERROR(DATE(YEAR(O26),MONTH(O26)+1,DAY(O26)),"-") -> 46268 | Q27: =IF(S27>0,1+Q26,) -> 12 | R27: =1+R26 -> 12 | S27: =IF('[29]Proforma-Input'!$C$108="No",X26,IF(AF27=TRUE,$P$3,X26)) -> 4948910.5 | T27: =IF(AND($N$8="Yes",Q27<=$P$8),V27,IF(S27>0,$P$7,)) -> 31603.401 | U27: =$P$4 -> 0.065 | V27: =IF(S27>0,U27/12*S27,0) -> 26806.599 | W27: =T27-V27 -> 4796.8025 | X27: =S27-W27 -> 4944113.7 | Y27: =IF(Q27=1,V27,Y26+V27) -> 323354.54 | Z27: =IF(Q27=1,W27,Z26+W27) -> 55886.273 | AA27: =$P$9*S27/12 -> 412.40921 | AB27: =$P$10*AA27 -> 41.240921 | AC27: =IF(P27>0,SUM(V27:V38),"-") -> - | AD27: =IF(P27>0,SUM(W27:W38),"-") -> - | AF27: =IF('[29]Proforma-Input'!$C$108="Yes",MONTH(O27)&YEAR(O27)=MONTH($C$9)&YEAR($C$9),0) -> 0 | AG27: 1
B28: =IFERROR(DATE(YEAR(B27),MONTH(B27)+1,DAY(B27)),"-") -> - | C28: 2 | D28: 13 | E28: 1 | F28: =IFERROR(IF(B28<$C$9,IF('[29]Proforma-Input'!$C$108="Yes",K27,K27),0),) -> 0 | G28: =IFERROR(IF(D28=$C$7,K27,IF(AND($D$10="Yes",D28<=$C$10),I28,IF(F28>0,$C$8,))),) -> 0 | H28: =IFERROR(IF(B28<$C$9,IF('[29]Proforma-Input'!$C$108="Yes",H27,),0),) -> 0 | I28: =(H28/12)*F28 -> 0 | J28: =IF(D28=$C$7,0,G28-I28) -> 0 | K28: =IFERROR(F28-J28,) -> 0 | L28: =IF(C28>0,SUM(I28:I39),"-") -> 0 | M28: =IF(C28>0,SUM(J28:J39),"-") -> 0 | O28: =IFERROR(DATE(YEAR(O27),MONTH(O27)+1,DAY(O27)),"-") -> 46298 | P28: 2 | Q28: =IF(S28>0,1+Q27,) -> 13 | R28: 1 | S28: =IF('[29]Proforma-Input'!$C$108="No",X27,IF(AF28=TRUE,$P$3,X27)) -> 4944113.7 | T28: =IF(AND($N$8="Yes",Q28<=$P$8),V28,IF(S28>0,$P$7,)) -> 31603.401 | U28: =$P$4 -> 0.065 | V28: =IF(S28>0,U28/12*S28,0) -> 26780.616 | W28: =T28-V28 -> 4822.7852 | X28: =S28-W28 -> 4939290.9 | Y28: =IF(Q28=1,V28,Y27+V28) -> 350135.16 | Z28: =IF(Q28=1,W28,Z27+W28) -> 60709.059 | AA28: =$P$9*S28/12 -> 412.00948 | AB28: =$P$10*AA28 -> 41.200948 | AC28: =IF(P28>0,SUM(V28:V39),"-") -> 319611.73 | AD28: =IF(P28>0,SUM(W28:W39),"-") -> 59629.081 | AF28: =IF('[29]Proforma-Input'!$C$108="Yes",MONTH(O28)&YEAR(O28)=MONTH($C$9)&YEAR($C$9),0) -> 0 | AG28: 2
B29: =IFERROR(DATE(YEAR(B28),MONTH(B28)+1,DAY(B28)),"-") -> - | D29: 14 | E29: =1+E28 -> 2 | F29: =IFERROR(IF(B29<$C$9,IF('[29]Proforma-Input'!$C$108="Yes",K28,K28),0),) -> 0 | G29: =IFERROR(IF(D29=$C$7,K28,IF(AND($D$10="Yes",D29<=$C$10),I29,IF(F29>0,$C$8,))),) -> 0 | H29: =IFERROR(IF(B29<$C$9,IF('[29]Proforma-Input'!$C$108="Yes",H28,),0),) -> 0 | I29: =(H29/12)*F29 -> 0 | J29: =IF(D29=$C$7,0,G29-I29) -> 0 | K29: =IFERROR(F29-J29,) -> 0 | L29: =IF(C29>0,SUM(I29:I40),"-") -> - | M29: =IF(C29>0,SUM(J29:J40),"-") -> - | O29: =IFERROR(DATE(YEAR(O28),MONTH(O28)+1,DAY(O28)),"-") -> 46329 | Q29: =IF(S29>0,1+Q28,) -> 14 | R29: =1+R28 -> 2 | S29: =IF('[29]Proforma-Input'!$C$108="No",X28,IF(AF29=TRUE,$P$3,X28)) -> 4939290.9 | T29: =IF(AND($N$8="Yes",Q29<=$P$8),V29,IF(S29>0,$P$7,)) -> 31603.401 | U29: =$P$4 -> 0.065 | V29: =IF(S29>0,U29/12*S29,0) -> 26754.493 | W29: =T29-V29 -> 4848.9086 | X29: =S29-W29 -> 4934442 | Y29: =IF(Q29=1,V29,Y28+V29) -> 376889.65 | Z29: =IF(Q29=1,W29,Z28+W29) -> 65557.967 | AA29: =$P$9*S29/12 -> 411.60758 | AB29: =$P$10*AA29 -> 41.160758 | AC29: =IF(P29>0,SUM(V29:V40),"-") -> - | AD29: =IF(P29>0,SUM(W29:W40),"-") -> - | AF29: =IF('[29]Proforma-Input'!$C$108="Yes",MONTH(O29)&YEAR(O29)=MONTH($C$9)&YEAR($C$9),0) -> 0 | AG29: 2
B30: =IFERROR(DATE(YEAR(B29),MONTH(B29)+1,DAY(B29)),"-") -> - | D30: 15 | E30: =1+E29 -> 3 | F30: =IFERROR(IF(B30<$C$9,IF('[29]Proforma-Input'!$C$108="Yes",K29,K29),0),) -> 0 | G30: =IFERROR(IF(D30=$C$7,K29,IF(AND($D$10="Yes",D30<=$C$10),I30,IF(F30>0,$C$8,))),) -> 0 | H30: =IFERROR(IF(B30<$C$9,IF('[29]Proforma-Input'!$C$108="Yes",H29,),0),) -> 0 | I30: =(H30/12)*F30 -> 0 | J30: =IF(D30=$C$7,0,G30-I30) -> 0 | K30: =IFERROR(F30-J30,) -> 0 | L30: =IF(C30>0,SUM(I30:I41),"-") -> - | M30: =IF(C30>0,SUM(J30:J41),"-") -> - | O30: =IFERROR(DATE(YEAR(O29),MONTH(O29)+1,DAY(O29)),"-") -> 46359 | Q30: =IF(S30>0,1+Q29,) -> 15 | R30: =1+R29 -> 3 | S30: =IF('[29]Proforma-Input'!$C$108="No",X29,IF(AF30=TRUE,$P$3,X29)) -> 4934442 | T30: =IF(AND($N$8="Yes",Q30<=$P$8),V30,IF(S30>0,$P$7,)) -> 31603.401 | U30: =$P$4 -> 0.065 | V30: =IF(S30>0,U30/12*S30,0) -> 26728.228 | W30: =T30-V30 -> 4875.1735 | X30: =S30-W30 -> 4929566.9 | Y30: =IF(Q30=1,V30,Y29+V30) -> 403617.88 | Z30: =IF(Q30=1,W30,Z29+W30) -> 70433.141 | AA30: =$P$9*S30/12 -> 411.2035 | AB30: =$P$10*AA30 -> 41.12035 | AC30: =IF(P30>0,SUM(V30:V41),"-") -> - | AD30: =IF(P30>0,SUM(W30:W41),"-") -> - | AF30: =IF('[29]Proforma-Input'!$C$108="Yes",MONTH(O30)&YEAR(O30)=MONTH($C$9)&YEAR($C$9),0) -> 0 | AG30: 2
B31: =IFERROR(DATE(YEAR(B30),MONTH(B30)+1,DAY(B30)),"-") -> - | D31: 16 | E31: =1+E30 -> 4 | F31: =IFERROR(IF(B31<$C$9,IF('[29]Proforma-Input'!$C$108="Yes",K30,K30),0),) -> 0 | G31: =IFERROR(IF(D31=$C$7,K30,IF(AND($D$10="Yes",D31<=$C$10),I31,IF(F31>0,$C$8,))),) -> 0 | H31: =IFERROR(IF(B31<$C$9,IF('[29]Proforma-Input'!$C$108="Yes",H30,),0),) -> 0 | I31: =(H31/12)*F31 -> 0 | J31: =IF(D31=$C$7,0,G31-I31) -> 0 | K31: =IFERROR(F31-J31,) -> 0 | L31: =IF(C31>0,SUM(I31:I42),"-") -> - | M31: =IF(C31>0,SUM(J31:J42),"-") -> - | O31: =IFERROR(DATE(YEAR(O30),MONTH(O30)+1,DAY(O30)),"-") -> 46390 | Q31: =IF(S31>0,1+Q30,) -> 16 | R31: =1+R30 -> 4 | S31: =IF('[29]Proforma-Input'!$C$108="No",X30,IF(AF31=TRUE,$P$3,X30)) -> 4929566.9 | T31: =IF(AND($N$8="Yes",Q31<=$P$8),V31,IF(S31>0,$P$7,)) -> 31603.401 | U31: =$P$4 -> 0.065 | V31: =IF(S31>0,U31/12*S31,0) -> 26701.82 | W31: =T31-V31 -> 4901.5807 | X31: =S31-W31 -> 4924665.3 | Y31: =IF(Q31=1,V31,Y30+V31) -> 430319.7 | Z31: =IF(Q31=1,W31,Z30+W31) -> 75334.721 | AA31: =$P$9*S31/12 -> 410.79724 | AB31: =$P$10*AA31 -> 41.079724 | AC31: =IF(P31>0,SUM(V31:V42),"-") -> - | AD31: =IF(P31>0,SUM(W31:W42),"-") -> - | AF31: =IF('[29]Proforma-Input'!$C$108="Yes",MONTH(O31)&YEAR(O31)=MONTH($C$9)&YEAR($C$9),0) -> 0 | AG31: 2
B32: =IFERROR(DATE(YEAR(B31),MONTH(B31)+1,DAY(B31)),"-") -> - | D32: 17 | E32: =1+E31 -> 5 | F32: =IFERROR(IF(B32<$C$9,IF('[29]Proforma-Input'!$C$108="Yes",K31,K31),0),) -> 0 | G32: =IFERROR(IF(D32=$C$7,K31,IF(AND($D$10="Yes",D32<=$C$10),I32,IF(F32>0,$C$8,))),) -> 0 | H32: =IFERROR(IF(B32<$C$9,IF('[29]Proforma-Input'!$C$108="Yes",H31,),0),) -> 0 | I32: =(H32/12)*F32 -> 0 | J32: =IF(D32=$C$7,0,G32-I32) -> 0 | K32: =IFERROR(F32-J32,) -> 0 | L32: =IF(C32>0,SUM(I32:I43),"-") -> - | M32: =IF(C32>0,SUM(J32:J43),"-") -> - | O32: =IFERROR(DATE(YEAR(O31),MONTH(O31)+1,DAY(O31)),"-") -> 46421 | Q32: =IF(S32>0,1+Q31,) -> 17 | R32: =1+R31 -> 5 | S32: =IF('[29]Proforma-Input'!$C$108="No",X31,IF(AF32=TRUE,$P$3,X31)) -> 4924665.3 | T32: =IF(AND($N$8="Yes",Q32<=$P$8),V32,IF(S32>0,$P$7,)) -> 31603.401 | U32: =$P$4 -> 0.065 | V32: =IF(S32>0,U32/12*S32,0) -> 26675.27 | W32: =T32-V32 -> 4928.1309 | X32: =S32-W32 -> 4919737.1 | Y32: =IF(Q32=1,V32,Y31+V32) -> 456994.97 | Z32: =IF(Q32=1,W32,Z31+W32) -> 80262.852 | AA32: =$P$9*S32/12 -> 410.38877 | AB32: =$P$10*AA32 -> 41.038877 | AC32: =IF(P32>0,SUM(V32:V43),"-") -> - | AD32: =IF(P32>0,SUM(W32:W43),"-") -> - | AF32: =IF('[29]Proforma-Input'!$C$108="Yes",MONTH(O32)&YEAR(O32)=MONTH($C$9)&YEAR($C$9),0) -> 0 | AG32: 2
B33: =IFERROR(DATE(YEAR(B32),MONTH(B32)+1,DAY(B32)),"-") -> - | D33: 18 | E33: =1+E32 -> 6 | F33: =IFERROR(IF(B33<$C$9,IF('[29]Proforma-Input'!$C$108="Yes",K32,K32),0),) -> 0 | G33: =IFERROR(IF(D33=$C$7,K32,IF(AND($D$10="Yes",D33<=$C$10),I33,IF(F33>0,$C$8,))),) -> 0 | H33: =IFERROR(IF(B33<$C$9,IF('[29]Proforma-Input'!$C$108="Yes",H32,),0),) -> 0 | I33: =(H33/12)*F33 -> 0 | J33: =IF(D33=$C$7,0,G33-I33) -> 0 | K33: =IFERROR(F33-J33,) -> 0 | L33: =IF(C33>0,SUM(I33:I44),"-") -> - | M33: =IF(C33>0,SUM(J33:J44),"-") -> - | O33: =IFERROR(DATE(YEAR(O32),MONTH(O32)+1,DAY(O32)),"-") -> 46449 | Q33: =IF(S33>0,1+Q32,) -> 18 | R33: =1+R32 -> 6 | S33: =IF('[29]Proforma-Input'!$C$108="No",X32,IF(AF33=TRUE,$P$3,X32)) -> 4919737.1 | T33: =IF(AND($N$8="Yes",Q33<=$P$8),V33,IF(S33>0,$P$7,)) -> 31603.401 | U33: =$P$4 -> 0.065 | V33: =IF(S33>0,U33/12*S33,0) -> 26648.576 | W33: =T33-V33 -> 4954.825 | X33: =S33-W33 -> 4914782.3 | Y33: =IF(Q33=1,V33,Y32+V33) -> 483643.54 | Z33: =IF(Q33=1,W33,Z32+W33) -> 85217.677 | AA33: =$P$9*S33/12 -> 409.9781 | AB33: =$P$10*AA33 -> 40.99781 | AC33: =IF(P33>0,SUM(V33:V44),"-") -> - | AD33: =IF(P33>0,SUM(W33:W44),"-") -> - | AF33: =IF('[29]Proforma-Input'!$C$108="Yes",MONTH(O33)&YEAR(O33)=MONTH($C$9)&YEAR($C$9),0) -> 0 | AG33: 2
B34: =IFERROR(DATE(YEAR(B33),MONTH(B33)+1,DAY(B33)),"-") -> - | D34: 19 | E34: =1+E33 -> 7 | F34: =IFERROR(IF(B34<$C$9,IF('[29]Proforma-Input'!$C$108="Yes",K33,K33),0),) -> 0 | G34: =IFERROR(IF(D34=$C$7,K33,IF(AND($D$10="Yes",D34<=$C$10),I34,IF(F34>0,$C$8,))),) -> 0 | H34: =IFERROR(IF(B34<$C$9,IF('[29]Proforma-Input'!$C$108="Yes",H33,),0),) -> 0 | I34: =(H34/12)*F34 -> 0 | J34: =IF(D34=$C$7,0,G34-I34) -> 0 | K34: =IFERROR(F34-J34,) -> 0 | L34: =IF(C34>0,SUM(I34:I45),"-") -> - | M34: =IF(C34>0,SUM(J34:J45),"-") -> - | O34: =IFERROR(DATE(YEAR(O33),MONTH(O33)+1,DAY(O33)),"-") -> 46480 | Q34: =IF(S34>0,1+Q33,) -> 19 | R34: =1+R33 -> 7 | S34: =IF('[29]Proforma-Input'!$C$108="No",X33,IF(AF34=TRUE,$P$3,X33)) -> 4914782.3 | T34: =IF(AND($N$8="Yes",Q34<=$P$8),V34,IF(S34>0,$P$7,)) -> 31603.401 | U34: =$P$4 -> 0.065 | V34: =IF(S34>0,U34/12*S34,0) -> 26621.738 | W34: =T34-V34 -> 4981.6636 | X34: =S34-W34 -> 4909800.7 | Y34: =IF(Q34=1,V34,Y33+V34) -> 510265.28 | Z34: =IF(Q34=1,W34,Z33+W34) -> 90199.341 | AA34: =$P$9*S34/12 -> 409.56519 | AB34: =$P$10*AA34 -> 40.956519 | AC34: =IF(P34>0,SUM(V34:V45),"-") -> - | AD34: =IF(P34>0,SUM(W34:W45),"-") -> - | AF34: =IF('[29]Proforma-Input'!$C$108="Yes",MONTH(O34)&YEAR(O34)=MONTH($C$9)&YEAR($C$9),0) -> 0 | AG34: 2
B35: =IFERROR(DATE(YEAR(B34),MONTH(B34)+1,DAY(B34)),"-") -> - | D35: 20 | E35: =1+E34 -> 8 | F35: =IFERROR(IF(B35<$C$9,IF('[29]Proforma-Input'!$C$108="Yes",K34,K34),0),) -> 0 | G35: =IFERROR(IF(D35=$C$7,K34,IF(AND($D$10="Yes",D35<=$C$10),I35,IF(F35>0,$C$8,))),) -> 0 | H35: =IFERROR(IF(B35<$C$9,IF('[29]Proforma-Input'!$C$108="Yes",H34,),0),) -> 0 | I35: =(H35/12)*F35 -> 0 | J35: =IF(D35=$C$7,0,G35-I35) -> 0 | K35: =IFERROR(F35-J35,) -> 0 | L35: =IF(C35>0,SUM(I35:I46),"-") -> - | M35: =IF(C35>0,SUM(J35:J46),"-") -> - | O35: =IFERROR(DATE(YEAR(O34),MONTH(O34)+1,DAY(O34)),"-") -> 46510 | Q35: =IF(S35>0,1+Q34,) -> 20 | R35: =1+R34 -> 8 | S35: =IF('[29]Proforma-Input'!$C$108="No",X34,IF(AF35=TRUE,$P$3,X34)) -> 4909800.7 | T35: =IF(AND($N$8="Yes",Q35<=$P$8),V35,IF(S35>0,$P$7,)) -> 31603.401 | U35: =$P$4 -> 0.065 | V35: =IF(S35>0,U35/12*S35,0) -> 26594.754 | W35: =T35-V35 -> 5008.6476 | X35: =S35-W35 -> 4904792 | Y35: =IF(Q35=1,V35,Y34+V35) -> 536860.04 | Z35: =IF(Q35=1,W35,Z34+W35) -> 95207.988 | AA35: =$P$9*S35/12 -> 409.15005 | AB35: =$P$10*AA35 -> 40.915005 | AC35: =IF(P35>0,SUM(V35:V46),"-") -> - | AD35: =IF(P35>0,SUM(W35:W46),"-") -> - | AF35: =IF('[29]Proforma-Input'!$C$108="Yes",MONTH(O35)&YEAR(O35)=MONTH($C$9)&YEAR($C$9),0) -> 0 | AG35: 2
B36: =IFERROR(DATE(YEAR(B35),MONTH(B35)+1,DAY(B35)),"-") -> - | D36: 21 | E36: =1+E35 -> 9 | F36: =IFERROR(IF(B36<$C$9,IF('[29]Proforma-Input'!$C$108="Yes",K35,K35),0),) -> 0 | G36: =IFERROR(IF(D36=$C$7,K35,IF(AND($D$10="Yes",D36<=$C$10),I36,IF(F36>0,$C$8,))),) -> 0 | H36: =IFERROR(IF(B36<$C$9,IF('[29]Proforma-Input'!$C$108="Yes",H35,),0),) -> 0 | I36: =(H36/12)*F36 -> 0 | J36: =IF(D36=$C$7,0,G36-I36) -> 0 | K36: =IFERROR(F36-J36,) -> 0 | L36: =IF(C36>0,SUM(I36:I47),"-") -> - | M36: =IF(C36>0,SUM(J36:J47),"-") -> - | O36: =IFERROR(DATE(YEAR(O35),MONTH(O35)+1,DAY(O35)),"-") -> 46541 | Q36: =IF(S36>0,1+Q35,) -> 21 | R36: =1+R35 -> 9 | S36: =IF('[29]Proforma-Input'!$C$108="No",X35,IF(AF36=TRUE,$P$3,X35)) -> 4904792 | T36: =IF(AND($N$8="Yes",Q36<=$P$8),V36,IF(S36>0,$P$7,)) -> 31603.401 | U36: =$P$4 -> 0.065 | V36: =IF(S36>0,U36/12*S36,0) -> 26567.623 | W36: =T36-V36 -> 5035.7778 | X36: =S36-W36 -> 4899756.2 | Y36: =IF(Q36=1,V36,Y35+V36) -> 563427.66 | Z36: =IF(Q36=1,W36,Z35+W36) -> 100243.77 | AA36: =$P$9*S36/12 -> 408.73267 | AB36: =$P$10*AA36 -> 40.873267 | AC36: =IF(P36>0,SUM(V36:V47),"-") -> - | AD36: =IF(P36>0,SUM(W36:W47),"-") -> - | AF36: =IF('[29]Proforma-Input'!$C$108="Yes",MONTH(O36)&YEAR(O36)=MONTH($C$9)&YEAR($C$9),0) -> 0 | AG36: 2
B37: =IFERROR(DATE(YEAR(B36),MONTH(B36)+1,DAY(B36)),"-") -> - | D37: 22 | E37: =1+E36 -> 10 | F37: =IFERROR(IF(B37<$C$9,IF('[29]Proforma-Input'!$C$108="Yes",K36,K36),0),) -> 0 | G37: =IFERROR(IF(D37=$C$7,K36,IF(AND($D$10="Yes",D37<=$C$10),I37,IF(F37>0,$C$8,))),) -> 0 | H37: =IFERROR(IF(B37<$C$9,IF('[29]Proforma-Input'!$C$108="Yes",H36,),0),) -> 0 | I37: =(H37/12)*F37 -> 0 | J37: =IF(D37=$C$7,0,G37-I37) -> 0 | K37: =IFERROR(F37-J37,) -> 0 | L37: =IF(C37>0,SUM(I37:I48),"-") -> - | M37: =IF(C37>0,SUM(J37:J48),"-") -> - | O37: =IFERROR(DATE(YEAR(O36),MONTH(O36)+1,DAY(O36)),"-") -> 46571 | Q37: =IF(S37>0,1+Q36,) -> 22 | R37: =1+R36 -> 10 | S37: =IF('[29]Proforma-Input'!$C$108="No",X36,IF(AF37=TRUE,$P$3,X36)) -> 4899756.2 | T37: =IF(AND($N$8="Yes",Q37<=$P$8),V37,IF(S37>0,$P$7,)) -> 31603.401 | U37: =$P$4 -> 0.065 | V37: =IF(S37>0,U37/12*S37,0) -> 26540.346 | W37: =T37-V37 -> 5063.0549 | X37: =S37-W37 -> 4894693.2 | Y37: =IF(Q37=1,V37,Y36+V37) -> 589968 | Z37: =IF(Q37=1,W37,Z36+W37) -> 105306.82 | AA37: =$P$9*S37/12 -> 408.31302 | AB37: =$P$10*AA37 -> 40.831302 | AC37: =IF(P37>0,SUM(V37:V48),"-") -> - | AD37: =IF(P37>0,SUM(W37:W48),"-") -> - | AF37: =IF('[29]Proforma-Input'!$C$108="Yes",MONTH(O37)&YEAR(O37)=MONTH($C$9)&YEAR($C$9),0) -> 0 | AG37: 2
B38: =IFERROR(DATE(YEAR(B37),MONTH(B37)+1,DAY(B37)),"-") -> - | D38: 23 | E38: =1+E37 -> 11 | F38: =IFERROR(IF(B38<$C$9,IF('[29]Proforma-Input'!$C$108="Yes",K37,K37),0),) -> 0 | G38: =IFERROR(IF(D38=$C$7,K37,IF(AND($D$10="Yes",D38<=$C$10),I38,IF(F38>0,$C$8,))),) -> 0 | H38: =IFERROR(IF(B38<$C$9,IF('[29]Proforma-Input'!$C$108="Yes",H37,),0),) -> 0 | I38: =(H38/12)*F38 -> 0 | J38: =IF(D38=$C$7,0,G38-I38) -> 0 | K38: =IFERROR(F38-J38,) -> 0 | L38: =IF(C38>0,SUM(I38:I49),"-") -> - | M38: =IF(C38>0,SUM(J38:J49),"-") -> - | O38: =IFERROR(DATE(YEAR(O37),MONTH(O37)+1,DAY(O37)),"-") -> 46602 | Q38: =IF(S38>0,1+Q37,) -> 23 | R38: =1+R37 -> 11 | S38: =IF('[29]Proforma-Input'!$C$108="No",X37,IF(AF38=TRUE,$P$3,X37)) -> 4894693.2 | T38: =IF(AND($N$8="Yes",Q38<=$P$8),V38,IF(S38>0,$P$7,)) -> 31603.401 | U38: =$P$4 -> 0.065 | V38: =IF(S38>0,U38/12*S38,0) -> 26512.921 | W38: =T38-V38 -> 5090.4798 | X38: =S38-W38 -> 4889602.7 | Y38: =IF(Q38=1,V38,Y37+V38) -> 616480.93 | Z38: =IF(Q38=1,W38,Z37+W38) -> 110397.3 | AA38: =$P$9*S38/12 -> 407.8911 | AB38: =$P$10*AA38 -> 40.78911 | AC38: =IF(P38>0,SUM(V38:V49),"-") -> - | AD38: =IF(P38>0,SUM(W38:W49),"-") -> - | AF38: =IF('[29]Proforma-Input'!$C$108="Yes",MONTH(O38)&YEAR(O38)=MONTH($C$9)&YEAR($C$9),0) -> 0 | AG38: 2
B39: =IFERROR(DATE(YEAR(B38),MONTH(B38)+1,DAY(B38)),"-") -> - | D39: 24 | E39: =1+E38 -> 12 | F39: =IFERROR(IF(B39<$C$9,IF('[29]Proforma-Input'!$C$108="Yes",K38,K38),0),) -> 0 | G39: =IFERROR(IF(D39=$C$7,K38,IF(AND($D$10="Yes",D39<=$C$10),I39,IF(F39>0,$C$8,))),) -> 0 | H39: =IFERROR(IF(B39<$C$9,IF('[29]Proforma-Input'!$C$108="Yes",H38,),0),) -> 0 | I39: =(H39/12)*F39 -> 0 | J39: =IF(D39=$C$7,0,G39-I39) -> 0 | K39: =IFERROR(F39-J39,) -> 0 | L39: =IF(C39>0,SUM(I39:I50),"-") -> - | M39: =IF(C39>0,SUM(J39:J50),"-") -> - | O39: =IFERROR(DATE(YEAR(O38),MONTH(O38)+1,DAY(O38)),"-") -> 46633 | Q39: =IF(S39>0,1+Q38,) -> 24 | R39: =1+R38 -> 12 | S39: =IF('[29]Proforma-Input'!$C$108="No",X38,IF(AF39=TRUE,$P$3,X38)) -> 4889602.7 | T39: =IF(AND($N$8="Yes",Q39<=$P$8),V39,IF(S39>0,$P$7,)) -> 31603.401 | U39: =$P$4 -> 0.065 | V39: =IF(S39>0,U39/12*S39,0) -> 26485.348 | W39: =T39-V39 -> 5118.0532 | X39: =S39-W39 -> 4884484.6 | Y39: =IF(Q39=1,V39,Y38+V39) -> 642966.27 | Z39: =IF(Q39=1,W39,Z38+W39) -> 115515.35 | AA39: =$P$9*S39/12 -> 407.46689 | AB39: =$P$10*AA39 -> 40.746689 | AC39: =IF(P39>0,SUM(V39:V50),"-") -> - | AD39: =IF(P39>0,SUM(W39:W50),"-") -> - | AF39: =IF('[29]Proforma-Input'!$C$108="Yes",MONTH(O39)&YEAR(O39)=MONTH($C$9)&YEAR($C$9),0) -> 0 | AG39: 2
B40: =IFERROR(DATE(YEAR(B39),MONTH(B39)+1,DAY(B39)),"-") -> - | C40: 3 | D40: 25 | E40: 1 | F40: =IFERROR(IF(B40<$C$9,IF('[29]Proforma-Input'!$C$108="Yes",K39,K39),0),) -> 0 | G40: =IFERROR(IF(D40=$C$7,K39,IF(AND($D$10="Yes",D40<=$C$10),I40,IF(F40>0,$C$8,))),) -> 0 | H40: =IFERROR(IF(B40<$C$9,IF('[29]Proforma-Input'!$C$108="Yes",H39,),0),) -> 0 | I40: =(H40/12)*F40 -> 0 | J40: =IF(D40=$C$7,0,G40-I40) -> 0 | K40: =IFERROR(F40-J40,) -> 0 | L40: =IF(C40>0,SUM(I40:I51),"-") -> 0 | M40: =IF(C40>0,SUM(J40:J51),"-") -> 0 | O40: =IFERROR(DATE(YEAR(O39),MONTH(O39)+1,DAY(O39)),"-") -> 46663 | P40: 3 | Q40: =IF(S40>0,1+Q39,) -> 25 | R40: 1 | S40: =IF('[29]Proforma-Input'!$C$108="No",X39,IF(AF40=TRUE,$P$3,X39)) -> 4884484.6 | T40: =IF(AND($N$8="Yes",Q40<=$P$8),V40,IF(S40>0,$P$7,)) -> 31603.401 | U40: =$P$4 -> 0.065 | V40: =IF(S40>0,U40/12*S40,0) -> 26457.625 | W40: =T40-V40 -> 5145.776 | X40: =S40-W40 -> 4879338.9 | Y40: =IF(Q40=1,V40,Y39+V40) -> 669423.9 | Z40: =IF(Q40=1,W40,Z39+W40) -> 120661.13 | AA40: =$P$9*S40/12 -> 407.04039 | AB40: =$P$10*AA40 -> 40.704039 | AC40: =IF(P40>0,SUM(V40:V51),"-") -> 315618.26 | AD40: =IF(P40>0,SUM(W40:W51),"-") -> 63622.551 | AF40: =IF('[29]Proforma-Input'!$C$108="Yes",MONTH(O40)&YEAR(O40)=MONTH($C$9)&YEAR($C$9),0) -> 0 | AG40: 3
B41: =IFERROR(DATE(YEAR(B40),MONTH(B40)+1,DAY(B40)),"-") -> - | D41: 26 | E41: =1+E40 -> 2 | F41: =IFERROR(IF(B41<$C$9,IF('[29]Proforma-Input'!$C$108="Yes",K40,K40),0),) -> 0 | G41: =IFERROR(IF(D41=$C$7,K40,IF(AND($D$10="Yes",D41<=$C$10),I41,IF(F41>0,$C$8,))),) -> 0 | H41: =IFERROR(IF(B41<$C$9,IF('[29]Proforma-Input'!$C$108="Yes",H40,),0),) -> 0 | I41: =(H41/12)*F41 -> 0 | J41: =IF(D41=$C$7,0,G41-I41) -> 0 | K41: =IFERROR(F41-J41,) -> 0 | L41: =IF(C41>0,SUM(I41:I52),"-") -> - | M41: =IF(C41>0,SUM(J41:J52),"-") -> - | O41: =IFERROR(DATE(YEAR(O40),MONTH(O40)+1,DAY(O40)),"-") -> 46694 | Q41: =IF(S41>0,1+Q40,) -> 26 | R41: =1+R40 -> 2 | S41: =IF('[29]Proforma-Input'!$C$108="No",X40,IF(AF41=TRUE,$P$3,X40)) -> 4879338.9 | T41: =IF(AND($N$8="Yes",Q41<=$P$8),V41,IF(S41>0,$P$7,)) -> 31603.401 | U41: =$P$4 -> 0.065 | V41: =IF(S41>0,U41/12*S41,0) -> 26429.752 | W41: =T41-V41 -> 5173.649 | X41: =S41-W41 -> 4874165.2 | Y41: =IF(Q41=1,V41,Y40+V41) -> 695853.65 | Z41: =IF(Q41=1,W41,Z40+W41) -> 125834.78 | AA41: =$P$9*S41/12 -> 406.61157 | AB41: =$P$10*AA41 -> 40.661157 | AC41: =IF(P41>0,SUM(V41:V52),"-") -> - | AD41: =IF(P41>0,SUM(W41:W52),"-") -> - | AF41: =IF('[29]Proforma-Input'!$C$108="Yes",MONTH(O41)&YEAR(O41)=MONTH($C$9)&YEAR($C$9),0) -> 0 | AG41: 3
B42: =IFERROR(DATE(YEAR(B41),MONTH(B41)+1,DAY(B41)),"-") -> - | D42: 27 | E42: =1+E41 -> 3 | F42: =IFERROR(IF(B42<$C$9,IF('[29]Proforma-Input'!$C$108="Yes",K41,K41),0),) -> 0 | G42: =IFERROR(IF(D42=$C$7,K41,IF(AND($D$10="Yes",D42<=$C$10),I42,IF(F42>0,$C$8,))),) -> 0 | H42: =IFERROR(IF(B42<$C$9,IF('[29]Proforma-Input'!$C$108="Yes",H41,),0),) -> 0 | I42: =(H42/12)*F42 -> 0 | J42: =IF(D42=$C$7,0,G42-I42) -> 0 | K42: =IFERROR(F42-J42,) -> 0 | L42: =IF(C42>0,SUM(I42:I53),"-") -> - | M42: =IF(C42>0,SUM(J42:J53),"-") -> - | O42: =IFERROR(DATE(YEAR(O41),MONTH(O41)+1,DAY(O41)),"-") -> 46724 | Q42: =IF(S42>0,1+Q41,) -> 27 | R42: =1+R41 -> 3 | S42: =IF('[29]Proforma-Input'!$C$108="No",X41,IF(AF42=TRUE,$P$3,X41)) -> 4874165.2 | T42: =IF(AND($N$8="Yes",Q42<=$P$8),V42,IF(S42>0,$P$7,)) -> 31603.401 | U42: =$P$4 -> 0.065 | V42: =IF(S42>0,U42/12*S42,0) -> 26401.728 | W42: =T42-V42 -> 5201.6729 | X42: =S42-W42 -> 4868963.5 | Y42: =IF(Q42=1,V42,Y41+V42) -> 722255.38 | Z42: =IF(Q42=1,W42,Z41+W42) -> 131036.45 | AA42: =$P$9*S42/12 -> 406.18044 | AB42: =$P$10*AA42 -> 40.618044 | AC42: =IF(P42>0,SUM(V42:V53),"-") -> - | AD42: =IF(P42>0,SUM(W42:W53),"-") -> - | AF42: =IF('[29]Proforma-Input'!$C$108="Yes",MONTH(O42)&YEAR(O42)=MONTH($C$9)&YEAR($C$9),0) -> 0 | AG42: 3
B43: =IFERROR(DATE(YEAR(B42),MONTH(B42)+1,DAY(B42)),"-") -> - | D43: 28 | E43: =1+E42 -> 4 | F43: =IFERROR(IF(B43<$C$9,IF('[29]Proforma-Input'!$C$108="Yes",K42,K42),0),) -> 0 | G43: =IFERROR(IF(D43=$C$7,K42,IF(AND($D$10="Yes",D43<=$C$10),I43,IF(F43>0,$C$8,))),) -> 0 | H43: =IFERROR(IF(B43<$C$9,IF('[29]Proforma-Input'!$C$108="Yes",H42,),0),) -> 0 | I43: =(H43/12)*F43 -> 0 | J43: =IF(D43=$C$7,0,G43-I43) -> 0 | K43: =IFERROR(F43-J43,) -> 0 | L43: =IF(C43>0,SUM(I43:I54),"-") -> - | M43: =IF(C43>0,SUM(J43:J54),"-") -> - | O43: =IFERROR(DATE(YEAR(O42),MONTH(O42)+1,DAY(O42)),"-") -> 46755 | Q43: =IF(S43>0,1+Q42,) -> 28 | R43: =1+R42 -> 4 | S43: =IF('[29]Proforma-Input'!$C$108="No",X42,IF(AF43=TRUE,$P$3,X42)) -> 4868963.5 | T43: =IF(AND($N$8="Yes",Q43<=$P$8),V43,IF(S43>0,$P$7,)) -> 31603.401 | U43: =$P$4 -> 0.065 | V43: =IF(S43>0,U43/12*S43,0) -> 26373.553 | W43: =T43-V43 -> 5229.8486 | X43: =S43-W43 -> 4863733.7 | Y43: =IF(Q43=1,V43,Y42+V43) -> 748628.93 | Z43: =IF(Q43=1,W43,Z42+W43) -> 136266.3 | AA43: =$P$9*S43/12 -> 405.74696 | AB43: =$P$10*AA43 -> 40.574696 | AC43: =IF(P43>0,SUM(V43:V54),"-") -> - | AD43: =IF(P43>0,SUM(W43:W54),"-") -> - | AF43: =IF('[29]Proforma-Input'!$C$108="Yes",MONTH(O43)&YEAR(O43)=MONTH($C$9)&YEAR($C$9),0) -> 0 | AG43: 3
B44: =IFERROR(DATE(YEAR(B43),MONTH(B43)+1,DAY(B43)),"-") -> - | D44: 29 | E44: =1+E43 -> 5 | F44: =IFERROR(IF(B44<$C$9,IF('[29]Proforma-Input'!$C$108="Yes",K43,K43),0),) -> 0 | G44: =IFERROR(IF(D44=$C$7,K43,IF(AND($D$10="Yes",D44<=$C$10),I44,IF(F44>0,$C$8,))),) -> 0 | H44: =IFERROR(IF(B44<$C$9,IF('[29]Proforma-Input'!$C$108="Yes",H43,),0),) -> 0 | I44: =(H44/12)*F44 -> 0 | J44: =IF(D44=$C$7,0,G44-I44) -> 0 | K44: =IFERROR(F44-J44,) -> 0 | L44: =IF(C44>0,SUM(I44:I55),"-") -> - | M44: =IF(C44>0,SUM(J44:J55),"-") -> - | O44: =IFERROR(DATE(YEAR(O43),MONTH(O43)+1,DAY(O43)),"-") -> 46786 | Q44: =IF(S44>0,1+Q43,) -> 29 | R44: =1+R43 -> 5 | S44: =IF('[29]Proforma-Input'!$C$108="No",X43,IF(AF44=TRUE,$P$3,X43)) -> 4863733.7 | T44: =IF(AND($N$8="Yes",Q44<=$P$8),V44,IF(S44>0,$P$7,)) -> 31603.401 | U44: =$P$4 -> 0.065 | V44: =IF(S44>0,U44/12*S44,0) -> 26345.224 | W44: =T44-V44 -> 5258.177 | X44: =S44-W44 -> 4858475.5 | Y44: =IF(Q44=1,V44,Y43+V44) -> 774974.16 | Z44: =IF(Q44=1,W44,Z43+W44) -> 141524.48 | AA44: =$P$9*S44/12 -> 405.31114 | AB44: =$P$10*AA44 -> 40.531114 | AC44: =IF(P44>0,SUM(V44:V55),"-") -> - | AD44: =IF(P44>0,SUM(W44:W55),"-") -> - | AF44: =IF('[29]Proforma-Input'!$C$108="Yes",MONTH(O44)&YEAR(O44)=MONTH($C$9)&YEAR($C$9),0) -> 0 | AG44: 3
B45: =IFERROR(DATE(YEAR(B44),MONTH(B44)+1,DAY(B44)),"-") -> - | D45: 30 | E45: =1+E44 -> 6 | F45: =IFERROR(IF(B45<$C$9,IF('[29]Proforma-Input'!$C$108="Yes",K44,K44),0),) -> 0 | G45: =IFERROR(IF(D45=$C$7,K44,IF(AND($D$10="Yes",D45<=$C$10),I45,IF(F45>0,$C$8,))),) -> 0 | H45: =IFERROR(IF(B45<$C$9,IF('[29]Proforma-Input'!$C$108="Yes",H44,),0),) -> 0 | I45: =(H45/12)*F45 -> 0 | J45: =IF(D45=$C$7,0,G45-I45) -> 0 | K45: =IFERROR(F45-J45,) -> 0 | L45: =IF(C45>0,SUM(I45:I56),"-") -> - | M45: =IF(C45>0,SUM(J45:J56),"-") -> - | O45: =IFERROR(DATE(YEAR(O44),MONTH(O44)+1,DAY(O44)),"-") -> 46815 | Q45: =IF(S45>0,1+Q44,) -> 30 | R45: =1+R44 -> 6 | S45: =IF('[29]Proforma-Input'!$C$108="No",X44,IF(AF45=TRUE,$P$3,X44)) -> 4858475.5 | T45: =IF(AND($N$8="Yes",Q45<=$P$8),V45,IF(S45>0,$P$7,)) -> 31603.401 | U45: =$P$4 -> 0.065 | V45: =IF(S45>0,U45/12*S45,0) -> 26316.742 | W45: =T45-V45 -> 5286.6588 | X45: =S45-W45 -> 4853188.9 | Y45: =IF(Q45=1,V45,Y44+V45) -> 801290.9 | Z45: =IF(Q45=1,W45,Z44+W45) -> 146811.14 | AA45: =$P$9*S45/12 -> 404.87296 | AB45: =$P$10*AA45 -> 40.487296 | AC45: =IF(P45>0,SUM(V45:V56),"-") -> - | AD45: =IF(P45>0,SUM(W45:W56),"-") -> - | AF45: =IF('[29]Proforma-Input'!$C$108="Yes",MONTH(O45)&YEAR(O45)=MONTH($C$9)&YEAR($C$9),0) -> 0 | AG45: 3
B46: =IFERROR(DATE(YEAR(B45),MONTH(B45)+1,DAY(B45)),"-") -> - | D46: 31 | E46: =1+E45 -> 7 | F46: =IFERROR(IF(B46<$C$9,IF('[29]Proforma-Input'!$C$108="Yes",K45,K45),0),) -> 0 | G46: =IFERROR(IF(D46=$C$7,K45,IF(AND($D$10="Yes",D46<=$C$10),I46,IF(F46>0,$C$8,))),) -> 0 | H46: =IFERROR(IF(B46<$C$9,IF('[29]Proforma-Input'!$C$108="Yes",H45,),0),) -> 0 | I46: =(H46/12)*F46 -> 0 | J46: =IF(D46=$C$7,0,G46-I46) -> 0 | K46: =IFERROR(F46-J46,) -> 0 | L46: =IF(C46>0,SUM(I46:I57),"-") -> - | M46: =IF(C46>0,SUM(J46:J57),"-") -> - | O46: =IFERROR(DATE(YEAR(O45),MONTH(O45)+1,DAY(O45)),"-") -> 46846 | Q46: =IF(S46>0,1+Q45,) -> 31 | R46: =1+R45 -> 7 | S46: =IF('[29]Proforma-Input'!$C$108="No",X45,IF(AF46=TRUE,$P$3,X45)) -> 4853188.9 | T46: =IF(AND($N$8="Yes",Q46<=$P$8),V46,IF(S46>0,$P$7,)) -> 31603.401 | U46: =$P$4 -> 0.065 | V46: =IF(S46>0,U46/12*S46,0) -> 26288.106 | W46: =T46-V46 -> 5315.2948 | X46: =S46-W46 -> 4847873.6 | Y46: =IF(Q46=1,V46,Y45+V46) -> 827579.01 | Z46: =IF(Q46=1,W46,Z45+W46) -> 152126.43 | AA46: =$P$9*S46/12 -> 404.43241 | AB46: =$P$10*AA46 -> 40.443241 | AC46: =IF(P46>0,SUM(V46:V57),"-") -> - | AD46: =IF(P46>0,SUM(W46:W57),"-") -> - | AF46: =IF('[29]Proforma-Input'!$C$108="Yes",MONTH(O46)&YEAR(O46)=MONTH($C$9)&YEAR($C$9),0) -> 0 | AG46: 3
B47: =IFERROR(DATE(YEAR(B46),MONTH(B46)+1,DAY(B46)),"-") -> - | D47: 32 | E47: =1+E46 -> 8 | F47: =IFERROR(IF(B47<$C$9,IF('[29]Proforma-Input'!$C$108="Yes",K46,K46),0),) -> 0 | G47: =IFERROR(IF(D47=$C$7,K46,IF(AND($D$10="Yes",D47<=$C$10),I47,IF(F47>0,$C$8,))),) -> 0 | H47: =IFERROR(IF(B47<$C$9,IF('[29]Proforma-Input'!$C$108="Yes",H46,),0),) -> 0 | I47: =(H47/12)*F47 -> 0 | J47: =IF(D47=$C$7,0,G47-I47) -> 0 | K47: =IFERROR(F47-J47,) -> 0 | L47: =IF(C47>0,SUM(I47:I58),"-") -> - | M47: =IF(C47>0,SUM(J47:J58),"-") -> - | O47: =IFERROR(DATE(YEAR(O46),MONTH(O46)+1,DAY(O46)),"-") -> 46876 | Q47: =IF(S47>0,1+Q46,) -> 32 | R47: =1+R46 -> 8 | S47: =IF('[29]Proforma-Input'!$C$108="No",X46,IF(AF47=TRUE,$P$3,X46)) -> 4847873.6 | T47: =IF(AND($N$8="Yes",Q47<=$P$8),V47,IF(S47>0,$P$7,)) -> 31603.401 | U47: =$P$4 -> 0.065 | V47: =IF(S47>0,U47/12*S47,0) -> 26259.315 | W47: =T47-V47 -> 5344.086 | X47: =S47-W47 -> 4842529.5 | Y47: =IF(Q47=1,V47,Y46+V47) -> 853838.32 | Z47: =IF(Q47=1,W47,Z46+W47) -> 157470.52 | AA47: =$P$9*S47/12 -> 403.98946 | AB47: =$P$10*AA47 -> 40.398946 | AC47: =IF(P47>0,SUM(V47:V58),"-") -> - | AD47: =IF(P47>0,SUM(W47:W58),"-") -> - | AF47: =IF('[29]Proforma-Input'!$C$108="Yes",MONTH(O47)&YEAR(O47)=MONTH($C$9)&YEAR($C$9),0) -> 0 | AG47: 3
B48: =IFERROR(DATE(YEAR(B47),MONTH(B47)+1,DAY(B47)),"-") -> - | D48: 33 | E48: =1+E47 -> 9 | F48: =IFERROR(IF(B48<$C$9,IF('[29]Proforma-Input'!$C$108="Yes",K47,K47),0),) -> 0 | G48: =IFERROR(IF(D48=$C$7,K47,IF(AND($D$10="Yes",D48<=$C$10),I48,IF(F48>0,$C$8,))),) -> 0 | H48: =IFERROR(IF(B48<$C$9,IF('[29]Proforma-Input'!$C$108="Yes",H47,),0),) -> 0 | I48: =(H48/12)*F48 -> 0 | J48: =IF(D48=$C$7,0,G48-I48) -> 0 | K48: =IFERROR(F48-J48,) -> 0 | L48: =IF(C48>0,SUM(I48:I59),"-") -> - | M48: =IF(C48>0,SUM(J48:J59),"-") -> - | O48: =IFERROR(DATE(YEAR(O47),MONTH(O47)+1,DAY(O47)),"-") -> 46907 | Q48: =IF(S48>0,1+Q47,) -> 33 | R48: =1+R47 -> 9 | S48: =IF('[29]Proforma-Input'!$C$108="No",X47,IF(AF48=TRUE,$P$3,X47)) -> 4842529.5 | T48: =IF(AND($N$8="Yes",Q48<=$P$8),V48,IF(S48>0,$P$7,)) -> 31603.401 | U48: =$P$4 -> 0.065 | V48: =IF(S48>0,U48/12*S48,0) -> 26230.368 | W48: =T48-V48 -> 5373.0331 | X48: =S48-W48 -> 4837156.4 | Y48: =IF(Q48=1,V48,Y47+V48) -> 880068.69 | Z48: =IF(Q48=1,W48,Z47+W48) -> 162843.55 | AA48: =$P$9*S48/12 -> 403.54412 | AB48: =$P$10*AA48 -> 40.354412 | AC48: =IF(P48>0,SUM(V48:V59),"-") -> - | AD48: =IF(P48>0,SUM(W48:W59),"-") -> - | AF48: =IF('[29]Proforma-Input'!$C$108="Yes",MONTH(O48)&YEAR(O48)=MONTH($C$9)&YEAR($C$9),0) -> 0 | AG48: 3
B49: =IFERROR(DATE(YEAR(B48),MONTH(B48)+1,DAY(B48)),"-") -> - | D49: 34 | E49: =1+E48 -> 10 | F49: =IFERROR(IF(B49<$C$9,IF('[29]Proforma-Input'!$C$108="Yes",K48,K48),0),) -> 0 | G49: =IFERROR(IF(D49=$C$7,K48,IF(AND($D$10="Yes",D49<=$C$10),I49,IF(F49>0,$C$8,))),) -> 0 | H49: =IFERROR(IF(B49<$C$9,IF('[29]Proforma-Input'!$C$108="Yes",H48,),0),) -> 0 | I49: =(H49/12)*F49 -> 0 | J49: =IF(D49=$C$7,0,G49-I49) -> 0 | K49: =IFERROR(F49-J49,) -> 0 | L49: =IF(C49>0,SUM(I49:I60),"-") -> - | M49: =IF(C49>0,SUM(J49:J60),"-") -> - | O49: =IFERROR(DATE(YEAR(O48),MONTH(O48)+1,DAY(O48)),"-") -> 46937 | Q49: =IF(S49>0,1+Q48,) -> 34 | R49: =1+R48 -> 10 | S49: =IF('[29]Proforma-Input'!$C$108="No",X48,IF(AF49=TRUE,$P$3,X48)) -> 4837156.4 | T49: =IF(AND($N$8="Yes",Q49<=$P$8),V49,IF(S49>0,$P$7,)) -> 31603.401 | U49: =$P$4 -> 0.065 | V49: =IF(S49>0,U49/12*S49,0) -> 26201.264 | W49: =T49-V49 -> 5402.1371 | X49: =S49-W49 -> 4831754.3 | Y49: =IF(Q49=1,V49,Y48+V49) -> 906269.95 | Z49: =IF(Q49=1,W49,Z48+W49) -> 168245.69 | AA49: =$P$9*S49/12 -> 403.09637 | AB49: =$P$10*AA49 -> 40.309637 | AC49: =IF(P49>0,SUM(V49:V60),"-") -> - | AD49: =IF(P49>0,SUM(W49:W60),"-") -> - | AF49: =IF('[29]Proforma-Input'!$C$108="Yes",MONTH(O49)&YEAR(O49)=MONTH($C$9)&YEAR($C$9),0) -> 0 | AG49: 3
B50: =IFERROR(DATE(YEAR(B49),MONTH(B49)+1,DAY(B49)),"-") -> - | D50: 35 | E50: =1+E49 -> 11 | F50: =IFERROR(IF(B50<$C$9,IF('[29]Proforma-Input'!$C$108="Yes",K49,K49),0),) -> 0 | G50: =IFERROR(IF(D50=$C$7,K49,IF(AND($D$10="Yes",D50<=$C$10),I50,IF(F50>0,$C$8,))),) -> 0 | H50: =IFERROR(IF(B50<$C$9,IF('[29]Proforma-Input'!$C$108="Yes",H49,),0),) -> 0 | I50: =(H50/12)*F50 -> 0 | J50: =IF(D50=$C$7,0,G50-I50) -> 0 | K50: =IFERROR(F50-J50,) -> 0 | L50: =IF(C50>0,SUM(I50:I61),"-") -> - | M50: =IF(C50>0,SUM(J50:J61),"-") -> - | O50: =IFERROR(DATE(YEAR(O49),MONTH(O49)+1,DAY(O49)),"-") -> 46968 | Q50: =IF(S50>0,1+Q49,) -> 35 | R50: =1+R49 -> 11 | S50: =IF('[29]Proforma-Input'!$C$108="No",X49,IF(AF50=TRUE,$P$3,X49)) -> 4831754.3 | T50: =IF(AND($N$8="Yes",Q50<=$P$8),V50,IF(S50>0,$P$7,)) -> 31603.401 | U50: =$P$4 -> 0.065 | V50: =IF(S50>0,U50/12*S50,0) -> 26172.003 | W50: =T50-V50 -> 5431.3986 | X50: =S50-W50 -> 4826322.9 | Y50: =IF(Q50=1,V50,Y49+V50) -> 932441.96 | Z50: =IF(Q50=1,W50,Z49+W50) -> 173677.09 | AA50: =$P$9*S50/12 -> 402.64619 | AB50: =$P$10*AA50 -> 40.264619 | AC50: =IF(P50>0,SUM(V50:V61),"-") -> - | AD50: =IF(P50>0,SUM(W50:W61),"-") -> - | AF50: =IF('[29]Proforma-Input'!$C$108="Yes",MONTH(O50)&YEAR(O50)=MONTH($C$9)&YEAR($C$9),0) -> 0 | AG50: 3
B51: =IFERROR(DATE(YEAR(B50),MONTH(B50)+1,DAY(B50)),"-") -> - | D51: 36 | E51: =1+E50 -> 12 | F51: =IFERROR(IF(B51<$C$9,IF('[29]Proforma-Input'!$C$108="Yes",K50,K50),0),) -> 0 | G51: =IFERROR(IF(D51=$C$7,K50,IF(AND($D$10="Yes",D51<=$C$10),I51,IF(F51>0,$C$8,))),) -> 0 | H51: =IFERROR(IF(B51<$C$9,IF('[29]Proforma-Input'!$C$108="Yes",H50,),0),) -> 0 | I51: =(H51/12)*F51 -> 0 | J51: =IF(D51=$C$7,0,G51-I51) -> 0 | K51: =IFERROR(F51-J51,) -> 0 | L51: =IF(C51>0,SUM(I51:I62),"-") -> - | M51: =IF(C51>0,SUM(J51:J62),"-") -> - | O51: =IFERROR(DATE(YEAR(O50),MONTH(O50)+1,DAY(O50)),"-") -> 46999 | Q51: =IF(S51>0,1+Q50,) -> 36 | R51: =1+R50 -> 12 | S51: =IF('[29]Proforma-Input'!$C$108="No",X50,IF(AF51=TRUE,$P$3,X50)) -> 4826322.9 | T51: =IF(AND($N$8="Yes",Q51<=$P$8),V51,IF(S51>0,$P$7,)) -> 31603.401 | U51: =$P$4 -> 0.065 | V51: =IF(S51>0,U51/12*S51,0) -> 26142.582 | W51: =T51-V51 -> 5460.8187 | X51: =S51-W51 -> 4820862.1 | Y51: =IF(Q51=1,V51,Y50+V51) -> 958584.54 | Z51: =IF(Q51=1,W51,Z50+W51) -> 179137.9 | AA51: =$P$9*S51/12 -> 402.19358 | AB51: =$P$10*AA51 -> 40.219358 | AC51: =IF(P51>0,SUM(V51:V62),"-") -> - | AD51: =IF(P51>0,SUM(W51:W62),"-") -> - | AF51: =IF('[29]Proforma-Input'!$C$108="Yes",MONTH(O51)&YEAR(O51)=MONTH($C$9)&YEAR($C$9),0) -> 0 | AG51: 3
B52: =IFERROR(DATE(YEAR(B51),MONTH(B51)+1,DAY(B51)),"-") -> - | C52: 4 | D52: 37 | E52: 1 | F52: =IFERROR(IF(B52<$C$9,IF('[29]Proforma-Input'!$C$108="Yes",K51,K51),0),) -> 0 | G52: =IFERROR(IF(D52=$C$7,K51,IF(AND($D$10="Yes",D52<=$C$10),I52,IF(F52>0,$C$8,))),) -> 0 | H52: =IFERROR(IF(B52<$C$9,IF('[29]Proforma-Input'!$C$108="Yes",H51,),0),) -> 0 | I52: =(H52/12)*F52 -> 0 | J52: =IF(D52=$C$7,0,G52-I52) -> 0 | K52: =IFERROR(F52-J52,) -> 0 | L52: =IF(C52>0,SUM(I52:I63),"-") -> 0 | M52: =IF(C52>0,SUM(J52:J63),"-") -> 0 | O52: =IFERROR(DATE(YEAR(O51),MONTH(O51)+1,DAY(O51)),"-") -> 47029 | P52: 4 | Q52: =IF(S52>0,1+Q51,) -> 37 | R52: 1 | S52: =IF('[29]Proforma-Input'!$C$108="No",X51,IF(AF52=TRUE,$P$3,X51)) -> 4820862.1 | T52: =IF(AND($N$8="Yes",Q52<=$P$8),V52,IF(S52>0,$P$7,)) -> 31603.401 | U52: =$P$4 -> 0.065 | V52: =IF(S52>0,U52/12*S52,0) -> 26113.003 | W52: =T52-V52 -> 5490.3982 | X52: =S52-W52 -> 4815371.7 | Y52: =IF(Q52=1,V52,Y51+V52) -> 984697.54 | Z52: =IF(Q52=1,W52,Z51+W52) -> 184628.3 | AA52: =$P$9*S52/12 -> 401.73851 | AB52: =$P$10*AA52 -> 40.173851 | AC52: =IF(P52>0,SUM(V52:V63),"-") -> 311357.34 | AD52: =IF(P52>0,SUM(W52:W63),"-") -> 67883.471 | AF52: =IF('[29]Proforma-Input'!$C$108="Yes",MONTH(O52)&YEAR(O52)=MONTH($C$9)&YEAR($C$9),0) -> 0 | AG52: 4
B53: =IFERROR(DATE(YEAR(B52),MONTH(B52)+1,DAY(B52)),"-") -> - | D53: 38 | E53: =1+E52 -> 2 | F53: =IFERROR(IF(B53<$C$9,IF('[29]Proforma-Input'!$C$108="Yes",K52,K52),0),) -> 0 | G53: =IFERROR(IF(D53=$C$7,K52,IF(AND($D$10="Yes",D53<=$C$10),I53,IF(F53>0,$C$8,))),) -> 0 | H53: =IFERROR(IF(B53<$C$9,IF('[29]Proforma-Input'!$C$108="Yes",H52,),0),) -> 0 | I53: =(H53/12)*F53 -> 0 | J53: =IF(D53=$C$7,0,G53-I53) -> 0 | K53: =IFERROR(F53-J53,) -> 0 | L53: =IF(C53>0,SUM(I53:I64),"-") -> - | M53: =IF(C53>0,SUM(J53:J64),"-") -> - | O53: =IFERROR(DATE(YEAR(O52),MONTH(O52)+1,DAY(O52)),"-") -> 47060 | Q53: =IF(S53>0,1+Q52,) -> 38 | R53: =1+R52 -> 2 | S53: =IF('[29]Proforma-Input'!$C$108="No",X52,IF(AF53=TRUE,$P$3,X52)) -> 4815371.7 | T53: =IF(AND($N$8="Yes",Q53<=$P$8),V53,IF(S53>0,$P$7,)) -> 31603.401 | U53: =$P$4 -> 0.065 | V53: =IF(S53>0,U53/12*S53,0) -> 26083.263 | W53: =T53-V53 -> 5520.1378 | X53: =S53-W53 -> 4809851.6 | Y53: =IF(Q53=1,V53,Y52+V53) -> 1010780.8 | Z53: =IF(Q53=1,W53,Z52+W53) -> 190148.44 | AA53: =$P$9*S53/12 -> 401.28097 | AB53: =$P$10*AA53 -> 40.128097 | AC53: =IF(P53>0,SUM(V53:V64),"-") -> - | AD53: =IF(P53>0,SUM(W53:W64),"-") -> - | AF53: =IF('[29]Proforma-Input'!$C$108="Yes",MONTH(O53)&YEAR(O53)=MONTH($C$9)&YEAR($C$9),0) -> 0 | AG53: 4
B54: =IFERROR(DATE(YEAR(B53),MONTH(B53)+1,DAY(B53)),"-") -> - | D54: 39 | E54: =1+E53 -> 3 | F54: =IFERROR(IF(B54<$C$9,IF('[29]Proforma-Input'!$C$108="Yes",K53,K53),0),) -> 0 | G54: =IFERROR(IF(D54=$C$7,K53,IF(AND($D$10="Yes",D54<=$C$10),I54,IF(F54>0,$C$8,))),) -> 0 | H54: =IFERROR(IF(B54<$C$9,IF('[29]Proforma-Input'!$C$108="Yes",H53,),0),) -> 0 | I54: =(H54/12)*F54 -> 0 | J54: =IF(D54=$C$7,0,G54-I54) -> 0 | K54: =IFERROR(F54-J54,) -> 0 | L54: =IF(C54>0,SUM(I54:I65),"-") -> - | M54: =IF(C54>0,SUM(J54:J65),"-") -> - | O54: =IFERROR(DATE(YEAR(O53),MONTH(O53)+1,DAY(O53)),"-") -> 47090 | Q54: =IF(S54>0,1+Q53,) -> 39 | R54: =1+R53 -> 3 | S54: =IF('[29]Proforma-Input'!$C$108="No",X53,IF(AF54=TRUE,$P$3,X53)) -> 4809851.6 | T54: =IF(AND($N$8="Yes",Q54<=$P$8),V54,IF(S54>0,$P$7,)) -> 31603.401 | U54: =$P$4 -> 0.065 | V54: =IF(S54>0,U54/12*S54,0) -> 26053.363 | W54: =T54-V54 -> 5550.0386 | X54: =S54-W54 -> 4804301.5 | Y54: =IF(Q54=1,V54,Y53+V54) -> 1036834.2 | Z54: =IF(Q54=1,W54,Z53+W54) -> 195698.48 | AA54: =$P$9*S54/12 -> 400.82096 | AB54: =$P$10*AA54 -> 40.082096 | AC54: =IF(P54>0,SUM(V54:V65),"-") -> - | AD54: =IF(P54>0,SUM(W54:W65),"-") -> - | AF54: =IF('[29]Proforma-Input'!$C$108="Yes",MONTH(O54)&YEAR(O54)=MONTH($C$9)&YEAR($C$9),0) -> 0 | AG54: 4
B55: =IFERROR(DATE(YEAR(B54),MONTH(B54)+1,DAY(B54)),"-") -> - | D55: 40 | E55: =1+E54 -> 4 | F55: =IFERROR(IF(B55<$C$9,IF('[29]Proforma-Input'!$C$108="Yes",K54,K54),0),) -> 0 | G55: =IFERROR(IF(D55=$C$7,K54,IF(AND($D$10="Yes",D55<=$C$10),I55,IF(F55>0,$C$8,))),) -> 0 | H55: =IFERROR(IF(B55<$C$9,IF('[29]Proforma-Input'!$C$108="Yes",H54,),0),) -> 0 | I55: =(H55/12)*F55 -> 0 | J55: =IF(D55=$C$7,0,G55-I55) -> 0 | K55: =IFERROR(F55-J55,) -> 0 | L55: =IF(C55>0,SUM(I55:I66),"-") -> - | M55: =IF(C55>0,SUM(J55:J66),"-") -> - | O55: =IFERROR(DATE(YEAR(O54),MONTH(O54)+1,DAY(O54)),"-") -> 47121 | Q55: =IF(S55>0,1+Q54,) -> 40 | R55: =1+R54 -> 4 | S55: =IF('[29]Proforma-Input'!$C$108="No",X54,IF(AF55=TRUE,$P$3,X54)) -> 4804301.5 | T55: =IF(AND($N$8="Yes",Q55<=$P$8),V55,IF(S55>0,$P$7,)) -> 31603.401 | U55: =$P$4 -> 0.065 | V55: =IF(S55>0,U55/12*S55,0) -> 26023.3 | W55: =T55-V55 -> 5580.1013 | X55: =S55-W55 -> 4798721.4 | Y55: =IF(Q55=1,V55,Y54+V55) -> 1062857.5 | Z55: =IF(Q55=1,W55,Z54+W55) -> 201278.58 | AA55: =$P$9*S55/12 -> 400.35846 | AB55: =$P$10*AA55 -> 40.035846 | AC55: =IF(P55>0,SUM(V55:V66),"-") -> - | AD55: =IF(P55>0,SUM(W55:W66),"-") -> - | AF55: =IF('[29]Proforma-Input'!$C$108="Yes",MONTH(O55)&YEAR(O55)=MONTH($C$9)&YEAR($C$9),0) -> 0 | AG55: 4
B56: =IFERROR(DATE(YEAR(B55),MONTH(B55)+1,DAY(B55)),"-") -> - | D56: 41 | E56: =1+E55 -> 5 | F56: =IFERROR(IF(B56<$C$9,IF('[29]Proforma-Input'!$C$108="Yes",K55,K55),0),) -> 0 | G56: =IFERROR(IF(D56=$C$7,K55,IF(AND($D$10="Yes",D56<=$C$10),I56,IF(F56>0,$C$8,))),) -> 0 | H56: =IFERROR(IF(B56<$C$9,IF('[29]Proforma-Input'!$C$108="Yes",H55,),0),) -> 0 | I56: =(H56/12)*F56 -> 0 | J56: =IF(D56=$C$7,0,G56-I56) -> 0 | K56: =IFERROR(F56-J56,) -> 0 | L56: =IF(C56>0,SUM(I56:I67),"-") -> - | M56: =IF(C56>0,SUM(J56:J67),"-") -> - | O56: =IFERROR(DATE(YEAR(O55),MONTH(O55)+1,DAY(O55)),"-") -> 47152 | Q56: =IF(S56>0,1+Q55,) -> 41 | R56: =1+R55 -> 5 | S56: =IF('[29]Proforma-Input'!$C$108="No",X55,IF(AF56=TRUE,$P$3,X55)) -> 4798721.4 | T56: =IF(AND($N$8="Yes",Q56<=$P$8),V56,IF(S56>0,$P$7,)) -> 31603.401 | U56: =$P$4 -> 0.065 | V56: =IF(S56>0,U56/12*S56,0) -> 25993.074 | W56: =T56-V56 -> 5610.3268 | X56: =S56-W56 -> 4793111.1 | Y56: =IF(Q56=1,V56,Y55+V56) -> 1088850.5 | Z56: =IF(Q56=1,W56,Z55+W56) -> 206888.91 | AA56: =$P$9*S56/12 -> 399.89345 | AB56: =$P$10*AA56 -> 39.989345 | AC56: =IF(P56>0,SUM(V56:V67),"-") -> - | AD56: =IF(P56>0,SUM(W56:W67),"-") -> - | AF56: =IF('[29]Proforma-Input'!$C$108="Yes",MONTH(O56)&YEAR(O56)=MONTH($C$9)&YEAR($C$9),0) -> 0 | AG56: 4
B57: =IFERROR(DATE(YEAR(B56),MONTH(B56)+1,DAY(B56)),"-") -> - | D57: 42 | E57: =1+E56 -> 6 | F57: =IFERROR(IF(B57<$C$9,IF('[29]Proforma-Input'!$C$108="Yes",K56,K56),0),) -> 0 | G57: =IFERROR(IF(D57=$C$7,K56,IF(AND($D$10="Yes",D57<=$C$10),I57,IF(F57>0,$C$8,))),) -> 0 | H57: =IFERROR(IF(B57<$C$9,IF('[29]Proforma-Input'!$C$108="Yes",H56,),0),) -> 0 | I57: =(H57/12)*F57 -> 0 | J57: =IF(D57=$C$7,0,G57-I57) -> 0 | K57: =IFERROR(F57-J57,) -> 0 | L57: =IF(C57>0,SUM(I57:I68),"-") -> - | M57: =IF(C57>0,SUM(J57:J68),"-") -> - | O57: =IFERROR(DATE(YEAR(O56),MONTH(O56)+1,DAY(O56)),"-") -> 47180 | Q57: =IF(S57>0,1+Q56,) -> 42 | R57: =1+R56 -> 6 | S57: =IF('[29]Proforma-Input'!$C$108="No",X56,IF(AF57=TRUE,$P$3,X56)) -> 4793111.1 | T57: =IF(AND($N$8="Yes",Q57<=$P$8),V57,IF(S57>0,$P$7,)) -> 31603.401 | U57: =$P$4 -> 0.065 | V57: =IF(S57>0,U57/12*S57,0) -> 25962.685 | W57: =T57-V57 -> 5640.7161 | X57: =S57-W57 -> 4787470.4 | Y57: =IF(Q57=1,V57,Y56+V57) -> 1114813.2 | Z57: =IF(Q57=1,W57,Z56+W57) -> 212529.62 | AA57: =$P$9*S57/12 -> 399.42592 | AB57: =$P$10*AA57 -> 39.942592 | AC57: =IF(P57>0,SUM(V57:V68),"-") -> - | AD57: =IF(P57>0,SUM(W57:W68),"-") -> - | AF57: =IF('[29]Proforma-Input'!$C$108="Yes",MONTH(O57)&YEAR(O57)=MONTH($C$9)&YEAR($C$9),0) -> 0 | AG57: 4
B58: =IFERROR(DATE(YEAR(B57),MONTH(B57)+1,DAY(B57)),"-") -> - | D58: 43 | E58: =1+E57 -> 7 | F58: =IFERROR(IF(B58<$C$9,IF('[29]Proforma-Input'!$C$108="Yes",K57,K57),0),) -> 0 | G58: =IFERROR(IF(D58=$C$7,K57,IF(AND($D$10="Yes",D58<=$C$10),I58,IF(F58>0,$C$8,))),) -> 0 | H58: =IFERROR(IF(B58<$C$9,IF('[29]Proforma-Input'!$C$108="Yes",H57,),0),) -> 0 | I58: =(H58/12)*F58 -> 0 | J58: =IF(D58=$C$7,0,G58-I58) -> 0 | K58: =IFERROR(F58-J58,) -> 0 | L58: =IF(C58>0,SUM(I58:I69),"-") -> - | M58: =IF(C58>0,SUM(J58:J69),"-") -> - | O58: =IFERROR(DATE(YEAR(O57),MONTH(O57)+1,DAY(O57)),"-") -> 47211 | Q58: =IF(S58>0,1+Q57,) -> 43 | R58: =1+R57 -> 7 | S58: =IF('[29]Proforma-Input'!$C$108="No",X57,IF(AF58=TRUE,$P$3,X57)) -> 4787470.4 | T58: =IF(AND($N$8="Yes",Q58<=$P$8),V58,IF(S58>0,$P$7,)) -> 31603.401 | U58: =$P$4 -> 0.065 | V58: =IF(S58>0,U58/12*S58,0) -> 25932.131 | W58: =T58-V58 -> 5671.27 | X58: =S58-W58 -> 4781799.1 | Y58: =IF(Q58=1,V58,Y57+V58) -> 1140745.4 | Z58: =IF(Q58=1,W58,Z57+W58) -> 218200.89 | AA58: =$P$9*S58/12 -> 398.95586 | AB58: =$P$10*AA58 -> 39.895586 | AC58: =IF(P58>0,SUM(V58:V69),"-") -> - | AD58: =IF(P58>0,SUM(W58:W69),"-") -> - | AF58: =IF('[29]Proforma-Input'!$C$108="Yes",MONTH(O58)&YEAR(O58)=MONTH($C$9)&YEAR($C$9),0) -> 0 | AG58: 4
B59: =IFERROR(DATE(YEAR(B58),MONTH(B58)+1,DAY(B58)),"-") -> - | D59: 44 | E59: =1+E58 -> 8 | F59: =IFERROR(IF(B59<$C$9,IF('[29]Proforma-Input'!$C$108="Yes",K58,K58),0),) -> 0 | G59: =IFERROR(IF(D59=$C$7,K58,IF(AND($D$10="Yes",D59<=$C$10),I59,IF(F59>0,$C$8,))),) -> 0 | H59: =IFERROR(IF(B59<$C$9,IF('[29]Proforma-Input'!$C$108="Yes",H58,),0),) -> 0 | I59: =(H59/12)*F59 -> 0 | J59: =IF(D59=$C$7,0,G59-I59) -> 0 | K59: =IFERROR(F59-J59,) -> 0 | L59: =IF(C59>0,SUM(I59:I70),"-") -> - | M59: =IF(C59>0,SUM(J59:J70),"-") -> - | O59: =IFERROR(DATE(YEAR(O58),MONTH(O58)+1,DAY(O58)),"-") -> 47241 | Q59: =IF(S59>0,1+Q58,) -> 44 | R59: =1+R58 -> 8 | S59: =IF('[29]Proforma-Input'!$C$108="No",X58,IF(AF59=TRUE,$P$3,X58)) -> 4781799.1 | T59: =IF(AND($N$8="Yes",Q59<=$P$8),V59,IF(S59>0,$P$7,)) -> 31603.401 | U59: =$P$4 -> 0.065 | V59: =IF(S59>0,U59/12*S59,0) -> 25901.412 | W59: =T59-V59 -> 5701.9893 | X59: =S59-W59 -> 4776097.1 | Y59: =IF(Q59=1,V59,Y58+V59) -> 1166646.8 | Z59: =IF(Q59=1,W59,Z58+W59) -> 223902.88 | AA59: =$P$9*S59/12 -> 398.48326 | AB59: =$P$10*AA59 -> 39.848326 | AC59: =IF(P59>0,SUM(V59:V70),"-") -> - | AD59: =IF(P59>0,SUM(W59:W70),"-") -> - | AF59: =IF('[29]Proforma-Input'!$C$108="Yes",MONTH(O59)&YEAR(O59)=MONTH($C$9)&YEAR($C$9),0) -> 0 | AG59: 4
B60: =IFERROR(DATE(YEAR(B59),MONTH(B59)+1,DAY(B59)),"-") -> - | D60: 45 | E60: =1+E59 -> 9 | F60: =IFERROR(IF(B60<$C$9,IF('[29]Proforma-Input'!$C$108="Yes",K59,K59),0),) -> 0 | G60: =IFERROR(IF(D60=$C$7,K59,IF(AND($D$10="Yes",D60<=$C$10),I60,IF(F60>0,$C$8,))),) -> 0 | H60: =IFERROR(IF(B60<$C$9,IF('[29]Proforma-Input'!$C$108="Yes",H59,),0),) -> 0 | I60: =(H60/12)*F60 -> 0 | J60: =IF(D60=$C$7,0,G60-I60) -> 0 | K60: =IFERROR(F60-J60,) -> 0 | L60: =IF(C60>0,SUM(I60:I71),"-") -> - | M60: =IF(C60>0,SUM(J60:J71),"-") -> - | O60: =IFERROR(DATE(YEAR(O59),MONTH(O59)+1,DAY(O59)),"-") -> 47272 | Q60: =IF(S60>0,1+Q59,) -> 45 | R60: =1+R59 -> 9 | S60: =IF('[29]Proforma-Input'!$C$108="No",X59,IF(AF60=TRUE,$P$3,X59)) -> 4776097.1 | T60: =IF(AND($N$8="Yes",Q60<=$P$8),V60,IF(S60>0,$P$7,)) -> 31603.401 | U60: =$P$4 -> 0.065 | V60: =IF(S60>0,U60/12*S60,0) -> 25870.526 | W60: =T60-V60 -> 5732.8751 | X60: =S60-W60 -> 4770364.2 | Y60: =IF(Q60=1,V60,Y59+V60) -> 1192517.3 | Z60: =IF(Q60=1,W60,Z59+W60) -> 229635.76 | AA60: =$P$9*S60/12 -> 398.00809 | AB60: =$P$10*AA60 -> 39.800809 | AC60: =IF(P60>0,SUM(V60:V71),"-") -> - | AD60: =IF(P60>0,SUM(W60:W71),"-") -> - | AF60: =IF('[29]Proforma-Input'!$C$108="Yes",MONTH(O60)&YEAR(O60)=MONTH($C$9)&YEAR($C$9),0) -> 0 | AG60: 4
B61: =IFERROR(DATE(YEAR(B60),MONTH(B60)+1,DAY(B60)),"-") -> - | D61: 46 | E61: =1+E60 -> 10 | F61: =IFERROR(IF(B61<$C$9,IF('[29]Proforma-Input'!$C$108="Yes",K60,K60),0),) -> 0 | G61: =IFERROR(IF(D61=$C$7,K60,IF(AND($D$10="Yes",D61<=$C$10),I61,IF(F61>0,$C$8,))),) -> 0 | H61: =IFERROR(IF(B61<$C$9,IF('[29]Proforma-Input'!$C$108="Yes",H60,),0),) -> 0 | I61: =(H61/12)*F61 -> 0 | J61: =IF(D61=$C$7,0,G61-I61) -> 0 | K61: =IFERROR(F61-J61,) -> 0 | L61: =IF(C61>0,SUM(I61:I72),"-") -> - | M61: =IF(C61>0,SUM(J61:J72),"-") -> - | O61: =IFERROR(DATE(YEAR(O60),MONTH(O60)+1,DAY(O60)),"-") -> 47302 | Q61: =IF(S61>0,1+Q60,) -> 46 | R61: =1+R60 -> 10 | S61: =IF('[29]Proforma-Input'!$C$108="No",X60,IF(AF61=TRUE,$P$3,X60)) -> 4770364.2 | T61: =IF(AND($N$8="Yes",Q61<=$P$8),V61,IF(S61>0,$P$7,)) -> 31603.401 | U61: =$P$4 -> 0.065 | V61: =IF(S61>0,U61/12*S61,0) -> 25839.473 | W61: =T61-V61 -> 5763.9282 | X61: =S61-W61 -> 4764600.3 | Y61: =IF(Q61=1,V61,Y60+V61) -> 1218356.8 | Z61: =IF(Q61=1,W61,Z60+W61) -> 235399.69 | AA61: =$P$9*S61/12 -> 397.53035 | AB61: =$P$10*AA61 -> 39.753035 | AC61: =IF(P61>0,SUM(V61:V72),"-") -> - | AD61: =IF(P61>0,SUM(W61:W72),"-") -> - | AF61: =IF('[29]Proforma-Input'!$C$108="Yes",MONTH(O61)&YEAR(O61)=MONTH($C$9)&YEAR($C$9),0) -> 0 | AG61: 4
B62: =IFERROR(DATE(YEAR(B61),MONTH(B61)+1,DAY(B61)),"-") -> - | D62: 47 | E62: =1+E61 -> 11 | F62: =IFERROR(IF(B62<$C$9,IF('[29]Proforma-Input'!$C$108="Yes",K61,K61),0),) -> 0 | G62: =IFERROR(IF(D62=$C$7,K61,IF(AND($D$10="Yes",D62<=$C$10),I62,IF(F62>0,$C$8,))),) -> 0 | H62: =IFERROR(IF(B62<$C$9,IF('[29]Proforma-Input'!$C$108="Yes",H61,),0),) -> 0 | I62: =(H62/12)*F62 -> 0 | J62: =IF(D62=$C$7,0,G62-I62) -> 0 | K62: =IFERROR(F62-J62,) -> 0 | L62: =IF(C62>0,SUM(I62:I73),"-") -> - | M62: =IF(C62>0,SUM(J62:J73),"-") -> - | O62: =IFERROR(DATE(YEAR(O61),MONTH(O61)+1,DAY(O61)),"-") -> 47333 | Q62: =IF(S62>0,1+Q61,) -> 47 | R62: =1+R61 -> 11 | S62: =IF('[29]Proforma-Input'!$C$108="No",X61,IF(AF62=TRUE,$P$3,X61)) -> 4764600.3 | T62: =IF(AND($N$8="Yes",Q62<=$P$8),V62,IF(S62>0,$P$7,)) -> 31603.401 | U62: =$P$4 -> 0.065 | V62: =IF(S62>0,U62/12*S62,0) -> 25808.252 | W62: =T62-V62 -> 5795.1495 | X62: =S62-W62 -> 4758805.2 | Y62: =IF(Q62=1,V62,Y61+V62) -> 1244165 | Z62: =IF(Q62=1,W62,Z61+W62) -> 241194.84 | AA62: =$P$9*S62/12 -> 397.05003 | AB62: =$P$10*AA62 -> 39.705003 | AC62: =IF(P62>0,SUM(V62:V73),"-") -> - | AD62: =IF(P62>0,SUM(W62:W73),"-") -> - | AF62: =IF('[29]Proforma-Input'!$C$108="Yes",MONTH(O62)&YEAR(O62)=MONTH($C$9)&YEAR($C$9),0) -> 0 | AG62: 4
B63: =IFERROR(DATE(YEAR(B62),MONTH(B62)+1,DAY(B62)),"-") -> - | D63: 48 | E63: =1+E62 -> 12 | F63: =IFERROR(IF(B63<$C$9,IF('[29]Proforma-Input'!$C$108="Yes",K62,K62),0),) -> 0 | G63: =IFERROR(IF(D63=$C$7,K62,IF(AND($D$10="Yes",D63<=$C$10),I63,IF(F63>0,$C$8,))),) -> 0 | H63: =IFERROR(IF(B63<$C$9,IF('[29]Proforma-Input'!$C$108="Yes",H62,),0),) -> 0 | I63: =(H63/12)*F63 -> 0 | J63: =IF(D63=$C$7,0,G63-I63) -> 0 | K63: =IFERROR(F63-J63,) -> 0 | L63: =IF(C63>0,SUM(I63:I74),"-") -> - | M63: =IF(C63>0,SUM(J63:J74),"-") -> - | O63: =IFERROR(DATE(YEAR(O62),MONTH(O62)+1,DAY(O62)),"-") -> 47364 | Q63: =IF(S63>0,1+Q62,) -> 48 | R63: =1+R62 -> 12 | S63: =IF('[29]Proforma-Input'!$C$108="No",X62,IF(AF63=TRUE,$P$3,X62)) -> 4758805.2 | T63: =IF(AND($N$8="Yes",Q63<=$P$8),V63,IF(S63>0,$P$7,)) -> 31603.401 | U63: =$P$4 -> 0.065 | V63: =IF(S63>0,U63/12*S63,0) -> 25776.861 | W63: =T63-V63 -> 5826.5399 | X63: =S63-W63 -> 4752978.6 | Y63: =IF(Q63=1,V63,Y62+V63) -> 1269941.9 | Z63: =IF(Q63=1,W63,Z62+W63) -> 247021.38 | AA63: =$P$9*S63/12 -> 396.5671 | AB63: =$P$10*AA63 -> 39.65671 | AC63: =IF(P63>0,SUM(V63:V74),"-") -> - | AD63: =IF(P63>0,SUM(W63:W74),"-") -> - | AF63: =IF('[29]Proforma-Input'!$C$108="Yes",MONTH(O63)&YEAR(O63)=MONTH($C$9)&YEAR($C$9),0) -> 0 | AG63: 4
B64: =IFERROR(DATE(YEAR(B63),MONTH(B63)+1,DAY(B63)),"-") -> - | C64: 5 | D64: 49 | E64: 1 | F64: =IFERROR(IF(B64<$C$9,IF('[29]Proforma-Input'!$C$108="Yes",K63,K63),0),) -> 0 | G64: =IFERROR(IF(D64=$C$7,K63,IF(AND($D$10="Yes",D64<=$C$10),I64,IF(F64>0,$C$8,))),) -> 0 | H64: =IFERROR(IF(B64<$C$9,IF('[29]Proforma-Input'!$C$108="Yes",H63,),0),) -> 0 | I64: =(H64/12)*F64 -> 0 | J64: =IF(D64=$C$7,0,G64-I64) -> 0 | K64: =IFERROR(F64-J64,) -> 0 | L64: =IF(C64>0,SUM(I64:I75),"-") -> 0 | M64: =IF(C64>0,SUM(J64:J75),"-") -> 0 | O64: =IFERROR(DATE(YEAR(O63),MONTH(O63)+1,DAY(O63)),"-") -> 47394 | P64: 5 | Q64: =IF(S64>0,1+Q63,) -> 49 | R64: 1 | S64: =IF('[29]Proforma-Input'!$C$108="No",X63,IF(AF64=TRUE,$P$3,X63)) -> 4752978.6 | T64: =IF(AND($N$8="Yes",Q64<=$P$8),V64,IF(S64>0,$P$7,)) -> 31603.401 | U64: =$P$4 -> 0.065 | V64: =IF(S64>0,U64/12*S64,0) -> 25745.301 | W64: =T64-V64 -> 5858.1003 | X64: =S64-W64 -> 4747120.5 | Y64: =IF(Q64=1,V64,Y63+V64) -> 1295687.2 | Z64: =IF(Q64=1,W64,Z63+W64) -> 252879.48 | AA64: =$P$9*S64/12 -> 396.08155 | AB64: =$P$10*AA64 -> 39.608155 | AC64: =IF(P64>0,SUM(V64:V75),"-") -> 306811.06 | AD64: =IF(P64>0,SUM(W64:W75),"-") -> 72429.752 | AF64: =IF('[29]Proforma-Input'!$C$108="Yes",MONTH(O64)&YEAR(O64)=MONTH($C$9)&YEAR($C$9),0) -> 0 | AG64: 5
B65: =IFERROR(DATE(YEAR(B64),MONTH(B64)+1,DAY(B64)),"-") -> - | D65: 50 | E65: =1+E64 -> 2 | F65: =IFERROR(IF(B65<$C$9,IF('[29]Proforma-Input'!$C$108="Yes",K64,K64),0),) -> 0 | G65: =IFERROR(IF(D65=$C$7,K64,IF(AND($D$10="Yes",D65<=$C$10),I65,IF(F65>0,$C$8,))),) -> 0 | H65: =IFERROR(IF(B65<$C$9,IF('[29]Proforma-Input'!$C$108="Yes",H64,),0),) -> 0 | I65: =(H65/12)*F65 -> 0 | J65: =IF(D65=$C$7,0,G65-I65) -> 0 | K65: =IFERROR(F65-J65,) -> 0 | L65: =IF(C65>0,SUM(I65:I76),"-") -> - | M65: =IF(C65>0,SUM(J65:J76),"-") -> - | O65: =IFERROR(DATE(YEAR(O64),MONTH(O64)+1,DAY(O64)),"-") -> 47425 | Q65: =IF(S65>0,1+Q64,) -> 50 | R65: =1+R64 -> 2 | S65: =IF('[29]Proforma-Input'!$C$108="No",X64,IF(AF65=TRUE,$P$3,X64)) -> 4747120.5 | T65: =IF(AND($N$8="Yes",Q65<=$P$8),V65,IF(S65>0,$P$7,)) -> 31603.401 | U65: =$P$4 -> 0.065 | V65: =IF(S65>0,U65/12*S65,0) -> 25713.57 | W65: =T65-V65 -> 5889.8317 | X65: =S65-W65 -> 4741230.7 | Y65: =IF(Q65=1,V65,Y64+V65) -> 1321400.8 | Z65: =IF(Q65=1,W65,Z64+W65) -> 258769.31 | AA65: =$P$9*S65/12 -> 395.59338 | AB65: =$P$10*AA65 -> 39.559338 | AC65: =IF(P65>0,SUM(V65:V76),"-") -> - | AD65: =IF(P65>0,SUM(W65:W76),"-") -> - | AF65: =IF('[29]Proforma-Input'!$C$108="Yes",MONTH(O65)&YEAR(O65)=MONTH($C$9)&YEAR($C$9),0) -> 0 | AG65: 5
B66: =IFERROR(DATE(YEAR(B65),MONTH(B65)+1,DAY(B65)),"-") -> - | D66: 51 | E66: =1+E65 -> 3 | F66: =IFERROR(IF(B66<$C$9,IF('[29]Proforma-Input'!$C$108="Yes",K65,K65),0),) -> 0 | G66: =IFERROR(IF(D66=$C$7,K65,IF(AND($D$10="Yes",D66<=$C$10),I66,IF(F66>0,$C$8,))),) -> 0 | H66: =IFERROR(IF(B66<$C$9,IF('[29]Proforma-Input'!$C$108="Yes",H65,),0),) -> 0 | I66: =(H66/12)*F66 -> 0 | J66: =IF(D66=$C$7,0,G66-I66) -> 0 | K66: =IFERROR(F66-J66,) -> 0 | L66: =IF(C66>0,SUM(I66:I77),"-") -> - | M66: =IF(C66>0,SUM(J66:J77),"-") -> - | O66: =IFERROR(DATE(YEAR(O65),MONTH(O65)+1,DAY(O65)),"-") -> 47455 | Q66: =IF(S66>0,1+Q65,) -> 51 | R66: =1+R65 -> 3 | S66: =IF('[29]Proforma-Input'!$C$108="No",X65,IF(AF66=TRUE,$P$3,X65)) -> 4741230.7 | T66: =IF(AND($N$8="Yes",Q66<=$P$8),V66,IF(S66>0,$P$7,)) -> 31603.401 | U66: =$P$4 -> 0.065 | V66: =IF(S66>0,U66/12*S66,0) -> 25681.666 | W66: =T66-V66 -> 5921.7349 | X66: =S66-W66 -> 4735309 | Y66: =IF(Q66=1,V66,Y65+V66) -> 1347082.4 | Z66: =IF(Q66=1,W66,Z65+W66) -> 264691.04 | AA66: =$P$9*S66/12 -> 395.10256 | AB66: =$P$10*AA66 -> 39.510256 | AC66: =IF(P66>0,SUM(V66:V77),"-") -> - | AD66: =IF(P66>0,SUM(W66:W77),"-") -> - | AF66: =IF('[29]Proforma-Input'!$C$108="Yes",MONTH(O66)&YEAR(O66)=MONTH($C$9)&YEAR($C$9),0) -> 0 | AG66: 5
B67: =IFERROR(DATE(YEAR(B66),MONTH(B66)+1,DAY(B66)),"-") -> - | D67: 52 | E67: =1+E66 -> 4 | F67: =IFERROR(IF(B67<$C$9,IF('[29]Proforma-Input'!$C$108="Yes",K66,K66),0),) -> 0 | G67: =IFERROR(IF(D67=$C$7,K66,IF(AND($D$10="Yes",D67<=$C$10),I67,IF(F67>0,$C$8,))),) -> 0 | H67: =IFERROR(IF(B67<$C$9,IF('[29]Proforma-Input'!$C$108="Yes",H66,),0),) -> 0 | I67: =(H67/12)*F67 -> 0 | J67: =IF(D67=$C$7,0,G67-I67) -> 0 | K67: =IFERROR(F67-J67,) -> 0 | L67: =IF(C67>0,SUM(I67:I78),"-") -> - | M67: =IF(C67>0,SUM(J67:J78),"-") -> - | O67: =IFERROR(DATE(YEAR(O66),MONTH(O66)+1,DAY(O66)),"-") -> 47486 | Q67: =IF(S67>0,1+Q66,) -> 52 | R67: =1+R66 -> 4 | S67: =IF('[29]Proforma-Input'!$C$108="No",X66,IF(AF67=TRUE,$P$3,X66)) -> 4735309 | T67: =IF(AND($N$8="Yes",Q67<=$P$8),V67,IF(S67>0,$P$7,)) -> 31603.401 | U67: =$P$4 -> 0.065 | V67: =IF(S67>0,U67/12*S67,0) -> 25649.59 | W67: =T67-V67 -> 5953.811 | X67: =S67-W67 -> 4729355.1 | Y67: =IF(Q67=1,V67,Y66+V67) -> 1372732 | Z67: =IF(Q67=1,W67,Z66+W67) -> 270644.85 | AA67: =$P$9*S67/12 -> 394.60908 | AB67: =$P$10*AA67 -> 39.460908 | AC67: =IF(P67>0,SUM(V67:V78),"-") -> - | AD67: =IF(P67>0,SUM(W67:W78),"-") -> - | AF67: =IF('[29]Proforma-Input'!$C$108="Yes",MONTH(O67)&YEAR(O67)=MONTH($C$9)&YEAR($C$9),0) -> 0 | AG67: 5
B68: =IFERROR(DATE(YEAR(B67),MONTH(B67)+1,DAY(B67)),"-") -> - | D68: 53 | E68: =1+E67 -> 5 | F68: =IFERROR(IF(B68<$C$9,IF('[29]Proforma-Input'!$C$108="Yes",K67,K67),0),) -> 0 | G68: =IFERROR(IF(D68=$C$7,K67,IF(AND($D$10="Yes",D68<=$C$10),I68,IF(F68>0,$C$8,))),) -> 0 | H68: =IFERROR(IF(B68<$C$9,IF('[29]Proforma-Input'!$C$108="Yes",H67,),0),) -> 0 | I68: =(H68/12)*F68 -> 0 | J68: =IF(D68=$C$7,0,G68-I68) -> 0 | K68: =IFERROR(F68-J68,) -> 0 | L68: =IF(C68>0,SUM(I68:I79),"-") -> - | M68: =IF(C68>0,SUM(J68:J79),"-") -> - | O68: =IFERROR(DATE(YEAR(O67),MONTH(O67)+1,DAY(O67)),"-") -> 47517 | Q68: =IF(S68>0,1+Q67,) -> 53 | R68: =1+R67 -> 5 | S68: =IF('[29]Proforma-Input'!$C$108="No",X67,IF(AF68=TRUE,$P$3,X67)) -> 4729355.1 | T68: =IF(AND($N$8="Yes",Q68<=$P$8),V68,IF(S68>0,$P$7,)) -> 31603.401 | U68: =$P$4 -> 0.065 | V68: =IF(S68>0,U68/12*S68,0) -> 25617.34 | W68: =T68-V68 -> 5986.0608 | X68: =S68-W68 -> 4723369.1 | Y68: =IF(Q68=1,V68,Y67+V68) -> 1398349.3 | Z68: =IF(Q68=1,W68,Z67+W68) -> 276630.91 | AA68: =$P$9*S68/12 -> 394.11293 | AB68: =$P$10*AA68 -> 39.411293 | AC68: =IF(P68>0,SUM(V68:V79),"-") -> - | AD68: =IF(P68>0,SUM(W68:W79),"-") -> - | AF68: =IF('[29]Proforma-Input'!$C$108="Yes",MONTH(O68)&YEAR(O68)=MONTH($C$9)&YEAR($C$9),0) -> 0 | AG68: 5
B69: =IFERROR(DATE(YEAR(B68),MONTH(B68)+1,DAY(B68)),"-") -> - | D69: 54 | E69: =1+E68 -> 6 | F69: =IFERROR(IF(B69<$C$9,IF('[29]Proforma-Input'!$C$108="Yes",K68,K68),0),) -> 0 | G69: =IFERROR(IF(D69=$C$7,K68,IF(AND($D$10="Yes",D69<=$C$10),I69,IF(F69>0,$C$8,))),) -> 0 | H69: =IFERROR(IF(B69<$C$9,IF('[29]Proforma-Input'!$C$108="Yes",H68,),0),) -> 0 | I69: =(H69/12)*F69 -> 0 | J69: =IF(D69=$C$7,0,G69-I69) -> 0 | K69: =IFERROR(F69-J69,) -> 0 | L69: =IF(C69>0,SUM(I69:I80),"-") -> - | M69: =IF(C69>0,SUM(J69:J80),"-") -> - | O69: =IFERROR(DATE(YEAR(O68),MONTH(O68)+1,DAY(O68)),"-") -> 47545 | Q69: =IF(S69>0,1+Q68,) -> 54 | R69: =1+R68 -> 6 | S69: =IF('[29]Proforma-Input'!$C$108="No",X68,IF(AF69=TRUE,$P$3,X68)) -> 4723369.1 | T69: =IF(AND($N$8="Yes",Q69<=$P$8),V69,IF(S69>0,$P$7,)) -> 31603.401 | U69: =$P$4 -> 0.065 | V69: =IF(S69>0,U69/12*S69,0) -> 25584.916 | W69: =T69-V69 -> 6018.4853 | X69: =S69-W69 -> 4717350.6 | Y69: =IF(Q69=1,V69,Y68+V69) -> 1423934.3 | Z69: =IF(Q69=1,W69,Z68+W69) -> 282649.4 | AA69: =$P$9*S69/12 -> 393.61409 | AB69: =$P$10*AA69 -> 39.361409 | AC69: =IF(P69>0,SUM(V69:V80),"-") -> - | AD69: =IF(P69>0,SUM(W69:W80),"-") -> - | AF69: =IF('[29]Proforma-Input'!$C$108="Yes",MONTH(O69)&YEAR(O69)=MONTH($C$9)&YEAR($C$9),0) -> 0 | AG69: 5
B70: =IFERROR(DATE(YEAR(B69),MONTH(B69)+1,DAY(B69)),"-") -> - | D70: 55 | E70: =1+E69 -> 7 | F70: =IFERROR(IF(B70<$C$9,IF('[29]Proforma-Input'!$C$108="Yes",K69,K69),0),) -> 0 | G70: =IFERROR(IF(D70=$C$7,K69,IF(AND($D$10="Yes",D70<=$C$10),I70,IF(F70>0,$C$8,))),) -> 0 | H70: =IFERROR(IF(B70<$C$9,IF('[29]Proforma-Input'!$C$108="Yes",H69,),0),) -> 0 | I70: =(H70/12)*F70 -> 0 | J70: =IF(D70=$C$7,0,G70-I70) -> 0 | K70: =IFERROR(F70-J70,) -> 0 | L70: =IF(C70>0,SUM(I70:I81),"-") -> - | M70: =IF(C70>0,SUM(J70:J81),"-") -> - | O70: =IFERROR(DATE(YEAR(O69),MONTH(O69)+1,DAY(O69)),"-") -> 47576 | Q70: =IF(S70>0,1+Q69,) -> 55 | R70: =1+R69 -> 7 | S70: =IF('[29]Proforma-Input'!$C$108="No",X69,IF(AF70=TRUE,$P$3,X69)) -> 4717350.6 | T70: =IF(AND($N$8="Yes",Q70<=$P$8),V70,IF(S70>0,$P$7,)) -> 31603.401 | U70: =$P$4 -> 0.065 | V70: =IF(S70>0,U70/12*S70,0) -> 25552.316 | W70: =T70-V70 -> 6051.0854 | X70: =S70-W70 -> 4711299.5 | Y70: =IF(Q70=1,V70,Y69+V70) -> 1449486.6 | Z70: =IF(Q70=1,W70,Z69+W70) -> 288700.48 | AA70: =$P$9*S70/12 -> 393.11255 | AB70: =$P$10*AA70 -> 39.311255 | AC70: =IF(P70>0,SUM(V70:V81),"-") -> - | AD70: =IF(P70>0,SUM(W70:W81),"-") -> - | AF70: =IF('[29]Proforma-Input'!$C$108="Yes",MONTH(O70)&YEAR(O70)=MONTH($C$9)&YEAR($C$9),0) -> 0 | AG70: 5
B71: =IFERROR(DATE(YEAR(B70),MONTH(B70)+1,DAY(B70)),"-") -> - | D71: 56 | E71: =1+E70 -> 8 | F71: =IFERROR(IF(B71<$C$9,IF('[29]Proforma-Input'!$C$108="Yes",K70,K70),0),) -> 0 | G71: =IFERROR(IF(D71=$C$7,K70,IF(AND($D$10="Yes",D71<=$C$10),I71,IF(F71>0,$C$8,))),) -> 0 | H71: =IFERROR(IF(B71<$C$9,IF('[29]Proforma-Input'!$C$108="Yes",H70,),0),) -> 0 | I71: =(H71/12)*F71 -> 0 | J71: =IF(D71=$C$7,0,G71-I71) -> 0 | K71: =IFERROR(F71-J71,) -> 0 | L71: =IF(C71>0,SUM(I71:I82),"-") -> - | M71: =IF(C71>0,SUM(J71:J82),"-") -> - | O71: =IFERROR(DATE(YEAR(O70),MONTH(O70)+1,DAY(O70)),"-") -> 47606 | Q71: =IF(S71>0,1+Q70,) -> 56 | R71: =1+R70 -> 8 | S71: =IF('[29]Proforma-Input'!$C$108="No",X70,IF(AF71=TRUE,$P$3,X70)) -> 4711299.5 | T71: =IF(AND($N$8="Yes",Q71<=$P$8),V71,IF(S71>0,$P$7,)) -> 31603.401 | U71: =$P$4 -> 0.065 | V71: =IF(S71>0,U71/12*S71,0) -> 25519.539 | W71: =T71-V71 -> 6083.8621 | X71: =S71-W71 -> 4705215.7 | Y71: =IF(Q71=1,V71,Y70+V71) -> 1475006.1 | Z71: =IF(Q71=1,W71,Z70+W71) -> 294784.35 | AA71: =$P$9*S71/12 -> 392.60829 | AB71: =$P$10*AA71 -> 39.260829 | AC71: =IF(P71>0,SUM(V71:V82),"-") -> - | AD71: =IF(P71>0,SUM(W71:W82),"-") -> - | AF71: =IF('[29]Proforma-Input'!$C$108="Yes",MONTH(O71)&YEAR(O71)=MONTH($C$9)&YEAR($C$9),0) -> 0 | AG71: 5
B72: =IFERROR(DATE(YEAR(B71),MONTH(B71)+1,DAY(B71)),"-") -> - | D72: 57 | E72: =1+E71 -> 9 | F72: =IFERROR(IF(B72<$C$9,IF('[29]Proforma-Input'!$C$108="Yes",K71,K71),0),) -> 0 | G72: =IFERROR(IF(D72=$C$7,K71,IF(AND($D$10="Yes",D72<=$C$10),I72,IF(F72>0,$C$8,))),) -> 0 | H72: =IFERROR(IF(B72<$C$9,IF('[29]Proforma-Input'!$C$108="Yes",H71,),0),) -> 0 | I72: =(H72/12)*F72 -> 0 | J72: =IF(D72=$C$7,0,G72-I72) -> 0 | K72: =IFERROR(F72-J72,) -> 0 | L72: =IF(C72>0,SUM(I72:I83),"-") -> - | M72: =IF(C72>0,SUM(J72:J83),"-") -> - | O72: =IFERROR(DATE(YEAR(O71),MONTH(O71)+1,DAY(O71)),"-") -> 47637 | Q72: =IF(S72>0,1+Q71,) -> 57 | R72: =1+R71 -> 9 | S72: =IF('[29]Proforma-Input'!$C$108="No",X71,IF(AF72=TRUE,$P$3,X71)) -> 4705215.7 | T72: =IF(AND($N$8="Yes",Q72<=$P$8),V72,IF(S72>0,$P$7,)) -> 31603.401 | U72: =$P$4 -> 0.065 | V72: =IF(S72>0,U72/12*S72,0) -> 25486.585 | W72: =T72-V72 -> 6116.8164 | X72: =S72-W72 -> 4699098.8 | Y72: =IF(Q72=1,V72,Y71+V72) -> 1500492.7 | Z72: =IF(Q72=1,W72,Z71+W72) -> 300901.16 | AA72: =$P$9*S72/12 -> 392.1013 | AB72: =$P$10*AA72 -> 39.21013 | AC72: =IF(P72>0,SUM(V72:V83),"-") -> - | AD72: =IF(P72>0,SUM(W72:W83),"-") -> - | AF72: =IF('[29]Proforma-Input'!$C$108="Yes",MONTH(O72)&YEAR(O72)=MONTH($C$9)&YEAR($C$9),0) -> 0 | AG72: 5
B73: =IFERROR(DATE(YEAR(B72),MONTH(B72)+1,DAY(B72)),"-") -> - | D73: 58 | E73: =1+E72 -> 10 | F73: =IFERROR(IF(B73<$C$9,IF('[29]Proforma-Input'!$C$108="Yes",K72,K72),0),) -> 0 | G73: =IFERROR(IF(D73=$C$7,K72,IF(AND($D$10="Yes",D73<=$C$10),I73,IF(F73>0,$C$8,))),) -> 0 | H73: =IFERROR(IF(B73<$C$9,IF('[29]Proforma-Input'!$C$108="Yes",H72,),0),) -> 0 | I73: =(H73/12)*F73 -> 0 | J73: =IF(D73=$C$7,0,G73-I73) -> 0 | K73: =IFERROR(F73-J73,) -> 0 | L73: =IF(C73>0,SUM(I73:I84),"-") -> - | M73: =IF(C73>0,SUM(J73:J84),"-") -> - | O73: =IFERROR(DATE(YEAR(O72),MONTH(O72)+1,DAY(O72)),"-") -> 47667 | Q73: =IF(S73>0,1+Q72,) -> 58 | R73: =1+R72 -> 10 | S73: =IF('[29]Proforma-Input'!$C$108="No",X72,IF(AF73=TRUE,$P$3,X72)) -> 4699098.8 | T73: =IF(AND($N$8="Yes",Q73<=$P$8),V73,IF(S73>0,$P$7,)) -> 31603.401 | U73: =$P$4 -> 0.065 | V73: =IF(S73>0,U73/12*S73,0) -> 25453.452 | W73: =T73-V73 -> 6149.9491 | X73: =S73-W73 -> 4692948.9 | Y73: =IF(Q73=1,V73,Y72+V73) -> 1525946.2 | Z73: =IF(Q73=1,W73,Z72+W73) -> 307051.11 | AA73: =$P$9*S73/12 -> 391.59157 | AB73: =$P$10*AA73 -> 39.159157 | AC73: =IF(P73>0,SUM(V73:V84),"-") -> - | AD73: =IF(P73>0,SUM(W73:W84),"-") -> - | AF73: =IF('[29]Proforma-Input'!$C$108="Yes",MONTH(O73)&YEAR(O73)=MONTH($C$9)&YEAR($C$9),0) -> 0 | AG73: 5
B74: =IFERROR(DATE(YEAR(B73),MONTH(B73)+1,DAY(B73)),"-") -> - | D74: 59 | E74: =1+E73 -> 11 | F74: =IFERROR(IF(B74<$C$9,IF('[29]Proforma-Input'!$C$108="Yes",K73,K73),0),) -> 0 | G74: =IFERROR(IF(D74=$C$7,K73,IF(AND($D$10="Yes",D74<=$C$10),I74,IF(F74>0,$C$8,))),) -> 0 | H74: =IFERROR(IF(B74<$C$9,IF('[29]Proforma-Input'!$C$108="Yes",H73,),0),) -> 0 | I74: =(H74/12)*F74 -> 0 | J74: =IF(D74=$C$7,0,G74-I74) -> 0 | K74: =IFERROR(F74-J74,) -> 0 | L74: =IF(C74>0,SUM(I74:I85),"-") -> - | M74: =IF(C74>0,SUM(J74:J85),"-") -> - | O74: =IFERROR(DATE(YEAR(O73),MONTH(O73)+1,DAY(O73)),"-") -> 47698 | Q74: =IF(S74>0,1+Q73,) -> 59 | R74: =1+R73 -> 11 | S74: =IF('[29]Proforma-Input'!$C$108="No",X73,IF(AF74=TRUE,$P$3,X73)) -> 4692948.9 | T74: =IF(AND($N$8="Yes",Q74<=$P$8),V74,IF(S74>0,$P$7,)) -> 31603.401 | U74: =$P$4 -> 0.065 | V74: =IF(S74>0,U74/12*S74,0) -> 25420.14 | W74: =T74-V74 -> 6183.2614 | X74: =S74-W74 -> 4686765.6 | Y74: =IF(Q74=1,V74,Y73+V74) -> 1551366.3 | Z74: =IF(Q74=1,W74,Z73+W74) -> 313234.37 | AA74: =$P$9*S74/12 -> 391.07907 | AB74: =$P$10*AA74 -> 39.107907 | AC74: =IF(P74>0,SUM(V74:V85),"-") -> - | AD74: =IF(P74>0,SUM(W74:W85),"-") -> - | AF74: =IF('[29]Proforma-Input'!$C$108="Yes",MONTH(O74)&YEAR(O74)=MONTH($C$9)&YEAR($C$9),0) -> 0 | AG74: 5
B75: =IFERROR(DATE(YEAR(B74),MONTH(B74)+1,DAY(B74)),"-") -> - | D75: 60 | E75: =1+E74 -> 12 | F75: =IFERROR(IF(B75<$C$9,IF('[29]Proforma-Input'!$C$108="Yes",K74,K74),0),) -> 0 | G75: =IFERROR(IF(D75=$C$7,K74,IF(AND($D$10="Yes",D75<=$C$10),I75,IF(F75>0,$C$8,))),) -> 0 | H75: =IFERROR(IF(B75<$C$9,IF('[29]Proforma-Input'!$C$108="Yes",H74,),0),) -> 0 | I75: =(H75/12)*F75 -> 0 | J75: =IF(D75=$C$7,0,G75-I75) -> 0 | K75: =IFERROR(F75-J75,) -> 0 | L75: =IF(C75>0,SUM(I75:I86),"-") -> - | M75: =IF(C75>0,SUM(J75:J86),"-") -> - | O75: =IFERROR(DATE(YEAR(O74),MONTH(O74)+1,DAY(O74)),"-") -> 47729 | Q75: =IF(S75>0,1+Q74,) -> 60 | R75: =1+R74 -> 12 | S75: =IF('[29]Proforma-Input'!$C$108="No",X74,IF(AF75=TRUE,$P$3,X74)) -> 4686765.6 | T75: =IF(AND($N$8="Yes",Q75<=$P$8),V75,IF(S75>0,$P$7,)) -> 31603.401 | U75: =$P$4 -> 0.065 | V75: =IF(S75>0,U75/12*S75,0) -> 25386.647 | W75: =T75-V75 -> 6216.754 | X75: =S75-W75 -> 4680548.9 | Y75: =IF(Q75=1,V75,Y74+V75) -> 1576752.9 | Z75: =IF(Q75=1,W75,Z74+W75) -> 319451.13 | AA75: =$P$9*S75/12 -> 390.5638 | AB75: =$P$10*AA75 -> 39.05638 | AC75: =IF(P75>0,SUM(V75:V86),"-") -> - | AD75: =IF(P75>0,SUM(W75:W86),"-") -> - | AF75: =IF('[29]Proforma-Input'!$C$108="Yes",MONTH(O75)&YEAR(O75)=MONTH($C$9)&YEAR($C$9),0) -> 0 | AG75: 5
B76: =IFERROR(DATE(YEAR(B75),MONTH(B75)+1,DAY(B75)),"-") -> - | C76: 6 | D76: 61 | E76: 1 | F76: =IFERROR(IF(B76<$C$9,IF('[29]Proforma-Input'!$C$108="Yes",K75,K75),0),) -> 0 | G76: =IFERROR(IF(D76=$C$7,K75,IF(AND($D$10="Yes",D76<=$C$10),I76,IF(F76>0,$C$8,))),) -> 0 | H76: =IFERROR(IF(B76<$C$9,IF('[29]Proforma-Input'!$C$108="Yes",H75,),0),) -> 0 | I76: =(H76/12)*F76 -> 0 | J76: =IF(D76=$C$7,0,G76-I76) -> 0 | K76: =IFERROR(F76-J76,) -> 0 | L76: =IF(C76>0,SUM(I76:I87),"-") -> 0 | M76: =IF(C76>0,SUM(J76:J87),"-") -> 0 | O76: =IFERROR(DATE(YEAR(O75),MONTH(O75)+1,DAY(O75)),"-") -> 47759 | P76: 6 | Q76: =IF(S76>0,1+Q75,) -> 61 | R76: 1 | S76: =IF('[29]Proforma-Input'!$C$108="No",X75,IF(AF76=TRUE,$P$3,X75)) -> 4680548.9 | T76: =IF(AND($N$8="Yes",Q76<=$P$8),V76,IF(S76>0,$P$7,)) -> 31603.401 | U76: =$P$4 -> 0.065 | V76: =IF(S76>0,U76/12*S76,0) -> 25352.973 | W76: =T76-V76 -> 6250.4281 | X76: =S76-W76 -> 4674298.4 | Y76: =IF(Q76=1,V76,Y75+V76) -> 1602105.9 | Z76: =IF(Q76=1,W76,Z75+W76) -> 325701.56 | AA76: =$P$9*S76/12 -> 390.04574 | AB76: =$P$10*AA76 -> 39.004574 | AC76: =IF(P76>0,SUM(V76:V87),"-") -> 301960.31 | AD76: =IF(P76>0,SUM(W76:W87),"-") -> 77280.507 | AF76: =IF('[29]Proforma-Input'!$C$108="Yes",MONTH(O76)&YEAR(O76)=MONTH($C$9)&YEAR($C$9),0) -> 0 | AG76: 6
B77: =IFERROR(DATE(YEAR(B76),MONTH(B76)+1,DAY(B76)),"-") -> - | D77: 62 | E77: =1+E76 -> 2 | F77: =IFERROR(IF(B77<$C$9,IF('[29]Proforma-Input'!$C$108="Yes",K76,K76),0),) -> 0 | G77: =IFERROR(IF(D77=$C$7,K76,IF(AND($D$10="Yes",D77<=$C$10),I77,IF(F77>0,$C$8,))),) -> 0 | H77: =IFERROR(IF(B77<$C$9,IF('[29]Proforma-Input'!$C$108="Yes",H76,),0),) -> 0 | I77: =(H77/12)*F77 -> 0 | J77: =IF(D77=$C$7,0,G77-I77) -> 0 | K77: =IFERROR(F77-J77,) -> 0 | L77: =IF(C77>0,SUM(I77:I88),"-") -> - | M77: =IF(C77>0,SUM(J77:J88),"-") -> - | O77: =IFERROR(DATE(YEAR(O76),MONTH(O76)+1,DAY(O76)),"-") -> 47790 | Q77: =IF(S77>0,1+Q76,) -> 62 | R77: =1+R76 -> 2 | S77: =IF('[29]Proforma-Input'!$C$108="No",X76,IF(AF77=TRUE,$P$3,X76)) -> 4674298.4 | T77: =IF(AND($N$8="Yes",Q77<=$P$8),V77,IF(S77>0,$P$7,)) -> 31603.401 | U77: =$P$4 -> 0.065 | V77: =IF(S77>0,U77/12*S77,0) -> 25319.117 | W77: =T77-V77 -> 6284.2846 | X77: =S77-W77 -> 4668014.2 | Y77: =IF(Q77=1,V77,Y76+V77) -> 1627425 | Z77: =IF(Q77=1,W77,Z76+W77) -> 331985.84 | AA77: =$P$9*S77/12 -> 389.52487 | AB77: =$P$10*AA77 -> 38.952487 | AC77: =IF(P77>0,SUM(V77:V88),"-") -> - | AD77: =IF(P77>0,SUM(W77:W88),"-") -> - | AF77: =IF('[29]Proforma-Input'!$C$108="Yes",MONTH(O77)&YEAR(O77)=MONTH($C$9)&YEAR($C$9),0) -> 0 | AG77: 6
B78: =IFERROR(DATE(YEAR(B77),MONTH(B77)+1,DAY(B77)),"-") -> - | D78: 63 | E78: =1+E77 -> 3 | F78: =IFERROR(IF(B78<$C$9,IF('[29]Proforma-Input'!$C$108="Yes",K77,K77),0),) -> 0 | G78: =IFERROR(IF(D78=$C$7,K77,IF(AND($D$10="Yes",D78<=$C$10),I78,IF(F78>0,$C$8,))),) -> 0 | H78: =IFERROR(IF(B78<$C$9,IF('[29]Proforma-Input'!$C$108="Yes",H77,),0),) -> 0 | I78: =(H78/12)*F78 -> 0 | J78: =IF(D78=$C$7,0,G78-I78) -> 0 | K78: =IFERROR(F78-J78,) -> 0 | L78: =IF(C78>0,SUM(I78:I89),"-") -> - | M78: =IF(C78>0,SUM(J78:J89),"-") -> - | O78: =IFERROR(DATE(YEAR(O77),MONTH(O77)+1,DAY(O77)),"-") -> 47820 | Q78: =IF(S78>0,1+Q77,) -> 63 | R78: =1+R77 -> 3 | S78: =IF('[29]Proforma-Input'!$C$108="No",X77,IF(AF78=TRUE,$P$3,X77)) -> 4668014.2 | T78: =IF(AND($N$8="Yes",Q78<=$P$8),V78,IF(S78>0,$P$7,)) -> 31603.401 | U78: =$P$4 -> 0.065 | V78: =IF(S78>0,U78/12*S78,0) -> 25285.077 | W78: =T78-V78 -> 6318.3245 | X78: =S78-W78 -> 4661695.8 | Y78: =IF(Q78=1,V78,Y77+V78) -> 1652710.1 | Z78: =IF(Q78=1,W78,Z77+W78) -> 338304.17 | AA78: =$P$9*S78/12 -> 389.00118 | AB78: =$P$10*AA78 -> 38.900118 | AC78: =IF(P78>0,SUM(V78:V89),"-") -> - | AD78: =IF(P78>0,SUM(W78:W89),"-") -> - | AF78: =IF('[29]Proforma-Input'!$C$108="Yes",MONTH(O78)&YEAR(O78)=MONTH($C$9)&YEAR($C$9),0) -> 0 | AG78: 6
